{
  "type": "Feature",
  "properties": {
    "gn:admin1_code":"22",
    "gn:asciiname":"Corbadzii",
    "gn:country_code":"MK",
    "gn:dem":808,
    "gn:feature_class":"P",
    "gn:feature_code":"PPL",
    "gn:name":"\u010corbad\u017eii",
    "gn:population":0,
    "gn:timezone":"Europe/Skopje",
    "iso:country":"MK",
    "name:mkd_x_preferred":[
        "\u010corbad\u017eii"
    ],
    "name:mkd_x_variant":[
        "\u0427\u043e\u0440\u0431\u0430\u045f\u0438\u0438"
    ],
    "wof:name":"Corbadzii",
    "wof:placetype":"locality"
},
  "geometry": {"coordinates":[22.79925,41.85548],"type":"Point"}
}