{
  "type": "Feature",
  "properties": {
    "gn:admin1_code":"D4",
    "gn:asciiname":"Padaliste",
    "gn:country_code":"MK",
    "gn:dem":888,
    "gn:feature_class":"P",
    "gn:feature_code":"PPL",
    "gn:name":"Padali\u0161te",
    "gn:population":0,
    "gn:timezone":"Europe/Skopje",
    "iso:country":"MK",
    "name:mkd_x_preferred":[
        "Padali\u0161te"
    ],
    "name:mkd_x_variant":[
        "\u041f\u0430\u0434\u0430\u043b\u0438\u0448\u0442\u0435"
    ],
    "wof:name":"Padaliste",
    "wof:placetype":"locality"
},
  "geometry": {"coordinates":[20.97583,41.68611],"type":"Point"}
}