{
  "type": "Feature",
  "properties": {
    "gn:admin1_code":"33",
    "gn:asciiname":"Davidovo",
    "gn:country_code":"MK",
    "gn:dem":88,
    "gn:feature_class":"P",
    "gn:feature_code":"PPL",
    "gn:name":"Davidovo",
    "gn:population":0,
    "gn:timezone":"Europe/Skopje",
    "iso:country":"MK",
    "name:bul_x_preferred":[
        "\u0414\u0430\u0432\u0438\u0434\u043e\u0432\u043e"
    ],
    "name:mkd_x_preferred":[
        "Davidovo"
    ],
    "name:mkd_x_variant":[
        "\u0414\u0430\u0432\u0438\u0434\u043e\u0432\u043e"
    ],
    "name:ron_x_preferred":[
        "Davidovo"
    ],
    "name:rus_x_preferred":[
        "\u0414\u0430\u0432\u0438\u0434\u043e\u0432\u043e"
    ],
    "name:srp_x_preferred":[
        "\u0414\u0430\u0432\u0438\u0434\u043e\u0432\u043e"
    ],
    "name:ukr_x_preferred":[
        "\u0414\u0430\u0432\u0438\u0434\u043e\u0432\u043e"
    ],
    "wof:name":"Davidovo",
    "wof:placetype":"locality"
},
  "geometry": {"coordinates":[22.43274,41.33204],"type":"Point"}
}