{
  "type": "Feature",
  "properties": {
    "gn:admin1_code":"46",
    "gn:asciiname":"Nebojani",
    "gn:country_code":"MK",
    "gn:dem":1305,
    "gn:feature_class":"P",
    "gn:feature_code":"PPLL",
    "gn:name":"Nebojani",
    "gn:population":0,
    "gn:timezone":"Europe/Skopje",
    "iso:country":"MK",
    "name:mkd_x_preferred":[
        "\u041d\u0435\u0431\u043e\u0458\u0430\u043d\u0438"
    ],
    "name:und_x_variant":[
        "Nebojan",
        "Nebojani"
    ],
    "wof:name":"Nebojani",
    "wof:placetype":"locality"
},
  "geometry": {"coordinates":[22.46544,42.06967],"type":"Point"}
}