{
  "type": "Feature",
  "properties": {
    "gn:admin1_code":"E6",
    "gn:asciiname":"Visni",
    "gn:country_code":"MK",
    "gn:dem":1061,
    "gn:feature_class":"P",
    "gn:feature_code":"PPL",
    "gn:name":"Vi\u0161ni",
    "gn:population":0,
    "gn:timezone":"Europe/Skopje",
    "iso:country":"MK",
    "name:mkd_x_preferred":[
        "\u0412\u0438\u0448\u043d\u0438"
    ],
    "name:und_x_variant":[
        "Vi\u0161nje",
        "Vi\u0161ni"
    ],
    "wof:name":"Visni",
    "wof:placetype":"locality"
},
  "geometry": {"coordinates":[20.59889,41.19333],"type":"Point"}
}