{
  "type": "Feature",
  "properties": {
    "gn:country":"MK",
    "gn:fcode":"PPL",
    "gn:population":263,
    "iso:country":"MK",
    "name:bul_x_preferred":[
        "\u041d\u043e\u0432\u043e\u0441\u0435\u043b\u0430\u043d\u0438"
    ],
    "name:ceb_x_preferred":[
        "Novoselani"
    ],
    "name:eng_x_preferred":[
        "Novoselani"
    ],
    "name:fra_x_preferred":[
        "Novoselani"
    ],
    "name:hun_x_preferred":[
        "Novoszelani"
    ],
    "name:mkd_x_preferred":[
        "\u041d\u043e\u0432\u043e\u0441\u0435\u043b\u0430\u043d\u0438"
    ],
    "name:nan_x_preferred":[
        "Novoselani"
    ],
    "name:sqi_x_preferred":[
        "Novoseljani"
    ],
    "name:srp_x_preferred":[
        "\u041d\u043e\u0432\u043e\u0441\u0435\u0459\u0430\u043d\u0438"
    ],
    "name:swe_x_preferred":[
        "Novoselani"
    ],
    "name:und_x_variant":[
        "Novosljani"
    ],
    "qs:name":"Novoselani",
    "qs:photos_9r":0,
    "qs:photos_sr":0,
    "qs:pop_sr":"2",
    "wd:wordcount":32,
    "wof:name":"Novoselani",
    "wof:placetype":"locality",
    "wof:population":263
},
  "geometry": {"coordinates":[21.43333,41.40361],"type":"Point"}
}