{
  "type": "Feature",
  "properties": {
    "gn:country":"MK",
    "gn:fcode":"PPL",
    "gn:pop":156,
    "iso:country":"MK",
    "name:mkd_x_preferred":[
        "\u0414\u0435\u0458\u043a\u043e\u0432\u0435\u0446"
    ],
    "name:unk_x_variant":[
        "Dekovec"
    ],
    "qs:name":"Dejkovec",
    "qs:photos_9r":0,
    "qs:photos_sr":0,
    "qs:pop_sr":"1",
    "wd:wordcount":115,
    "wof:name":"Dejkovec",
    "wof:placetype":"locality",
    "wof:population":156
},
  "geometry": {"coordinates":[21.56667,41.79194],"type":"Point"}
}