{
  "type": "Feature",
  "properties": {
    "gn:admin1_code":"52",
    "gn:asciiname":"Lingorovci",
    "gn:country_code":"MK",
    "gn:dem":1116,
    "gn:feature_class":"P",
    "gn:feature_code":"PPL",
    "gn:name":"Lingorovci",
    "gn:population":0,
    "gn:timezone":"Europe/Skopje",
    "iso:country":"MK",
    "name:mkd_x_preferred":[
        "Lingorovci"
    ],
    "name:mkd_x_variant":[
        "\u041b\u0438\u043d\u0433\u043e\u0440\u043e\u0432\u0446\u0438"
    ],
    "wof:name":"Lingorovci",
    "wof:placetype":"locality"
},
  "geometry": {"coordinates":[22.38087,42.29483],"type":"Point"}
}