{
  "type": "Feature",
  "properties": {
    "gn:admin1_code":"85",
    "gn:asciiname":"Kotarina Maala",
    "gn:country_code":"MK",
    "gn:dem":566,
    "gn:feature_class":"P",
    "gn:feature_code":"PPL",
    "gn:name":"Kotarina Maala",
    "gn:population":0,
    "gn:timezone":"Europe/Skopje",
    "iso:country":"MK",
    "name:mkd_x_preferred":[
        "Kotarina Maala"
    ],
    "name:mkd_x_variant":[
        "\u041a\u043e\u0442\u0430\u0440\u0438\u043d\u0430 \u041c\u0430\u0430\u043b\u0430"
    ],
    "wof:name":"Kotarina Maala",
    "wof:placetype":"locality"
},
  "geometry": {"coordinates":[22.12804,42.14122],"type":"Point"}
}