{
  "type": "Feature",
  "properties": {
    "gn:admin1_code":"E1",
    "gn:asciiname":"Dobroveni",
    "gn:country_code":"MK",
    "gn:dem":582,
    "gn:feature_class":"P",
    "gn:feature_code":"PPL",
    "gn:name":"Dobroveni",
    "gn:population":0,
    "gn:timezone":"Europe/Skopje",
    "iso:country":"MK",
    "name:mkd_x_preferred":[
        "\u0414\u043e\u0431\u0440\u043e\u0432\u0435\u043d\u0438"
    ],
    "name:und_x_variant":[
        "Dobroven"
    ],
    "wof:name":"Dobroveni",
    "wof:placetype":"locality"
},
  "geometry": {"coordinates":[21.60225,40.94992],"type":"Point"}
}