{
  "type": "Feature",
  "properties": {
    "gn:admin1_code":"E5",
    "gn:asciiname":"Kurtamzali",
    "gn:country_code":"MK",
    "gn:dem":331,
    "gn:feature_class":"P",
    "gn:feature_code":"PPL",
    "gn:name":"Kurtamzali",
    "gn:population":0,
    "gn:timezone":"Europe/Skopje",
    "iso:country":"MK",
    "name:mkd_x_preferred":[
        "Kurtamzali"
    ],
    "name:mkd_x_variant":[
        "\u041a\u0443\u0440\u0442\u0430\u043c\u0437\u0430\u043b\u0438"
    ],
    "wof:name":"Kurtamzali",
    "wof:placetype":"locality"
},
  "geometry": {"coordinates":[22.69437000000001,41.29471],"type":"Point"}
}