{
  "type": "Feature",
  "properties": {
    "gn:admin1_code":"E4",
    "gn:asciiname":"Sence",
    "gn:country_code":"MK",
    "gn:dem":1111,
    "gn:feature_class":"P",
    "gn:feature_code":"PPL",
    "gn:name":"Sence",
    "gn:population":0,
    "gn:timezone":"Europe/Skopje",
    "iso:country":"MK",
    "name:mkd_x_preferred":[
        "Sence"
    ],
    "name:mkd_x_variant":[
        "\u0421\u0435\u043d\u0446\u0435"
    ],
    "wof:name":"Sence",
    "wof:placetype":"locality"
},
  "geometry": {"coordinates":[20.65815,41.68262],"type":"Point"}
}