{
  "type": "Feature",
  "properties": {
    "gn:admin1_code":"46",
    "gn:asciiname":"Lisje Brdo",
    "gn:country_code":"MK",
    "gn:dem":1009,
    "gn:feature_class":"P",
    "gn:feature_code":"PPL",
    "gn:name":"Lisje Brdo",
    "gn:population":0,
    "gn:timezone":"Europe/Skopje",
    "iso:country":"MK",
    "name:mkd_x_preferred":[
        "Lisje Brdo"
    ],
    "name:mkd_x_variant":[
        "\u041b\u0438\u0441\u0458\u0435 \u0411\u0440\u0434\u043e"
    ],
    "wof:name":"Lisje Brdo",
    "wof:placetype":"locality"
},
  "geometry": {"coordinates":[22.40333,42.035],"type":"Point"}
}