{
  "type": "Feature",
  "properties": {
    "gn:admin1_code":"22",
    "gn:asciiname":"Bozanska Maala",
    "gn:country_code":"MK",
    "gn:dem":589,
    "gn:feature_class":"P",
    "gn:feature_code":"PPL",
    "gn:name":"Bo\u017eanska Maala",
    "gn:population":0,
    "gn:timezone":"Europe/Skopje",
    "iso:country":"MK",
    "name:mkd_x_preferred":[
        "Bo\u017eanska Maala"
    ],
    "name:mkd_x_variant":[
        "\u0411\u043e\u0436\u0430\u043d\u0441\u043a\u0430 \u041c\u0430\u0430\u043b\u0430"
    ],
    "wof:name":"Bozanska Maala",
    "wof:placetype":"locality"
},
  "geometry": {"coordinates":[22.65071,41.97122],"type":"Point"}
}