{
  "type": "Feature",
  "properties": {
    "gn:admin1_code":"62",
    "gn:asciiname":"Cergovci",
    "gn:country_code":"MK",
    "gn:dem":962,
    "gn:feature_class":"P",
    "gn:feature_code":"PPL",
    "gn:name":"\u010cergovci",
    "gn:population":0,
    "gn:timezone":"Europe/Skopje",
    "iso:country":"MK",
    "name:mkd_x_preferred":[
        "\u010cergovci"
    ],
    "name:mkd_x_variant":[
        "\u0427\u0435\u0440\u0433\u043e\u0432\u0446\u0438"
    ],
    "wof:name":"Cergovci",
    "wof:placetype":"locality"
},
  "geometry": {"coordinates":[22.55843,42.07247],"type":"Point"}
}