{
  "type": "Feature",
  "properties": {
    "gn:admin1_code":"11",
    "gn:asciiname":"Drvos",
    "gn:country_code":"MK",
    "gn:dem":365,
    "gn:feature_class":"P",
    "gn:feature_code":"PPL",
    "gn:name":"Drvo\u0161",
    "gn:population":0,
    "gn:timezone":"Europe/Skopje",
    "iso:country":"MK",
    "name:mkd_x_preferred":[
        "Drvo\u0161"
    ],
    "name:mkd_x_variant":[
        "\u0414\u0440\u0432\u043e\u0448"
    ],
    "wof:name":"Drvos",
    "wof:placetype":"locality"
},
  "geometry": {"coordinates":[22.77306,41.49824],"type":"Point"}
}