{
  "type": "Feature",
  "properties": {
    "gn:admin1_code":"D7",
    "gn:asciiname":"Amalinci",
    "gn:country_code":"MK",
    "gn:dem":479,
    "gn:feature_class":"P",
    "gn:feature_code":"PPL",
    "gn:name":"Amalinci",
    "gn:population":0,
    "gn:timezone":"Europe/Skopje",
    "iso:country":"MK",
    "name:mkd_x_preferred":[
        "Amalinci"
    ],
    "name:mkd_x_variant":[
        "\u0410\u043c\u0430\u043b\u0438\u043d\u0446\u0438"
    ],
    "wof:name":"Amalinci",
    "wof:placetype":"locality"
},
  "geometry": {"coordinates":[21.75421,42.19894],"type":"Point"}
}