{
  "type": "Feature",
  "properties": {
    "gn:country":"MK",
    "gn:fcode":"PPL",
    "gn:pop":168,
    "iso:country":"MK",
    "name:mkd_x_preferred":[
        "Orel"
    ],
    "name:mkd_x_variant":[
        "\u041e\u0440\u0435\u043b"
    ],
    "qs:name":"Orel",
    "qs:photos_9r":0,
    "qs:photos_sr":0,
    "qs:pop_sr":"1",
    "wd:wordcount":145,
    "wof:name":"Orel",
    "wof:placetype":"locality",
    "wof:population":168
},
  "geometry": {"coordinates":[21.97806,41.93972],"type":"Point"}
}