{
  "type": "Feature",
  "properties": {
    "gn:country":"MK",
    "gn:fcode":"PPL",
    "gn:population":168,
    "iso:country":"MK",
    "name:bel_x_preferred":[
        "\u0410\u0440\u043e\u043b"
    ],
    "name:bre_x_preferred":[
        "Oryol"
    ],
    "name:ceb_x_preferred":[
        "Orel"
    ],
    "name:ces_x_preferred":[
        "Orel"
    ],
    "name:deu_x_preferred":[
        "Orel"
    ],
    "name:fra_x_preferred":[
        "Orel"
    ],
    "name:ita_x_preferred":[
        "Orel"
    ],
    "name:jpn_x_preferred":[
        "\u30aa\u30ea\u30e7\u30fc\u30eb"
    ],
    "name:mkd_x_preferred":[
        "Orel"
    ],
    "name:mkd_x_variant":[
        "\u041e\u0440\u0435\u043b"
    ],
    "name:nld_x_preferred":[
        "Orel"
    ],
    "name:rus_x_preferred":[
        "\u041e\u0440\u0451\u043b"
    ],
    "name:slk_x_preferred":[
        "Orel"
    ],
    "name:slv_x_preferred":[
        "Orel"
    ],
    "name:swe_x_preferred":[
        "Orel"
    ],
    "qs:name":"Orel",
    "qs:photos_9r":0,
    "qs:photos_sr":0,
    "qs:pop_sr":"1",
    "wd:wordcount":145,
    "wof:name":"Orel",
    "wof:placetype":"locality",
    "wof:population":168
},
  "geometry": {"coordinates":[21.97806,41.93972],"type":"Point"}
}