{
  "type": "Feature",
  "properties": {
    "gn:admin1_code":"97",
    "gn:asciiname":"Trle",
    "gn:country_code":"MK",
    "gn:dem":413,
    "gn:feature_class":"P",
    "gn:feature_code":"PPL",
    "gn:name":"Trle",
    "gn:population":0,
    "gn:timezone":"Europe/Skopje",
    "iso:country":"MK",
    "name:mkd_x_preferred":[
        "Trle"
    ],
    "name:mkd_x_variant":[
        "\u0422\u0440\u043b\u0435"
    ],
    "wof:name":"Trle",
    "wof:placetype":"locality"
},
  "geometry": {"coordinates":[21.84476,42.27298],"type":"Point"}
}