{
  "type": "Feature",
  "properties": {
    "gn:admin1_code":"97",
    "gn:asciiname":"Mutavcici",
    "gn:country_code":"MK",
    "gn:dem":915,
    "gn:feature_class":"P",
    "gn:feature_code":"PPL",
    "gn:name":"Mutav\u010dici",
    "gn:population":0,
    "gn:timezone":"Europe/Skopje",
    "iso:country":"MK",
    "name:mkd_x_preferred":[
        "Mutav\u010dici"
    ],
    "name:mkd_x_variant":[
        "\u041c\u0443\u0442\u0430\u0432\u0447\u0438\u0446\u0438"
    ],
    "name:und_x_variant":[
        "Mutav\u010di\u0107i"
    ],
    "wof:name":"Mutavcici",
    "wof:placetype":"locality"
},
  "geometry": {"coordinates":[21.98028,42.27083],"type":"Point"}
}