{
  "type": "Feature",
  "properties": {
    "gn:country":"MK",
    "gn:fcode":"PPL",
    "gn:population":165,
    "iso:country":"MK",
    "name:arz_x_preferred":[
        "\u0643\u0627\u0632\u0627\u0646\u0649"
    ],
    "name:bul_x_preferred":[
        "\u041a\u0430\u0436\u0430\u043d\u0438"
    ],
    "name:cat_x_preferred":[
        "Ka\u017eani"
    ],
    "name:ceb_x_preferred":[
        "Ka\u017eani"
    ],
    "name:che_x_preferred":[
        "\u041a\u0430\u0436\u0430\u043d\u0438"
    ],
    "name:deu_x_preferred":[
        "Ka\u017eani"
    ],
    "name:ell_x_preferred":[
        "\u039a\u03b1\u03b6\u03ac\u03bd\u03b9"
    ],
    "name:eng_x_preferred":[
        "Ka\u017eani"
    ],
    "name:epo_x_preferred":[
        "Ka\u0135ani"
    ],
    "name:fra_x_preferred":[
        "Kajani"
    ],
    "name:hun_x_preferred":[
        "Kazsani"
    ],
    "name:mkd_x_preferred":[
        "Ka\u017eani"
    ],
    "name:mkd_x_variant":[
        "\u041a\u0430\u0436\u0430\u043d\u0438"
    ],
    "name:nan_x_preferred":[
        "Kajani"
    ],
    "name:nld_x_preferred":[
        "Ka\u017eani"
    ],
    "name:pol_x_preferred":[
        "Ka\u017cani"
    ],
    "name:sqi_x_preferred":[
        "Kazhani"
    ],
    "name:srp_x_preferred":[
        "\u041a\u0430\u0436\u0430\u043d\u0438"
    ],
    "name:swe_x_preferred":[
        "Ka\u017eani"
    ],
    "name:ukr_x_preferred":[
        "\u041a\u0430\u0436\u0430\u043d\u0456"
    ],
    "name:zho_x_preferred":[
        "\u00d0avato"
    ],
    "qs:name":"Ka\u017eani",
    "qs:name_adm0":"Macedonia",
    "qs:name_adm1":"Bitola",
    "qs:photos_9k":1,
    "qs:photos_9r":1,
    "qs:photos_all":2,
    "qs:photos_sr":0,
    "qs:placetype":"Town",
    "qs:pop_sr":"1",
    "wd:elevation":880.0,
    "wd:population":75,
    "wd:wordcount":31,
    "wof:name":"Ka\u017eani",
    "wof:placetype":"locality",
    "wof:population":75
},
  "geometry": {"coordinates":[21.14722,41.06528],"type":"Point"}
}