{
  "type": "Feature",
  "properties": {
    "gn:country":"MK",
    "gn:fcode":"PPLA",
    "gn:pop":8646,
    "iso:country":"MK",
    "name:mkd_x_preferred":[
        "\u0427\u0443\u0447\u0435\u0440"
    ],
    "name:unk_x_variant":[
        "\u010cu\u010der"
    ],
    "qs:name":"\u010cu\u010der - Sandevo",
    "qs:name_adm0":"Macedonia",
    "qs:name_adm1":"\u010cu\u010der-Sandevo",
    "qs:photos_9k":1,
    "qs:photos_9r":1,
    "qs:photos_all":2,
    "qs:photos_sr":0,
    "qs:placetype":"Town",
    "qs:pop_sr":"5",
    "wd:wordcount":119,
    "wof:name":"\u010cu\u010der - Sandevo",
    "wof:placetype":"locality",
    "wof:population":8646
},
  "geometry": {"coordinates":[21.38222,42.10361],"type":"Point"}
}