{
  "type": "Feature",
  "properties": {
    "gn:admin1_code":"D4",
    "gn:asciiname":"Kunovo",
    "gn:country_code":"MK",
    "gn:dem":965,
    "gn:feature_class":"P",
    "gn:feature_code":"PPL",
    "gn:name":"Kunovo",
    "gn:population":0,
    "gn:timezone":"Europe/Skopje",
    "iso:country":"MK",
    "name:mkd_x_preferred":[
        "Kunovo"
    ],
    "name:mkd_x_variant":[
        "\u041a\u0443\u043d\u043e\u0432\u043e"
    ],
    "wof:name":"Kunovo",
    "wof:placetype":"locality"
},
  "geometry": {"coordinates":[20.95214,41.74238],"type":"Point"}
}