{
  "type": "Feature",
  "properties": {
    "gn:admin1_code":"51",
    "gn:asciiname":"Salevci",
    "gn:country_code":"MK",
    "gn:dem":564,
    "gn:feature_class":"P",
    "gn:feature_code":"PPL",
    "gn:name":"\u0160alevci",
    "gn:population":0,
    "gn:timezone":"Europe/Skopje",
    "iso:country":"MK",
    "name:mkd_x_preferred":[
        "\u0160alevci"
    ],
    "name:mkd_x_variant":[
        "\u0428\u0430\u043b\u0435\u0432\u0446\u0438"
    ],
    "wof:name":"Salevci",
    "wof:placetype":"locality"
},
  "geometry": {"coordinates":[22.00287,42.12295],"type":"Point"}
}