{
  "type": "Feature",
  "properties": {
    "gn:country":"MK",
    "gn:fcode":"PPL",
    "gn:population":256,
    "iso:country":"MK",
    "name:bul_x_preferred":[
        "\u0421\u043b\u0435\u043f\u0447\u0435"
    ],
    "name:cat_x_preferred":[
        "Slep\u010de"
    ],
    "name:ceb_x_preferred":[
        "Slepce"
    ],
    "name:ell_x_preferred":[
        "\u03a3\u03bb\u03ad\u03c0\u03c4\u03c3\u03b5 \u03a0\u03c1\u03b9\u03bb\u03ac\u03c0\u03bf\u03c5"
    ],
    "name:eng_x_preferred":[
        "Slep\u010de"
    ],
    "name:fra_x_preferred":[
        "Sleptch\u00e9"
    ],
    "name:hun_x_preferred":[
        "Szlepcse"
    ],
    "name:mkd_x_preferred":[
        "Slep\u010de"
    ],
    "name:mkd_x_variant":[
        "\u0421\u043b\u0435\u043f\u0447\u0435"
    ],
    "name:nan_x_preferred":[
        "Sleptch\u00e9"
    ],
    "name:nld_x_preferred":[
        "Slep\u010de"
    ],
    "name:sqi_x_preferred":[
        "Sllep\u00e7a"
    ],
    "name:srp_x_preferred":[
        "\u0421\u043b\u0435\u043f\u0447\u0435"
    ],
    "name:swe_x_preferred":[
        "Slepce"
    ],
    "qs:name":"Slep\u010de",
    "qs:photos_9r":0,
    "qs:photos_sr":0,
    "qs:pop_sr":"2",
    "wd:wordcount":67,
    "wof:name":"Slep\u010de",
    "wof:placetype":"locality",
    "wof:population":256
},
  "geometry": {"coordinates":[21.45167,41.50083],"type":"Point"}
}