{
  "type": "Feature",
  "properties": {
    "gn:country":"MK",
    "gn:fcode":"PPL",
    "gn:pop":256,
    "iso:country":"MK",
    "name:mkd_x_preferred":[
        "Slep\u010de"
    ],
    "name:mkd_x_variant":[
        "\u0421\u043b\u0435\u043f\u0447\u0435"
    ],
    "qs:name":"Slep\u010de",
    "qs:photos_9r":0,
    "qs:photos_sr":0,
    "qs:pop_sr":"2",
    "wd:wordcount":67,
    "wof:name":"Slep\u010de",
    "wof:placetype":"locality",
    "wof:population":256
},
  "geometry": {"coordinates":[21.45167,41.50083],"type":"Point"}
}