{
  "type": "Feature",
  "properties": {
    "gn:admin1_code":"D7",
    "gn:asciiname":"Recica",
    "gn:country_code":"MK",
    "gn:dem":362,
    "gn:feature_class":"P",
    "gn:feature_code":"PPL",
    "gn:name":"Re\u010dica",
    "gn:population":0,
    "gn:timezone":"Europe/Skopje",
    "iso:country":"MK",
    "name:mkd_x_preferred":[
        "Re\u010dica"
    ],
    "name:mkd_x_variant":[
        "\u0420\u0435\u0447\u0438\u0446\u0430"
    ],
    "wof:name":"Recica",
    "wof:placetype":"locality"
},
  "geometry": {"coordinates":[21.69472,42.17444],"type":"Point"}
}