{
  "type": "Feature",
  "properties": {
    "gn:admin1_code":"E6",
    "gn:asciiname":"Dolna Belica",
    "gn:country_code":"MK",
    "gn:dem":739,
    "gn:feature_class":"P",
    "gn:feature_code":"PPL",
    "gn:name":"Dolna Belica",
    "gn:population":0,
    "gn:timezone":"Europe/Skopje",
    "iso:country":"MK",
    "name:bul_x_preferred":[
        "\u0414\u043e\u043b\u043d\u0430 \u0411\u0435\u043b\u0438\u0446\u0430"
    ],
    "name:deu_x_preferred":[
        "Dolna Belica"
    ],
    "name:fra_x_preferred":[
        "Dolna Belitsa"
    ],
    "name:hun_x_preferred":[
        "Dolna Belica"
    ],
    "name:mkd_x_preferred":[
        "Dolna Belica"
    ],
    "name:mkd_x_variant":[
        "\u0414\u043e\u043b\u043d\u0430 \u0411\u0435\u043b\u0438\u0446\u0430"
    ],
    "name:por_x_preferred":[
        "Dolna Belica"
    ],
    "name:sqi_x_preferred":[
        "Belica e Poshtme"
    ],
    "name:srp_x_preferred":[
        "\u0414\u043e\u045a\u0430 \u0411\u0435\u043b\u0438\u0446\u0430"
    ],
    "wof:name":"Dolna Belica",
    "wof:placetype":"locality"
},
  "geometry": {"coordinates":[20.635,41.21333],"type":"Point"}
}