{
  "type": "Feature",
  "properties": {
    "gn:admin1_code":"51",
    "gn:asciiname":"Arnautovci",
    "gn:country_code":"MK",
    "gn:dem":486,
    "gn:feature_class":"P",
    "gn:feature_code":"PPL",
    "gn:name":"Arnautovci",
    "gn:population":0,
    "gn:timezone":"Europe/Skopje",
    "iso:country":"MK",
    "name:mkd_x_preferred":[
        "Arnautovci"
    ],
    "name:mkd_x_variant":[
        "\u0410\u0440\u043d\u0430\u0443\u0442\u043e\u0432\u0446\u0438"
    ],
    "wof:name":"Arnautovci",
    "wof:placetype":"locality"
},
  "geometry": {"coordinates":[22.08169,42.11948],"type":"Point"}
}