{
  "type": "Feature",
  "properties": {
    "gn:admin1_code":"52",
    "gn:asciiname":"Dzangovci",
    "gn:country_code":"MK",
    "gn:dem":1006,
    "gn:feature_class":"P",
    "gn:feature_code":"PPL",
    "gn:name":"D\u017eangovci",
    "gn:population":0,
    "gn:timezone":"Europe/Skopje",
    "iso:country":"MK",
    "name:mkd_x_preferred":[
        "D\u017eangovci"
    ],
    "name:mkd_x_variant":[
        "\u040f\u0430\u043d\u0433\u043e\u0432\u0446\u0438"
    ],
    "wof:name":"Dzangovci",
    "wof:placetype":"locality"
},
  "geometry": {"coordinates":[22.31245,42.24368],"type":"Point"}
}