{
  "type": "Feature",
  "properties": {
    "gn:admin1_code":"52",
    "gn:asciiname":"Dzikovska Maala",
    "gn:country_code":"MK",
    "gn:dem":1040,
    "gn:feature_class":"P",
    "gn:feature_code":"PPL",
    "gn:name":"D\u017eikovska Maala",
    "gn:population":0,
    "gn:timezone":"Europe/Skopje",
    "iso:country":"MK",
    "name:mkd_x_preferred":[
        "D\u017eikovska Maala"
    ],
    "name:mkd_x_variant":[
        "\u040f\u0438\u043a\u043e\u0432\u0441\u043a\u0430 \u041c\u0430\u0430\u043b\u0430"
    ],
    "wof:name":"Dzikovska Maala",
    "wof:placetype":"locality"
},
  "geometry": {"coordinates":[22.40711,42.21625],"type":"Point"}
}