{
  "type": "Feature",
  "properties": {
    "gn:admin1_code":"20",
    "gn:asciiname":"Tuseva Maala",
    "gn:country_code":"MK",
    "gn:dem":778,
    "gn:feature_class":"P",
    "gn:feature_code":"PPL",
    "gn:name":"Tu\u0161eva Maala",
    "gn:population":0,
    "gn:timezone":"Europe/Skopje",
    "iso:country":"MK",
    "name:mkd_x_preferred":[
        "\u0422\u0443\u0448\u0435\u0432\u0430 \u041c\u0430\u0430\u043b\u0430"
    ],
    "name:und_x_variant":[
        "Tu\u0161eva Mala",
        "Tu\u0161eva Maala"
    ],
    "wof:name":"Tuseva Maala",
    "wof:placetype":"locality"
},
  "geometry": {"coordinates":[21.33813,42.14177],"type":"Point"}
}