{
  "type": "Feature",
  "properties": {
    "gn:admin1_code":"86",
    "gn:asciiname":"Surlenci",
    "gn:country_code":"MK",
    "gn:dem":854,
    "gn:feature_class":"P",
    "gn:feature_code":"PPL",
    "gn:name":"\u0160urlenci",
    "gn:population":0,
    "gn:timezone":"Europe/Skopje",
    "iso:country":"MK",
    "name:bul_x_preferred":[
        "\u0428\u0443\u0440\u043b\u0435\u043d\u0446\u0438"
    ],
    "name:fra_x_preferred":[
        "Chourlentsi"
    ],
    "name:mkd_x_preferred":[
        "\u0160urlenci"
    ],
    "name:mkd_x_variant":[
        "\u0428\u0443\u0440\u043b\u0435\u043d\u0446\u0438"
    ],
    "name:por_x_preferred":[
        "\u0160urlenci"
    ],
    "name:sqi_x_preferred":[
        "Shurlenca"
    ],
    "name:srp_x_preferred":[
        "\u0428\u0443\u0440\u043b\u0435\u043d\u0446\u0438"
    ],
    "wof:name":"Surlenci",
    "wof:placetype":"locality"
},
  "geometry": {"coordinates":[20.94895,41.01297],"type":"Point"}
}