{
  "type": "Feature",
  "properties": {
    "gn:admin1_code":"A9",
    "gn:asciiname":"Angelci",
    "gn:country_code":"MK",
    "gn:dem":243,
    "gn:feature_class":"P",
    "gn:feature_code":"PPL",
    "gn:name":"Angelci",
    "gn:population":0,
    "gn:timezone":"Europe/Skopje",
    "iso:country":"MK",
    "name:mkd_x_preferred":[
        "Angelci"
    ],
    "name:mkd_x_variant":[
        "\u0410\u043d\u0433\u0435\u043b\u0446\u0438"
    ],
    "wof:name":"Angelci",
    "wof:placetype":"locality"
},
  "geometry": {"coordinates":[22.61483,41.47773],"type":"Point"}
}