{
  "type": "Feature",
  "properties": {
    "gn:country":"MK",
    "gn:fcode":"PPL",
    "gn:population":565,
    "iso:country":"MK",
    "name:bar_x_preferred":[
        "Dobromiri"
    ],
    "name:bul_x_preferred":[
        "\u0414\u043e\u0431\u0440\u043e\u043c\u0438\u0440\u0438"
    ],
    "name:cat_x_preferred":[
        "Dobromiri"
    ],
    "name:ceb_x_preferred":[
        "Dobromiri"
    ],
    "name:ces_x_preferred":[
        "Dobromiri"
    ],
    "name:dan_x_preferred":[
        "Dobromiri"
    ],
    "name:deu_x_preferred":[
        "Dobromiri"
    ],
    "name:eng_x_preferred":[
        "Dobromiri"
    ],
    "name:epo_x_preferred":[
        "Dobromiri"
    ],
    "name:fin_x_preferred":[
        "Dobromiri"
    ],
    "name:fra_x_preferred":[
        "Dobromiri"
    ],
    "name:gla_x_preferred":[
        "Dobromiri"
    ],
    "name:glg_x_preferred":[
        "Dobromiri"
    ],
    "name:gsw_x_preferred":[
        "Dobromiri"
    ],
    "name:hrv_x_preferred":[
        "Dobromiri"
    ],
    "name:hun_x_preferred":[
        "Dobromiri"
    ],
    "name:ind_x_preferred":[
        "Dobromiri"
    ],
    "name:isl_x_preferred":[
        "Dobromiri"
    ],
    "name:ita_x_preferred":[
        "Dobromiri"
    ],
    "name:ltz_x_preferred":[
        "Dobromiri"
    ],
    "name:min_x_preferred":[
        "Dobromiri"
    ],
    "name:mkd_x_preferred":[
        "\u0414\u043e\u0431\u0440\u043e\u043c\u0438\u0440\u0438"
    ],
    "name:msa_x_preferred":[
        "Dobromiri"
    ],
    "name:nan_x_preferred":[
        "Dobromiri"
    ],
    "name:nds_x_preferred":[
        "Dobromiri"
    ],
    "name:nld_x_preferred":[
        "Dobromiri"
    ],
    "name:nno_x_preferred":[
        "Dobromiri"
    ],
    "name:nob_x_preferred":[
        "Dobromiri"
    ],
    "name:pol_x_preferred":[
        "Dobromiri"
    ],
    "name:por_x_preferred":[
        "Dobromiri"
    ],
    "name:ron_x_preferred":[
        "Dobromiri"
    ],
    "name:slk_x_preferred":[
        "Dobromiri"
    ],
    "name:slv_x_preferred":[
        "Dobromiri"
    ],
    "name:spa_x_preferred":[
        "Dobromiri"
    ],
    "name:sqi_x_preferred":[
        "Dobromiri"
    ],
    "name:srp_x_preferred":[
        "\u0414\u043e\u0431\u0440\u043e\u043c\u0438\u0440\u0438"
    ],
    "name:swe_x_preferred":[
        "Dobromiri"
    ],
    "name:und_x_variant":[
        "Dobromir"
    ],
    "qs:name":"Dobromiri",
    "qs:photos_9r":0,
    "qs:photos_sr":0,
    "qs:pop_sr":"2",
    "wd:wordcount":133,
    "wof:name":"Dobromiri",
    "wof:placetype":"locality",
    "wof:population":565
},
  "geometry": {"coordinates":[21.45583,41.06944],"type":"Point"}
}