{
  "type": "Feature",
  "properties": {
    "gn:country":"MK",
    "gn:fcode":"PPL",
    "gn:pop":2173,
    "iso:country":"MK",
    "name:bul_x_preferred":[
        "\u0420\u0443\u0441\u0438\u043d\u043e\u0432\u043e"
    ],
    "name:eng_x_preferred":[
        "Rusinovo"
    ],
    "name:fra_x_preferred":[
        "Roussinovo"
    ],
    "name:hun_x_preferred":[
        "Ruszinovo"
    ],
    "name:mkd_x_preferred":[
        "Rusinovo"
    ],
    "name:mkd_x_variant":[
        "\u0420\u0443\u0441\u0438\u043d\u043e\u0432\u043e"
    ],
    "name:nan_x_preferred":[
        "Roussinovo"
    ],
    "name:nld_x_preferred":[
        "Rusinovo"
    ],
    "name:rus_x_preferred":[
        "\u0420\u0443\u0441\u0438\u043d\u043e\u0432\u043e"
    ],
    "name:sqi_x_preferred":[
        "Rusinova"
    ],
    "name:srp_x_preferred":[
        "\u0420\u0443\u0441\u0438\u043d\u043e\u0432\u043e"
    ],
    "name:swe_x_preferred":[
        "Rusinovo"
    ],
    "name:ukr_x_preferred":[
        "\u0420\u0443\u0441\u0438\u043d\u043e\u0432\u043e"
    ],
    "qs:name":"Rusinovo",
    "qs:name_adm0":"Macedonia",
    "qs:name_adm1":"Berovo",
    "qs:photos_9k":1,
    "qs:photos_9r":1,
    "qs:photos_all":6,
    "qs:photos_sr":0,
    "qs:placetype":"Town",
    "qs:pop_sr":"4",
    "wd:elevation":933.0,
    "wd:wordcount":31,
    "wof:name":"Rusinovo",
    "wof:placetype":"locality",
    "wof:population":2173
},
  "geometry": {"coordinates":[22.80833,41.68333],"type":"Point"}
}