{
  "type": "Feature",
  "properties": {
    "gn:admin1_code":"D5",
    "gn:asciiname":"Semsevo",
    "gn:country_code":"MK",
    "gn:dem":403,
    "gn:feature_class":"P",
    "gn:feature_code":"PPL",
    "gn:name":"\u0160em\u0161evo",
    "gn:population":0,
    "gn:timezone":"Europe/Skopje",
    "iso:country":"MK",
    "name:mkd_x_preferred":[
        "\u0428\u0435\u043c\u0448\u0435\u0432\u043e"
    ],
    "name:mkd_x_variant":[
        "\u0160em\u0161ovo",
        "\u0428\u0435\u043c\u0448\u043e\u0432\u043e"
    ],
    "name:und_x_variant":[
        "Shemshevo",
        "\u0160em\u0161evo"
    ],
    "wof:name":"Semsevo",
    "wof:placetype":"locality"
},
  "geometry": {"coordinates":[21.07915,42.02425],"type":"Point"}
}