{
  "type": "Feature",
  "properties": {
    "gn:country":"MK",
    "gn:fcode":"PPL",
    "gn:pop":714,
    "iso:country":"MK",
    "name:mkd_x_preferred":[
        "Melnica"
    ],
    "name:mkd_x_variant":[
        "\u041c\u0435\u043b\u043d\u0438\u0446\u0430"
    ],
    "qs:name":"Melnica",
    "qs:photos_9r":0,
    "qs:photos_sr":0,
    "qs:pop_sr":"2",
    "wd:wordcount":55,
    "wof:name":"Melnica",
    "wof:placetype":"locality",
    "wof:population":714
},
  "geometry": {"coordinates":[21.59,41.64167],"type":"Point"}
}