{
  "type": "Feature",
  "properties": {
    "gn:admin1_code":"43",
    "gn:asciiname":"Ehlovec",
    "gn:country_code":"MK",
    "gn:dem":1042,
    "gn:feature_class":"P",
    "gn:feature_code":"PPL",
    "gn:name":"Ehlovec",
    "gn:population":0,
    "gn:timezone":"Europe/Skopje",
    "iso:country":"MK",
    "name:mkd_x_preferred":[
        "\u0415\u0445\u043b\u043e\u0432\u0435\u0446"
    ],
    "name:und_x_variant":[
        "Jehlovac",
        "Ehlovac",
        "Evloec",
        "Ehloec",
        "Ehlovec"
    ],
    "wof:name":"Ehlovec",
    "wof:placetype":"locality"
},
  "geometry": {"coordinates":[20.76583,41.45972],"type":"Point"}
}