{
  "type": "Feature",
  "properties": {
    "gn:country":"MK",
    "gn:fcode":"PPL",
    "gn:pop":169,
    "iso:country":"MK",
    "name:mkd_x_preferred":[
        "Latovo"
    ],
    "name:mkd_x_variant":[
        "\u041b\u0430\u0442\u043e\u0432\u043e"
    ],
    "qs:name":"Latovo",
    "qs:photos_9r":0,
    "qs:photos_sr":0,
    "qs:pop_sr":"1",
    "wd:wordcount":302,
    "wof:name":"Latovo",
    "wof:placetype":"locality",
    "wof:population":169
},
  "geometry": {"coordinates":[21.16917,41.48833],"type":"Point"}
}