{
  "type": "Feature",
  "properties": {
    "gn:country":"MK",
    "gn:fcode":"PPL",
    "gn:pop":286,
    "iso:country":"MK",
    "name:mkd_x_preferred":[
        "\u0414\u043e\u043b\u043d\u043e \u041e\u0440\u0435\u0445\u043e\u0432\u043e"
    ],
    "name:unk_x_variant":[
        "Dolno Orehovo"
    ],
    "qs:name":"Orehovo",
    "qs:photos_9r":0,
    "qs:photos_sr":0,
    "qs:pop_sr":"2",
    "wd:wordcount":59,
    "wof:name":"Orehovo",
    "wof:placetype":"locality",
    "wof:population":286
},
  "geometry": {"coordinates":[21.56194,41.06444],"type":"Point"}
}