{
  "type": "Feature",
  "properties": {
    "gn:country":"MK",
    "gn:fcode":"PPL",
    "gn:population":286,
    "iso:country":"MK",
    "name:bos_x_preferred":[
        "Orehovo"
    ],
    "name:ceb_x_preferred":[
        "Orehovo"
    ],
    "name:che_x_preferred":[
        "\u041e\u0440\u0435\u0445\u043e\u0432\u043e"
    ],
    "name:eng_x_preferred":[
        "Orehovo"
    ],
    "name:fra_x_preferred":[
        "Orehovo"
    ],
    "name:hrv_x_preferred":[
        "Orehovo"
    ],
    "name:mkd_x_preferred":[
        "\u0414\u043e\u043b\u043d\u043e \u041e\u0440\u0435\u0445\u043e\u0432\u043e"
    ],
    "name:mkd_x_variant":[
        "\u041e\u0440\u0435\u0445\u043e\u0432\u043e"
    ],
    "name:nld_x_preferred":[
        "Orehovo"
    ],
    "name:pol_x_preferred":[
        "Orehovo"
    ],
    "name:ron_x_preferred":[
        "Orehovo"
    ],
    "name:slv_x_preferred":[
        "Orehovo"
    ],
    "name:tat_x_preferred":[
        "\u041e\u0440\u0435\u0445\u043e\u0432\u043e"
    ],
    "name:ukr_x_preferred":[
        "\u041e\u0440\u0435\u0445\u043e\u0432\u043e"
    ],
    "name:und_x_variant":[
        "Dolno Orehovo"
    ],
    "qs:name":"Orehovo",
    "qs:photos_9r":0,
    "qs:photos_sr":0,
    "qs:pop_sr":"2",
    "wd:wordcount":59,
    "wof:name":"Orehovo",
    "wof:placetype":"locality",
    "wof:population":286
},
  "geometry": {"coordinates":[21.56194,41.06444],"type":"Point"}
}