{
  "type": "Feature",
  "properties": {
    "gn:admin1_code":"18",
    "gn:asciiname":"Dolgas",
    "gn:country_code":"MK",
    "gn:dem":808,
    "gn:feature_class":"P",
    "gn:feature_code":"PPL",
    "gn:name":"Dolga\u0161",
    "gn:population":0,
    "gn:timezone":"Europe/Skopje",
    "iso:country":"MK",
    "name:mkd_x_preferred":[
        "\u0414\u043e\u043b\u0433\u0430\u0448"
    ],
    "name:und_x_variant":[
        "Dallgash",
        "Dolga\u0161"
    ],
    "wof:name":"Dolgas",
    "wof:placetype":"locality"
},
  "geometry": {"coordinates":[20.58681,41.42315],"type":"Point"}
}