{
  "type": "Feature",
  "properties": {
    "gn:country":"MK",
    "gn:fcode":"PPL",
    "gn:pop":178,
    "iso:country":"MK",
    "name:mkd_x_preferred":[
        "\u0421\u0442\u0430\u045a\u0435\u0432\u0446\u0438"
    ],
    "name:unk_x_variant":[
        "Stanjevce"
    ],
    "qs:name":"Stanjevci",
    "qs:photos_9r":0,
    "qs:photos_sr":0,
    "qs:pop_sr":"1",
    "wd:wordcount":99,
    "wof:name":"Stanjevci",
    "wof:placetype":"locality",
    "wof:population":178
},
  "geometry": {"coordinates":[21.90333,41.9575],"type":"Point"}
}