{
  "type": "Feature",
  "properties": {
    "gn:country":"MK",
    "gn:fcode":"PPL",
    "gn:pop":178,
    "iso:country":"MK",
    "name:bos_x_preferred":[
        "Stanjevci"
    ],
    "name:ceb_x_preferred":[
        "Stanjevci"
    ],
    "name:epo_x_preferred":[
        "Stanjevci"
    ],
    "name:hrv_x_preferred":[
        "Stanjevci"
    ],
    "name:hun_x_preferred":[
        "Kerkaszabadhegy"
    ],
    "name:mkd_x_preferred":[
        "\u0421\u0442\u0430\u045a\u0435\u0432\u0446\u0438"
    ],
    "name:nld_x_preferred":[
        "Stanjevci"
    ],
    "name:pol_x_preferred":[
        "Stanjevci"
    ],
    "name:ron_x_preferred":[
        "Stanjevci"
    ],
    "name:slv_x_preferred":[
        "Stanjevci"
    ],
    "name:srp_x_preferred":[
        "\u0421\u0442\u0430\u045a\u0435\u0432\u0446\u0438"
    ],
    "name:ukr_x_preferred":[
        "\u0421\u0442\u0430\u043d\u0454\u0432\u0446\u0456"
    ],
    "name:unk_x_variant":[
        "Stanjevce"
    ],
    "qs:name":"Stanjevci",
    "qs:photos_9r":0,
    "qs:photos_sr":0,
    "qs:pop_sr":"1",
    "wd:wordcount":99,
    "wof:name":"Stanjevci",
    "wof:placetype":"locality",
    "wof:population":178
},
  "geometry": {"coordinates":[21.90333,41.9575],"type":"Point"}
}