{
  "type": "Feature",
  "properties": {
    "gn:admin1_code":"47",
    "gn:asciiname":"Lubnica",
    "gn:country_code":"MK",
    "gn:dem":568,
    "gn:feature_class":"P",
    "gn:feature_code":"PPL",
    "gn:name":"Lubnica",
    "gn:population":0,
    "gn:timezone":"Europe/Skopje",
    "iso:country":"MK",
    "name:fra_x_preferred":[
        "Lubnica"
    ],
    "name:mkd_x_preferred":[
        "Lubnica"
    ],
    "name:mkd_x_variant":[
        "\u041b\u0443\u0431\u043d\u0438\u0446\u0430"
    ],
    "name:pol_x_preferred":[
        "Lubnica"
    ],
    "name:por_x_preferred":[
        "Lubnica"
    ],
    "name:sqi_x_preferred":[
        "Lubnica"
    ],
    "wof:name":"Lubnica",
    "wof:placetype":"locality"
},
  "geometry": {"coordinates":[22.36779,41.50116],"type":"Point"}
}