{
  "type": "Feature",
  "properties": {
    "gn:country":"MK",
    "gn:fcode":"PPL",
    "gn:pop":0,
    "iso:country":"MK",
    "name:bul_x_preferred":[
        "\u041c\u0430\u0442\u043a\u0430"
    ],
    "name:deu_x_preferred":[
        "Matka"
    ],
    "name:ell_x_preferred":[
        "\u039c\u03ac\u03c4\u03ba\u03b1"
    ],
    "name:eng_x_preferred":[
        "Matka"
    ],
    "name:fra_x_preferred":[
        "Matka"
    ],
    "name:mkd_x_preferred":[
        "\u041c\u0430\u0442\u043a\u0430"
    ],
    "name:nan_x_preferred":[
        "Matka"
    ],
    "name:nld_x_preferred":[
        "Matka"
    ],
    "name:sqi_x_preferred":[
        "Matka"
    ],
    "name:srp_x_preferred":[
        "\u041c\u0430\u0442\u043a\u0430"
    ],
    "name:unk_x_variant":[
        "Ma\u015bka"
    ],
    "qs:name":"Matka",
    "qs:name_adm0":"Macedonia",
    "qs:name_adm1":"Saraj",
    "qs:photos":47,
    "qs:photos_1k":10,
    "qs:photos_9k":1,
    "qs:photos_9r":2,
    "qs:photos_all":47,
    "qs:photos_sr":2,
    "qs:placetype":"Town",
    "qs:pop_sr":"0",
    "wd:wordcount":54,
    "wof:name":"Matka",
    "wof:placetype":"locality",
    "wof:population":0
},
  "geometry": {"coordinates":[21.28611,41.96917],"type":"Point"}
}