{
  "type": "Feature",
  "properties": {
    "gn:country":"MK",
    "gn:fcode":"PPL",
    "gn:population":611,
    "iso:country":"MK",
    "name:mkd_x_preferred":[
        "\u0421\u0442\u0430\u0440 \u041a\u0430\u0440\u0430\u043e\u0440\u043c\u0430\u043d"
    ],
    "name:und_x_variant":[
        "Star Karaorman"
    ],
    "qs:name":"Stari Karaorman",
    "qs:photos_9r":0,
    "qs:photos_sr":0,
    "qs:pop_sr":"2",
    "wof:name":"Stari Karaorman",
    "wof:placetype":"locality",
    "wof:population":611
},
  "geometry": {"coordinates":[22.20361,41.78167],"type":"Point"}
}