{
  "type": "Feature",
  "properties": {
    "gn:admin1_code":"E9",
    "gn:asciiname":"Kazandol",
    "gn:country_code":"MK",
    "gn:dem":365,
    "gn:feature_class":"P",
    "gn:feature_code":"PPL",
    "gn:name":"Kazandol",
    "gn:population":0,
    "gn:timezone":"Europe/Skopje",
    "iso:country":"MK",
    "name:mkd_x_preferred":[
        "Kazandol"
    ],
    "name:mkd_x_variant":[
        "\u041a\u0430\u0437\u0430\u043d\u0434\u043e\u043b"
    ],
    "wof:name":"Kazandol",
    "wof:placetype":"locality"
},
  "geometry": {"coordinates":[22.57291,41.2755],"type":"Point"}
}