{
  "type": "Feature",
  "properties": {
    "gn:country":"MK",
    "gn:fcode":"PPLL",
    "gn:pop":130,
    "iso:country":"MK",
    "name:mkd_x_preferred":[
        "\u0421\u043b\u0430\u0442\u0438\u043d\u0430"
    ],
    "name:unk_x_variant":[
        "Slatino"
    ],
    "qs:name":"Slatina",
    "qs:photos_9r":0,
    "qs:photos_sr":0,
    "qs:pop_sr":"1",
    "wd:wordcount":542,
    "wof:name":"Slatina",
    "wof:placetype":"locality",
    "wof:population":130
},
  "geometry": {"coordinates":[21.18222,41.58611],"type":"Point"}
}