{
  "type": "Feature",
  "properties": {
    "gn:country":"MK",
    "gn:fcode":"PPL",
    "gn:pop":179,
    "iso:country":"MK",
    "name:alb_x_preferred":[
        "Dupja\u00e7ani"
    ],
    "name:bul_x_preferred":[
        "\u0414\u0443\u043f\u044f\u0447\u0430\u043d\u0438"
    ],
    "name:dut_x_preferred":[
        "Dupja\u010dani"
    ],
    "name:eng_x_preferred":[
        "Dupja\u010dani"
    ],
    "name:fre_x_preferred":[
        "Doupyatchani"
    ],
    "name:ger_x_preferred":[
        "Dupja\u010dani"
    ],
    "name:hun_x_preferred":[
        "Dupjacsani"
    ],
    "name:mac_x_preferred":[
        "\u0414\u0443\u043f\u0458\u0430\u0447\u0430\u043d\u0438"
    ],
    "name:mkd_x_preferred":[
        "Dupja\u010dani"
    ],
    "name:mkd_x_variant":[
        "\u0414\u0443\u043f\u0458\u0430\u0447\u0430\u043d\u0438"
    ],
    "name:srp_x_preferred":[
        "\u0414\u0443\u043fj\u0430\u0447\u0430\u043d\u0438"
    ],
    "name:swe_x_preferred":[
        "Dupja\u010dani"
    ],
    "qs:name":"Dupja\u010dani",
    "qs:photos_9r":0,
    "qs:photos_sr":0,
    "qs:pop_sr":"1",
    "wd:wordcount":40,
    "wof:name":"Dupja\u010dani",
    "wof:placetype":"locality",
    "wof:population":179
},
  "geometry": {"coordinates":[21.52194,41.44083],"type":"Point"}
}