{
  "type": "Feature",
  "properties": {
    "gn:admin1_code":"E7",
    "gn:asciiname":"Ric",
    "gn:country_code":"MK",
    "gn:dem":508,
    "gn:feature_class":"P",
    "gn:feature_code":"PPL",
    "gn:name":"Ri\u010d",
    "gn:population":0,
    "gn:timezone":"Europe/Skopje",
    "iso:country":"MK",
    "name:mkd_x_preferred":[
        "Ri\u010d"
    ],
    "name:mkd_x_variant":[
        "\u0420\u0438\u0447"
    ],
    "wof:name":"Ric",
    "wof:placetype":"locality"
},
  "geometry": {"coordinates":[22.51986,41.44284],"type":"Point"}
}