{
  "type": "Feature",
  "properties": {
    "gn:admin1_code":"20",
    "gn:asciiname":"Bardovska Maala",
    "gn:country_code":"MK",
    "gn:dem":421,
    "gn:feature_class":"P",
    "gn:feature_code":"PPL",
    "gn:name":"Bardovska Maala",
    "gn:population":0,
    "gn:timezone":"Europe/Skopje",
    "iso:country":"MK",
    "name:mkd_x_preferred":[
        "\u0411\u0430\u0440\u0434\u043e\u0432\u0441\u043a\u0430 \u041c\u0430\u0430\u043b\u0430"
    ],
    "name:und_x_variant":[
        "Bardovska Mala",
        "Bardovska Maala"
    ],
    "wof:name":"Bardovska Maala",
    "wof:placetype":"locality"
},
  "geometry": {"coordinates":[21.30723,42.14102000000001],"type":"Point"}
}