{
  "type": "Feature",
  "properties": {
    "gn:admin1_code":"D4",
    "gn:asciiname":"Dolno Jelovce",
    "gn:country_code":"MK",
    "gn:dem":1038,
    "gn:feature_class":"P",
    "gn:feature_code":"PPL",
    "gn:name":"Dolno Jelovce",
    "gn:population":0,
    "gn:timezone":"Europe/Skopje",
    "iso:country":"MK",
    "name:mkd_x_preferred":[
        "Dolno Jelovce"
    ],
    "name:mkd_x_variant":[
        "\u0414\u043e\u043b\u043d\u043e \u0408\u0435\u043b\u043e\u0432\u0446\u0435"
    ],
    "wof:name":"Dolno Jelovce",
    "wof:placetype":"locality"
},
  "geometry": {"coordinates":[20.83688,41.8017],"type":"Point"}
}