{
  "type": "Feature",
  "properties": {
    "gn:admin1_code":"E4",
    "gn:asciiname":"Krakornica",
    "gn:country_code":"MK",
    "gn:dem":1515,
    "gn:feature_class":"P",
    "gn:feature_code":"PPL",
    "gn:name":"Krakornica",
    "gn:population":0,
    "gn:timezone":"Europe/Skopje",
    "iso:country":"MK",
    "name:bul_x_preferred":[
        "\u041a\u0440\u0430\u043a\u043e\u0440\u043d\u0438\u0446\u0430"
    ],
    "name:fra_x_preferred":[
        "Krakornitsa"
    ],
    "name:mkd_x_preferred":[
        "Krakornica"
    ],
    "name:mkd_x_variant":[
        "\u041a\u0440\u0430\u043a\u043e\u0440\u043d\u0438\u0446\u0430"
    ],
    "name:sqi_x_preferred":[
        "Krakarnica"
    ],
    "name:srp_x_preferred":[
        "\u041a\u0440\u0430\u043a\u043e\u0440\u043d\u0438\u0446\u0430"
    ],
    "wof:name":"Krakornica",
    "wof:placetype":"locality"
},
  "geometry": {"coordinates":[20.69363,41.75577],"type":"Point"}
}