{
  "type": "Feature",
  "properties": {
    "gn:country":"MK",
    "gn:fcode":"PPLA",
    "gn:population":4112,
    "iso:country":"MK",
    "name:bul_x_preferred":[
        "\u0421\u0442\u0430\u0440\u043e \u041d\u0430\u0433\u043e\u0440\u0438\u0447\u0430\u043d\u0435"
    ],
    "name:ceb_x_preferred":[
        "Staro Nagorichane"
    ],
    "name:eng_x_preferred":[
        "Staro Nagori\u010dane"
    ],
    "name:fra_x_preferred":[
        "Staro Nagoritchan\u00e9"
    ],
    "name:hrv_x_preferred":[
        "Staro Nagori\u010dane"
    ],
    "name:hun_x_preferred":[
        "Sztaro Nagoricsane"
    ],
    "name:kat_x_preferred":[
        "\u10e1\u10e2\u10d0\u10e0\u10dd-\u10dc\u10d0\u10d2\u10dd\u10e0\u10d8\u10e9\u10d0\u10dc\u10d4"
    ],
    "name:kor_x_preferred":[
        "\uc2a4\ud0c0\ub85c\ub098\uace0\ub9ac\ucc28\ub124"
    ],
    "name:mkd_x_preferred":[
        "\u0421\u0442\u0430\u0440\u043e \u041d\u0430\u0433\u043e\u0440\u0438\u0447\u0430\u043d\u0435"
    ],
    "name:nan_x_preferred":[
        "Staro Nagoritchan\u00e9"
    ],
    "name:nld_x_preferred":[
        "Staro Nagori\u010dane"
    ],
    "name:spa_x_preferred":[
        "Staro Nagori\u010dane"
    ],
    "name:sqi_x_preferred":[
        "Nagori\u00e7i i Vjet\u00ebr"
    ],
    "name:srp_x_preferred":[
        "\u0421\u0442\u0430\u0440\u043e \u041d\u0430\u0433\u043e\u0440\u0438\u0447\u0430\u043d\u043e"
    ],
    "name:swe_x_preferred":[
        "Staro Nagori\u010dane"
    ],
    "name:tur_x_preferred":[
        "Staro Nagori\u010dane"
    ],
    "name:ukr_x_preferred":[
        "\u0421\u0442\u0430\u0440\u043e-\u041d\u0430\u0433\u043e\u0440\u0438\u0447\u0430\u043d\u0435"
    ],
    "name:und_x_variant":[
        "Nagori\u00e7an i Vjet\u00ebr"
    ],
    "qs:name":"\u0421\u0442\u0430\u0440\u043e \u041d\u0430\u0433\u043e\u0440\u0438\u0447\u0430\u043d\u0435",
    "qs:photos_9r":0,
    "qs:photos_sr":0,
    "qs:pop_sr":"4",
    "wd:wordcount":235,
    "wof:name":"\u0421\u0442\u0430\u0440\u043e \u041d\u0430\u0433\u043e\u0440\u0438\u0447\u0430\u043d\u0435",
    "wof:placetype":"locality",
    "wof:population":4112
},
  "geometry": {"coordinates":[21.82861,42.19806],"type":"Point"}
}