{
  "type": "Feature",
  "properties": {
    "gn:admin1_code":"51",
    "gn:asciiname":"Vrbica",
    "gn:country_code":"MK",
    "gn:dem":1058,
    "gn:feature_class":"P",
    "gn:feature_code":"PPL",
    "gn:name":"Vrbica",
    "gn:population":0,
    "gn:timezone":"Europe/Skopje",
    "iso:country":"MK",
    "name:mkd_x_preferred":[
        "Vrbica"
    ],
    "name:mkd_x_variant":[
        "\u0412\u0440\u0431\u0438\u0446\u0430"
    ],
    "wof:name":"Vrbica",
    "wof:placetype":"locality"
},
  "geometry": {"coordinates":[22.16588,42.10772],"type":"Point"}
}