{
  "type": "Feature",
  "properties": {
    "gn:country":"MK",
    "gn:fcode":"PPL",
    "gn:population":281,
    "iso:country":"MK",
    "name:mkd_x_preferred":[
        "\u0411\u0443\u043d\u0430\u0440\u045f\u0438\u043a"
    ],
    "name:srp_x_preferred":[
        "Bunard\u017eik"
    ],
    "qs:name":"\u0411\u0443\u043d\u0430\u0440\u045f\u0438\u043a",
    "qs:photos_9r":0,
    "qs:photos_sr":0,
    "qs:pop_sr":"2",
    "wof:name":"\u0411\u0443\u043d\u0430\u0440\u045f\u0438\u043a",
    "wof:placetype":"locality",
    "wof:population":281
},
  "geometry": {"coordinates":[21.61694,41.99333],"type":"Point"}
}