{
  "type": "Feature",
  "properties": {
    "gn:country":"MK",
    "gn:fcode":"PPL",
    "gn:pop":194,
    "iso:country":"MK",
    "name:alb_x_preferred":[
        "Babina"
    ],
    "name:bul_x_preferred":[
        "\u0411\u0430\u0431\u0438\u043d\u043e"
    ],
    "name:eng_x_preferred":[
        "Babino"
    ],
    "name:fre_x_preferred":[
        "Babino"
    ],
    "name:hun_x_preferred":[
        "Babino"
    ],
    "name:mac_x_preferred":[
        "\u0411\u0430\u0431\u0438\u043d\u043e"
    ],
    "name:mkd_x_preferred":[
        "Babino"
    ],
    "name:mkd_x_variant":[
        "\u0411\u0430\u0431\u0438\u043d\u043e"
    ],
    "name:nan_x_preferred":[
        "Babino"
    ],
    "name:pol_x_preferred":[
        "Babino"
    ],
    "name:srp_x_preferred":[
        "\u0411\u0430\u0431\u0438\u043d\u043e"
    ],
    "qs:name":"Babino",
    "qs:photos_9r":0,
    "qs:photos_sr":0,
    "qs:pop_sr":"1",
    "wof:name":"Babino",
    "wof:placetype":"locality",
    "wof:population":194
},
  "geometry": {"coordinates":[21.07972,41.29944],"type":"Point"}
}