{
  "type": "Feature",
  "properties": {
    "gn:admin1_code":"11",
    "gn:asciiname":"Robovo",
    "gn:country_code":"MK",
    "gn:dem":218,
    "gn:feature_class":"P",
    "gn:feature_code":"PPL",
    "gn:name":"Robovo",
    "gn:population":0,
    "gn:timezone":"Europe/Skopje",
    "iso:country":"MK",
    "name:bul_x_preferred":[
        "\u0420\u043e\u0431\u043e\u0432\u043e"
    ],
    "name:fra_x_preferred":[
        "Robovo"
    ],
    "name:hun_x_preferred":[
        "Robovo"
    ],
    "name:mkd_x_preferred":[
        "Robovo"
    ],
    "name:mkd_x_variant":[
        "\u0420\u043e\u0431\u043e\u0432\u043e"
    ],
    "name:sqi_x_preferred":[
        "Robova"
    ],
    "name:srp_x_preferred":[
        "\u0420\u043e\u0431\u043e\u0432\u043e"
    ],
    "wof:name":"Robovo",
    "wof:placetype":"locality"
},
  "geometry": {"coordinates":[22.70744,41.43481],"type":"Point"}
}