{
  "type": "Feature",
  "properties": {
    "gn:admin1_code":"97",
    "gn:asciiname":"Pasinci",
    "gn:country_code":"MK",
    "gn:dem":393,
    "gn:feature_class":"P",
    "gn:feature_code":"PPL",
    "gn:name":"Pa\u0161inci",
    "gn:population":0,
    "gn:timezone":"Europe/Skopje",
    "iso:country":"MK",
    "name:mkd_x_preferred":[
        "Pa\u0161inci"
    ],
    "name:mkd_x_variant":[
        "\u041f\u0430\u0448\u0438\u043d\u0446\u0438"
    ],
    "wof:name":"Pasinci",
    "wof:placetype":"locality"
},
  "geometry": {"coordinates":[21.84138,42.23037],"type":"Point"}
}