{
  "type": "Feature",
  "properties": {
    "gn:admin1_code":"85",
    "gn:asciiname":"Baba Angina Maala",
    "gn:country_code":"MK",
    "gn:dem":1113,
    "gn:feature_class":"P",
    "gn:feature_code":"PPL",
    "gn:name":"Baba An\u01f5ina Maala",
    "gn:population":0,
    "gn:timezone":"Europe/Skopje",
    "iso:country":"MK",
    "name:mkd_x_preferred":[
        "Baba An\u01f5ina Maala"
    ],
    "name:mkd_x_variant":[
        "\u0411\u0430\u0431\u0430 \u0410\u043d\u0453\u0438\u043d\u0430 \u041c\u0430\u0430\u043b\u0430"
    ],
    "wof:name":"Baba Angina Maala",
    "wof:placetype":"locality"
},
  "geometry": {"coordinates":[22.19478,42.24404000000001],"type":"Point"}
}