{
  "type": "Feature",
  "properties": {
    "gn:country":"MK",
    "gn:fcode":"PPL",
    "gn:pop":965,
    "iso:country":"MK",
    "name:bul_x_preferred":[
        "\u041b\u044e\u0431\u043e\u0439\u043d\u043e"
    ],
    "name:ceb_x_preferred":[
        "Ljubojno"
    ],
    "name:eng_x_preferred":[
        "Ljubojno"
    ],
    "name:epo_x_preferred":[
        "Ljubojno"
    ],
    "name:fra_x_preferred":[
        "Lyouboyno"
    ],
    "name:hsb_x_preferred":[
        "Ljubojno"
    ],
    "name:mkd_x_preferred":[
        "\u0409\u0443\u0431\u043e\u0458\u043d\u043e"
    ],
    "name:nan_x_preferred":[
        "Lyouboyno"
    ],
    "name:nld_x_preferred":[
        "Ljubojno"
    ],
    "name:por_x_preferred":[
        "Ljubojno"
    ],
    "name:sqi_x_preferred":[
        "Lubonja"
    ],
    "name:srp_x_preferred":[
        "\u0409\u0443\u0431\u043e\u0458\u043d\u043e"
    ],
    "name:swe_x_preferred":[
        "Ljubojno"
    ],
    "name:unk_x_variant":[
        "Ljubojna"
    ],
    "qs:name":"Ljubojno",
    "qs:name_adm0":"Macedonia",
    "qs:name_adm1":"Resen",
    "qs:photos_9k":1,
    "qs:photos_9r":3,
    "qs:photos_all":95,
    "qs:photos_sr":0,
    "qs:placetype":"Town",
    "qs:pop_sr":"2",
    "wd:elevation":923.0,
    "wd:wordcount":167,
    "wof:name":"Ljubojno",
    "wof:placetype":"locality",
    "wof:population":965
},
  "geometry": {"coordinates":[21.14083,40.89417],"type":"Point"}
}