{
  "type": "Feature",
  "properties": {
    "gn:country":"MK",
    "gn:fcode":"PPL",
    "gn:pop":68,
    "iso:country":"MK",
    "name:mkd_x_preferred":[
        "\u0411\u0443\u0441\u0438\u043b\u0446\u0438"
    ],
    "name:unk_x_variant":[
        "Busilca"
    ],
    "qs:name":"Busilci",
    "qs:photos_9r":0,
    "qs:photos_sr":0,
    "qs:pop_sr":"1",
    "wd:wordcount":194,
    "wof:name":"Busilci",
    "wof:placetype":"locality",
    "wof:population":68
},
  "geometry": {"coordinates":[21.70389,41.62306],"type":"Point"}
}