{
  "type": "Feature",
  "properties": {
    "gn:country":"MK",
    "gn:fcode":"PPL",
    "gn:population":71,
    "iso:country":"MK",
    "name:bul_x_preferred":[
        "\u0416\u0430\u0431\u044f\u043d\u0438"
    ],
    "name:deu_x_preferred":[
        "\u017dabjani"
    ],
    "name:eng_x_preferred":[
        "\u017dabjani"
    ],
    "name:fra_x_preferred":[
        "Jabyani"
    ],
    "name:hun_x_preferred":[
        "Zsabjani"
    ],
    "name:mkd_x_preferred":[
        "\u017dabjani"
    ],
    "name:mkd_x_variant":[
        "\u0416\u0430\u0431\u0458\u0430\u043d\u0438"
    ],
    "name:nan_x_preferred":[
        "Jabyani"
    ],
    "name:sqi_x_preferred":[
        "Zhabjani"
    ],
    "name:srp_x_preferred":[
        "\u0416\u0430\u0431\u0458\u0430\u043d\u0438"
    ],
    "qs:name":"\u017dabjani",
    "qs:photos_9r":0,
    "qs:photos_sr":0,
    "qs:pop_sr":"1",
    "wd:wordcount":37,
    "wof:name":"\u017dabjani",
    "wof:placetype":"locality",
    "wof:population":71
},
  "geometry": {"coordinates":[21.38083,41.45306],"type":"Point"}
}