{
  "type": "Feature",
  "properties": {
    "gn:country":"MK",
    "gn:fcode":"PPL",
    "gn:pop":73,
    "iso:country":"MK",
    "name:alb_x_preferred":[
        "Bellovodica"
    ],
    "name:bar_x_preferred":[
        "Belovodica"
    ],
    "name:bul_x_preferred":[
        "\u0411\u0435\u043b\u043e\u0432\u043e\u0434\u0438\u0446\u0430"
    ],
    "name:cat_x_preferred":[
        "Belovodica"
    ],
    "name:cze_x_preferred":[
        "Belovodica"
    ],
    "name:dan_x_preferred":[
        "Belovodica"
    ],
    "name:dut_x_preferred":[
        "Belovodica"
    ],
    "name:eng_x_preferred":[
        "Belovodica"
    ],
    "name:epo_x_preferred":[
        "Belovodica"
    ],
    "name:fin_x_preferred":[
        "Belovodica"
    ],
    "name:fre_x_preferred":[
        "Belovoditsa"
    ],
    "name:ger_x_preferred":[
        "Belovodica"
    ],
    "name:gla_x_preferred":[
        "Belovodica"
    ],
    "name:glg_x_preferred":[
        "Belovodica"
    ],
    "name:gsw_x_preferred":[
        "Belovodica"
    ],
    "name:hrv_x_preferred":[
        "Belovodica"
    ],
    "name:hun_x_preferred":[
        "Belovodica"
    ],
    "name:ice_x_preferred":[
        "Belovodica"
    ],
    "name:ind_x_preferred":[
        "Belovodica"
    ],
    "name:ita_x_preferred":[
        "Belovodica"
    ],
    "name:ltz_x_preferred":[
        "Belovodica"
    ],
    "name:mac_x_preferred":[
        "\u0411\u0435\u043b\u043e\u0432\u043e\u0434\u0438\u0446\u0430"
    ],
    "name:may_x_preferred":[
        "Belovodica"
    ],
    "name:min_x_preferred":[
        "Belovodica"
    ],
    "name:mkd_x_preferred":[
        "\u0411\u0435\u043b\u043e\u0432\u043e\u0434\u0438\u0446\u0430"
    ],
    "name:nds_x_preferred":[
        "Belovodica"
    ],
    "name:nno_x_preferred":[
        "Belovodica"
    ],
    "name:nob_x_preferred":[
        "Belovodica"
    ],
    "name:pol_x_preferred":[
        "Belovodica"
    ],
    "name:por_x_preferred":[
        "Belovodica"
    ],
    "name:rum_x_preferred":[
        "Belovodica"
    ],
    "name:slo_x_preferred":[
        "Belovodica"
    ],
    "name:slv_x_preferred":[
        "Belovodica"
    ],
    "name:spa_x_preferred":[
        "Belovodica"
    ],
    "name:srp_x_preferred":[
        "\u0411\u0435\u043b\u043e\u0432\u043e\u0434\u0438\u0446\u0430"
    ],
    "name:swe_x_preferred":[
        "Belovodica"
    ],
    "name:unk_x_variant":[
        "Bela Vodica"
    ],
    "qs:name":"Belovodica",
    "qs:photos_9r":0,
    "qs:photos_sr":0,
    "qs:pop_sr":"1",
    "wd:wordcount":30,
    "wof:name":"Belovodica",
    "wof:placetype":"locality",
    "wof:population":73
},
  "geometry": {"coordinates":[21.70361,41.33667],"type":"Point"}
}