{
  "type": "Feature",
  "properties": {
    "gn:country":"MK",
    "gn:fcode":"PPL",
    "gn:pop":1243,
    "iso:country":"MK",
    "name:bul_x_preferred":[
        "\u0411\u0443\u0447\u0438\u043d"
    ],
    "name:deu_x_preferred":[
        "Bu\u010din"
    ],
    "name:eng_x_preferred":[
        "Bu\u010din"
    ],
    "name:fra_x_preferred":[
        "Boutchin"
    ],
    "name:mkd_x_preferred":[
        "\u0411\u0443\u0447\u0438\u043d"
    ],
    "name:nld_x_preferred":[
        "Bu\u010din"
    ],
    "name:sqi_x_preferred":[
        "Bu\u00e7ini"
    ],
    "name:srp_x_preferred":[
        "\u0411\u0443\u0447\u0438\u043d"
    ],
    "name:swe_x_preferred":[
        "Bu\u010din"
    ],
    "qs:name":"Bu\u010din",
    "qs:name_adm0":"Macedonia",
    "qs:name_adm1":"Kru\u0161evo",
    "qs:photos_9r":0,
    "qs:photos_sr":0,
    "qs:placetype":"Town",
    "qs:pop_sr":"3",
    "wd:elevation":604.0,
    "wd:wordcount":97,
    "wof:name":"Bu\u010din",
    "wof:placetype":"locality",
    "wof:population":1243
},
  "geometry": {"coordinates":[21.31667,41.27472],"type":"Point"}
}