{
  "type": "Feature",
  "properties": {
    "gn:admin1_code":"98",
    "gn:asciiname":"Baltalija",
    "gn:country_code":"MK",
    "gn:dem":347,
    "gn:feature_class":"P",
    "gn:feature_code":"PPL",
    "gn:name":"Baltalija",
    "gn:population":0,
    "gn:timezone":"Europe/Skopje",
    "iso:country":"MK",
    "name:mkd_x_preferred":[
        "Baltalija"
    ],
    "name:mkd_x_variant":[
        "\u0411\u0430\u043b\u0442\u0430\u043b\u0438\u0458\u0430"
    ],
    "wof:name":"Baltalija",
    "wof:placetype":"locality"
},
  "geometry": {"coordinates":[22.23639,41.65194],"type":"Point"}
}