{
  "type": "Feature",
  "properties": {
    "gn:admin1_code":"33",
    "gn:asciiname":"Negorci",
    "gn:country_code":"MK",
    "gn:dem":79,
    "gn:feature_class":"P",
    "gn:feature_code":"PPL",
    "gn:name":"Negorci",
    "gn:population":0,
    "gn:timezone":"Europe/Skopje",
    "iso:country":"MK",
    "name:bul_x_preferred":[
        "\u041d\u0435\u0433\u043e\u0440\u0446\u0438"
    ],
    "name:ceb_x_preferred":[
        "Negorci"
    ],
    "name:fra_x_preferred":[
        "Negortsi"
    ],
    "name:hun_x_preferred":[
        "Negorci"
    ],
    "name:mkd_x_preferred":[
        "Negorci"
    ],
    "name:mkd_x_variant":[
        "\u041d\u0435\u0433\u043e\u0440\u0446\u0438"
    ],
    "name:sqi_x_preferred":[
        "Negorca"
    ],
    "name:srp_x_preferred":[
        "\u041d\u0435\u0433\u043e\u0440\u0446\u0438"
    ],
    "name:swe_x_preferred":[
        "Negorci"
    ],
    "wof:name":"Negorci",
    "wof:placetype":"locality"
},
  "geometry": {"coordinates":[22.47734,41.18402],"type":"Point"}
}