{
  "type": "Feature",
  "properties": {
    "gn:admin1_code":"22",
    "gn:asciiname":"Parastjel",
    "gn:country_code":"MK",
    "gn:dem":738,
    "gn:feature_class":"P",
    "gn:feature_code":"PPL",
    "gn:name":"Parastjel",
    "gn:population":0,
    "gn:timezone":"Europe/Skopje",
    "iso:country":"MK",
    "name:mkd_x_preferred":[
        "Parastjel"
    ],
    "name:mkd_x_variant":[
        "\u041f\u0430\u0440\u0430\u0441\u0442\u0458\u0435\u043b"
    ],
    "wof:name":"Parastjel",
    "wof:placetype":"locality"
},
  "geometry": {"coordinates":[22.72315,42.02385],"type":"Point"}
}