{
  "type": "Feature",
  "properties": {
    "gn:admin1_code":"D5",
    "gn:asciiname":"Raotince",
    "gn:country_code":"MK",
    "gn:dem":388,
    "gn:feature_class":"P",
    "gn:feature_code":"PPL",
    "gn:name":"Raotince",
    "gn:population":0,
    "gn:timezone":"Europe/Skopje",
    "iso:country":"MK",
    "name:bul_x_preferred":[
        "\u0420\u0430\u043e\u0442\u0438\u043d\u0446\u0435"
    ],
    "name:ceb_x_preferred":[
        "Raotince"
    ],
    "name:fra_x_preferred":[
        "Raotints\u00e9"
    ],
    "name:mkd_x_preferred":[
        "\u0420\u0430\u043e\u0442\u0438\u043d\u0446\u0435"
    ],
    "name:mkd_x_variant":[
        "Rotince",
        "\u0420\u043e\u0442\u0438\u043d\u0446\u0435"
    ],
    "name:sqi_x_preferred":[
        "Rotinca"
    ],
    "name:srp_x_preferred":[
        "\u0420\u0430\u043e\u0442\u0438\u043d\u0446\u0435"
    ],
    "name:swe_x_preferred":[
        "Raotince"
    ],
    "name:und_x_variant":[
        "Rastince",
        "Raotince"
    ],
    "wof:name":"Raotince",
    "wof:placetype":"locality"
},
  "geometry": {"coordinates":[21.14341,42.06117],"type":"Point"}
}