{
  "type": "Feature",
  "properties": {
    "iso:country":"MK",
    "qs:name":"Bezmisth",
    "qs:name_adm0":"Macedonia",
    "qs:name_adm1":"Ohrid",
    "qs:photos":37,
    "qs:photos_1k":7,
    "qs:photos_9k":1,
    "qs:photos_9r":2,
    "qs:photos_all":37,
    "qs:photos_sr":2,
    "qs:placetype":"Town",
    "qs:pop_sr":"0",
    "wof:name":"Bezmisth",
    "wof:placetype":"locality"
},
  "geometry": {"coordinates":[20.7621,40.929077],"type":"Point"}
}