{
  "type": "Feature",
  "properties": {
    "gn:country":"MK",
    "gn:fcode":"PPL",
    "gn:pop":157,
    "iso:country":"MK",
    "name:mkd_x_preferred":[
        "\u040c\u0430\u0444\u0430"
    ],
    "name:mkd_x_variant":[
        "\u1e30afa"
    ],
    "name:unk_x_variant":[
        "Kafa"
    ],
    "qs:name":"\u0106afa",
    "qs:photos_9r":0,
    "qs:photos_sr":0,
    "qs:pop_sr":"1",
    "wof:name":"\u0106afa",
    "wof:placetype":"locality",
    "wof:population":157
},
  "geometry": {"coordinates":[21.02028,41.65722],"type":"Point"}
}