{
  "type": "Feature",
  "properties": {
    "gn:admin1_code":"98",
    "gn:asciiname":"Vrsakovo",
    "gn:country_code":"MK",
    "gn:dem":307,
    "gn:feature_class":"P",
    "gn:feature_code":"PPL",
    "gn:name":"Vrsakovo",
    "gn:population":0,
    "gn:timezone":"Europe/Skopje",
    "iso:country":"MK",
    "name:mkd_x_preferred":[
        "Vrsakovo"
    ],
    "name:mkd_x_variant":[
        "\u0412\u0440\u0441\u0430\u043a\u043e\u0432\u043e"
    ],
    "wof:name":"Vrsakovo",
    "wof:placetype":"locality"
},
  "geometry": {"coordinates":[22.11986,41.81752],"type":"Point"}
}