{
  "type": "Feature",
  "properties": {
    "gn:admin1_code":"83",
    "gn:asciiname":"Dreveno",
    "gn:country_code":"MK",
    "gn:dem":630,
    "gn:feature_class":"P",
    "gn:feature_code":"PPL",
    "gn:name":"Dreveno",
    "gn:population":0,
    "gn:timezone":"Europe/Skopje",
    "iso:country":"MK",
    "name:mkd_x_preferred":[
        "Dreveno"
    ],
    "name:mkd_x_variant":[
        "\u0414\u0440\u0435\u0432\u0435\u043d\u043e"
    ],
    "wof:name":"Dreveno",
    "wof:placetype":"locality"
},
  "geometry": {"coordinates":[22.21104,42.00809],"type":"Point"}
}