{
  "type": "Feature",
  "properties": {
    "gn:country":"MK",
    "gn:fcode":"PPL",
    "gn:pop":165,
    "iso:country":"MK",
    "name:alb_x_preferred":[
        "Magarova"
    ],
    "name:bul_x_preferred":[
        "\u041c\u0430\u0433\u0430\u0440\u0435\u0432\u043e"
    ],
    "name:dut_x_preferred":[
        "Magarevo"
    ],
    "name:eng_x_preferred":[
        "Magarevo"
    ],
    "name:fre_x_preferred":[
        "Magarevo"
    ],
    "name:hun_x_preferred":[
        "Magarevo"
    ],
    "name:mac_x_preferred":[
        "\u041c\u0430\u0433\u0430\u0440\u0435\u0432\u043e"
    ],
    "name:mkd_x_preferred":[
        "\u041c\u0430\u0433\u0430\u0440\u0435\u0432\u043e"
    ],
    "name:pol_x_preferred":[
        "Magarewo"
    ],
    "name:srp_x_preferred":[
        "\u041c\u0430\u0433\u0430\u0440\u0435\u0432\u043e"
    ],
    "name:swe_x_preferred":[
        "Magarevo"
    ],
    "qs:name":"Magarevo",
    "qs:photos_9r":0,
    "qs:photos_sr":0,
    "qs:pop_sr":"1",
    "wd:wordcount":60,
    "wof:name":"Magarevo",
    "wof:placetype":"locality",
    "wof:population":165
},
  "geometry": {"coordinates":[21.23694,41.0425],"type":"Point"}
}