{
  "type": "Feature",
  "properties": {
    "gn:admin1_code":"22",
    "gn:asciiname":"Bumbarska Maala",
    "gn:country_code":"MK",
    "gn:dem":783,
    "gn:feature_class":"P",
    "gn:feature_code":"PPL",
    "gn:name":"Bumbarska Maala",
    "gn:population":0,
    "gn:timezone":"Europe/Skopje",
    "iso:country":"MK",
    "name:mkd_x_preferred":[
        "Bumbarska Maala"
    ],
    "name:mkd_x_variant":[
        "\u0411\u0443\u043c\u0431\u0430\u0440\u0441\u043a\u0430 \u041c\u0430\u0430\u043b\u0430"
    ],
    "wof:name":"Bumbarska Maala",
    "wof:placetype":"locality"
},
  "geometry": {"coordinates":[22.6709,41.94682],"type":"Point"}
}