{
  "type": "Feature",
  "properties": {
    "gn:admin1_code":"59",
    "gn:admin2_code":"Kosovo",
    "gn:asciiname":"Dravska Maala",
    "gn:country_code":"MK",
    "gn:dem":1118,
    "gn:feature_class":"P",
    "gn:feature_code":"PPL",
    "gn:name":"Dravska Maala",
    "gn:population":0,
    "gn:timezone":"Europe/Skopje",
    "iso:country":"MK",
    "name:mkd_x_preferred":[
        "\u0414\u0440\u0430\u0432\u0441\u043a\u0430 \u041c\u0430\u0430\u043b\u0430"
    ],
    "name:srp_x_preferred":[
        "Dravska Maala"
    ],
    "name:und_x_variant":[
        "Dravska Mala",
        "Dravska Mahala"
    ],
    "wof:name":"Dravska Maala",
    "wof:placetype":"locality"
},
  "geometry": {"coordinates":[21.53336,42.16076],"type":"Point"}
}