{
  "type": "Feature",
  "properties": {
    "gn:admin1_code":"D7",
    "gn:asciiname":"Zdravkovci",
    "gn:country_code":"MK",
    "gn:dem":586,
    "gn:feature_class":"P",
    "gn:feature_code":"PPL",
    "gn:name":"Zdravkovci",
    "gn:population":0,
    "gn:timezone":"Europe/Skopje",
    "iso:country":"MK",
    "name:mkd_x_preferred":[
        "Zdravkovci"
    ],
    "name:mkd_x_variant":[
        "\u0417\u0434\u0440\u0430\u0432\u043a\u043e\u0432\u0446\u0438"
    ],
    "wof:name":"Zdravkovci",
    "wof:placetype":"locality"
},
  "geometry": {"coordinates":[21.94711,42.05388],"type":"Point"}
}