{
  "type": "Feature",
  "properties": {
    "gn:admin1_code":"51",
    "gn:asciiname":"Gorna Maala",
    "gn:country_code":"MK",
    "gn:dem":558,
    "gn:feature_class":"P",
    "gn:feature_code":"PPL",
    "gn:name":"Gorna Maala",
    "gn:population":0,
    "gn:timezone":"Europe/Skopje",
    "iso:country":"MK",
    "name:mkd_x_preferred":[
        "Gorna Maala"
    ],
    "name:mkd_x_variant":[
        "\u0413\u043e\u0440\u043d\u0430 \u041c\u0430\u0430\u043b\u0430"
    ],
    "wof:name":"Gorna Maala",
    "wof:placetype":"locality"
},
  "geometry": {"coordinates":[22.12256,42.09153],"type":"Point"}
}