{
  "type": "Feature",
  "properties": {
    "gn:admin1_code":"00",
    "gn:asciiname":"Smiljkovci",
    "gn:cc2":"MK",
    "gn:country_code":"MK",
    "gn:dem":281,
    "gn:feature_class":"P",
    "gn:feature_code":"PPL",
    "gn:name":"Smiljkovci",
    "gn:population":0,
    "gn:timezone":"Europe/Skopje",
    "iso:country":"MK",
    "name:und_x_variant":[
        "Smilkovci",
        "Smiljkovci"
    ],
    "wof:name":"Smiljkovci",
    "wof:placetype":"locality"
},
  "geometry": {"coordinates":[21.49444,42.0375],"type":"Point"}
}