{
  "type": "Feature",
  "properties": {
    "gn:admin1_code":"62",
    "gn:asciiname":"Palamarska Maala",
    "gn:country_code":"MK",
    "gn:dem":544,
    "gn:feature_class":"P",
    "gn:feature_code":"PPL",
    "gn:name":"Palamarska Maala",
    "gn:population":0,
    "gn:timezone":"Europe/Skopje",
    "iso:country":"MK",
    "name:mkd_x_preferred":[
        "Palamarska Maala"
    ],
    "name:mkd_x_variant":[
        "\u041f\u0430\u043b\u0430\u043c\u0430\u0440\u0441\u043a\u0430 \u041c\u0430\u0430\u043b\u0430"
    ],
    "wof:name":"Palamarska Maala",
    "wof:placetype":"locality"
},
  "geometry": {"coordinates":[22.62796,42.01011],"type":"Point"}
}