{
  "type": "Feature",
  "properties": {
    "gn:country":"MK",
    "gn:fcode":"PPLA",
    "gn:population":23096,
    "iso:country":"MK",
    "name:bul_x_preferred":[
        "\u0422\u0435\u0430\u0440\u0446\u0435"
    ],
    "name:ceb_x_preferred":[
        "Tearce"
    ],
    "name:ces_x_preferred":[
        "Tearce"
    ],
    "name:deu_x_preferred":[
        "Tearce"
    ],
    "name:eng_x_preferred":[
        "Tearce"
    ],
    "name:epo_x_preferred":[
        "Tearce"
    ],
    "name:fra_x_preferred":[
        "T\u00e9arts\u00e9"
    ],
    "name:heb_x_preferred":[
        "\u05d8\u05d9\u05d0\u05e8\u05e6\u05d4"
    ],
    "name:hun_x_preferred":[
        "Tearce"
    ],
    "name:kat_x_preferred":[
        "\u10e2\u10d4\u10d0\u10e0\u10ea\u10d4"
    ],
    "name:mkd_x_preferred":[
        "\u0422\u0435\u0430\u0440\u0446\u0435"
    ],
    "name:nan_x_preferred":[
        "T\u00e9arts\u00e9"
    ],
    "name:nld_x_preferred":[
        "Tearce"
    ],
    "name:pol_x_preferred":[
        "Tearce"
    ],
    "name:rus_x_preferred":[
        "\u0422\u0435\u0430\u0440\u0446\u0435"
    ],
    "name:sqi_x_preferred":[
        "Tearca"
    ],
    "name:srp_x_preferred":[
        "\u0422\u0435\u0430\u0440\u0446\u0435"
    ],
    "name:swe_x_preferred":[
        "Tearce"
    ],
    "name:tur_x_preferred":[
        "Tear\u00e7e"
    ],
    "name:ukr_x_preferred":[
        "\u0422\u0435\u0430\u0440\u0446\u0435"
    ],
    "qs:name":"Tearce",
    "qs:name_adm0":"Macedonia",
    "qs:name_adm1":"Tearce",
    "qs:photos_9k":1,
    "qs:photos_9r":1,
    "qs:photos_all":10,
    "qs:photos_sr":0,
    "qs:placetype":"Town",
    "qs:pop_sr":"7",
    "wd:wordcount":133,
    "wof:name":"Tearce",
    "wof:placetype":"locality",
    "wof:population":23096
},
  "geometry": {"coordinates":[21.0525,42.07444],"type":"Point"}
}