{
  "type": "Feature",
  "properties": {
    "gn:admin1_code":"22",
    "gn:asciiname":"Iliovo",
    "gn:country_code":"MK",
    "gn:dem":529,
    "gn:feature_class":"P",
    "gn:feature_code":"PPLL",
    "gn:name":"Iliovo",
    "gn:population":0,
    "gn:timezone":"Europe/Skopje",
    "iso:country":"MK",
    "name:mkd_x_preferred":[
        "\u0418\u043b\u0438\u043e\u0432\u043e"
    ],
    "name:und_x_variant":[
        "Ilijevo",
        "Ilovo",
        "Iliovo"
    ],
    "wof:name":"Iliovo",
    "wof:placetype":"locality"
},
  "geometry": {"coordinates":[22.64237,41.99069],"type":"Point"}
}