{
  "type": "Feature",
  "properties": {
    "gn:admin1_code":"51",
    "gn:asciiname":"Lazinci",
    "gn:country_code":"MK",
    "gn:dem":452,
    "gn:feature_class":"P",
    "gn:feature_code":"PPL",
    "gn:name":"Lazinci",
    "gn:population":0,
    "gn:timezone":"Europe/Skopje",
    "iso:country":"MK",
    "name:mkd_x_preferred":[
        "Lazinci"
    ],
    "name:mkd_x_variant":[
        "\u041b\u0430\u0437\u0438\u043d\u0446\u0438"
    ],
    "wof:name":"Lazinci",
    "wof:placetype":"locality"
},
  "geometry": {"coordinates":[22.10794,42.13429],"type":"Point"}
}