{
  "type": "Feature",
  "properties": {
    "gn:admin1_code":"51",
    "gn:asciiname":"Karamanska Maala",
    "gn:country_code":"MK",
    "gn:dem":587,
    "gn:feature_class":"P",
    "gn:feature_code":"PPL",
    "gn:name":"Karamanska Maala",
    "gn:population":0,
    "gn:timezone":"Europe/Skopje",
    "iso:country":"MK",
    "name:mkd_x_preferred":[
        "Karamanska Maala"
    ],
    "name:mkd_x_variant":[
        "\u041a\u0430\u0440\u0430\u043c\u0430\u043d\u0441\u043a\u0430 \u041c\u0430\u0430\u043b\u0430"
    ],
    "wof:name":"Karamanska Maala",
    "wof:placetype":"locality"
},
  "geometry": {"coordinates":[22.10651,42.05678],"type":"Point"}
}