{
  "type": "Feature",
  "properties": {
    "gn:country":"MK",
    "gn:fcode":"PPLA",
    "gn:population":3737,
    "iso:country":"MK",
    "name:ceb_x_preferred":[
        "Gradsko"
    ],
    "name:deu_x_preferred":[
        "Gradsko"
    ],
    "name:eng_x_preferred":[
        "Gradsko"
    ],
    "name:fra_x_preferred":[
        "Gradsko"
    ],
    "name:heb_x_preferred":[
        "\u05d2\u05e8\u05d0\u05d3\u05e1\u05e7\u05d5"
    ],
    "name:hun_x_preferred":[
        "Gradsko"
    ],
    "name:kaz_x_preferred":[
        "\u0413\u0440\u0430\u0434\u0441\u043a\u043e"
    ],
    "name:mkd_x_preferred":[
        "\u0413\u0440\u0430\u0434\u0441\u043a\u043e"
    ],
    "name:nld_x_preferred":[
        "Gradsko"
    ],
    "name:rus_x_preferred":[
        "\u0413\u0440\u0430\u0434\u0441\u043a\u043e"
    ],
    "name:swe_x_preferred":[
        "Gradsko"
    ],
    "qs:name":"Gradsko",
    "qs:name_adm0":"Macedonia",
    "qs:name_adm1":"Gradsko",
    "qs:photos":110,
    "qs:photos_1k":22,
    "qs:photos_9k":1,
    "qs:photos_9r":3,
    "qs:photos_all":110,
    "qs:photos_sr":3,
    "qs:placetype":"Town",
    "qs:pop_sr":"4",
    "wd:wordcount":33,
    "wof:name":"Gradsko",
    "wof:placetype":"locality",
    "wof:population":3737
},
  "geometry": {"coordinates":[21.94278,41.5775],"type":"Point"}
}