{
  "type": "Feature",
  "properties": {
    "gn:admin1_code":"51",
    "gn:asciiname":"Dolna Maala",
    "gn:country_code":"MK",
    "gn:dem":437,
    "gn:feature_class":"P",
    "gn:feature_code":"PPL",
    "gn:name":"Dolna Maala",
    "gn:population":0,
    "gn:timezone":"Europe/Skopje",
    "iso:country":"MK",
    "name:mkd_x_preferred":[
        "Dolna Maala"
    ],
    "name:mkd_x_variant":[
        "\u0414\u043e\u043b\u043d\u0430 \u041c\u0430\u0430\u043b\u0430"
    ],
    "name:srp_x_preferred":[
        "Donja Maala"
    ],
    "name:srp_x_variant":[
        "\u0414\u043e\u045a\u0430 \u041c\u0430\u0430\u043b\u0430"
    ],
    "wof:name":"Dolna Maala",
    "wof:placetype":"locality"
},
  "geometry": {"coordinates":[21.96242,42.08228],"type":"Point"}
}