{
  "type": "Feature",
  "properties": {
    "gn:admin1_code":"40",
    "gn:asciiname":"Ebeplija",
    "gn:country_code":"MK",
    "gn:dem":890,
    "gn:feature_class":"P",
    "gn:feature_code":"PPL",
    "gn:name":"Ebeplija",
    "gn:population":0,
    "gn:timezone":"Europe/Skopje",
    "iso:country":"MK",
    "name:mkd_x_preferred":[
        "Ebeplija"
    ],
    "name:mkd_x_variant":[
        "\u0415\u0431\u0435\u043f\u043b\u0438\u0458\u0430"
    ],
    "wof:name":"Ebeplija",
    "wof:placetype":"locality"
},
  "geometry": {"coordinates":[22.36965,41.75998],"type":"Point"}
}