{
  "type": "Feature",
  "properties": {
    "gn:admin1_code":"00",
    "gn:asciiname":"Ljuboten",
    "gn:cc2":"MK",
    "gn:country_code":"MK",
    "gn:dem":643,
    "gn:feature_class":"P",
    "gn:feature_code":"PPL",
    "gn:name":"\u0409\u0443\u0431\u043e\u0442\u0435\u043d",
    "gn:population":0,
    "gn:timezone":"Europe/Skopje",
    "iso:country":"MK",
    "name:mkd_x_preferred":[
        "Luboten"
    ],
    "name:mkd_x_variant":[
        "Ljuboten"
    ],
    "wof:name":"Ljuboten",
    "wof:placetype":"locality"
},
  "geometry": {"coordinates":[21.47167,42.0975],"type":"Point"}
}