{
  "type": "Feature",
  "properties": {
    "gn:admin1_code":"C7",
    "gn:asciiname":"Novake",
    "gn:country_code":"MK",
    "gn:dem":750,
    "gn:feature_class":"P",
    "gn:feature_code":"PPL",
    "gn:name":"Nova\u1e31e",
    "gn:population":0,
    "gn:timezone":"Europe/Skopje",
    "iso:country":"MK",
    "name:mkd_x_preferred":[
        "Nova\u1e31e"
    ],
    "name:mkd_x_variant":[
        "\u041d\u043e\u0432\u0430\u045c\u0435",
        "Novake",
        "\u041d\u043e\u0432\u0430\u043a\u0435"
    ],
    "wof:name":"Novake",
    "wof:placetype":"locality"
},
  "geometry": {"coordinates":[20.915,41.96028],"type":"Point"}
}