{
  "type": "Feature",
  "properties": {
    "gn:admin1_code":"52",
    "gn:asciiname":"Delska Maala",
    "gn:country_code":"MK",
    "gn:dem":1176,
    "gn:feature_class":"P",
    "gn:feature_code":"PPL",
    "gn:name":"Delska Maala",
    "gn:population":0,
    "gn:timezone":"Europe/Skopje",
    "iso:country":"MK",
    "name:mkd_x_preferred":[
        "Delska Maala"
    ],
    "name:mkd_x_variant":[
        "\u0414\u0435\u043b\u0441\u043a\u0430 \u041c\u0430\u0430\u043b\u0430"
    ],
    "wof:name":"Delska Maala",
    "wof:placetype":"locality"
},
  "geometry": {"coordinates":[22.19637,42.3201],"type":"Point"}
}