{
  "type": "Feature",
  "properties": {
    "gn:admin1_code":"62",
    "gn:asciiname":"Stamboliska Maala",
    "gn:country_code":"MK",
    "gn:dem":975,
    "gn:feature_class":"P",
    "gn:feature_code":"PPL",
    "gn:name":"Stamboliska Maala",
    "gn:population":0,
    "gn:timezone":"Europe/Skopje",
    "iso:country":"MK",
    "name:mkd_x_preferred":[
        "Stamboliska Maala"
    ],
    "name:mkd_x_variant":[
        "\u0421\u0442\u0430\u043c\u0431\u043e\u043b\u0438\u0441\u043a\u0430 \u041c\u0430\u0430\u043b\u0430"
    ],
    "wof:name":"Stamboliska Maala",
    "wof:placetype":"locality"
},
  "geometry": {"coordinates":[22.5237,42.02876],"type":"Point"}
}