{
  "type": "Feature",
  "properties": {
    "gn:admin1_code":"52",
    "gn:asciiname":"Puskarska Maala",
    "gn:country_code":"MK",
    "gn:dem":928,
    "gn:feature_class":"P",
    "gn:feature_code":"PPL",
    "gn:name":"Pu\u0161karska Maala",
    "gn:population":0,
    "gn:timezone":"Europe/Skopje",
    "iso:country":"MK",
    "name:mkd_x_preferred":[
        "Pu\u0161karska Maala"
    ],
    "name:mkd_x_variant":[
        "\u041f\u0443\u0448\u043a\u0430\u0440\u0441\u043a\u0430 \u041c\u0430\u0430\u043b\u0430"
    ],
    "wof:name":"Puskarska Maala",
    "wof:placetype":"locality"
},
  "geometry": {"coordinates":[22.30341,42.2209],"type":"Point"}
}