{
  "type": "Feature",
  "properties": {
    "gn:admin1_code":"97",
    "gn:asciiname":"Coljaci",
    "gn:country_code":"MK",
    "gn:dem":446,
    "gn:feature_class":"P",
    "gn:feature_code":"PPL",
    "gn:name":"\u010coljaci",
    "gn:population":0,
    "gn:timezone":"Europe/Skopje",
    "iso:country":"MK",
    "name:mkd_x_preferred":[
        "\u010coljaci"
    ],
    "name:mkd_x_variant":[
        "\u0427\u043e\u0459\u0430\u0446\u0438"
    ],
    "wof:name":"Coljaci",
    "wof:placetype":"locality"
},
  "geometry": {"coordinates":[21.91166,42.1572],"type":"Point"}
}