{
  "type": "Feature",
  "properties": {
    "gn:admin1_code":"97",
    "gn:asciiname":"Mglence",
    "gn:country_code":"MK",
    "gn:dem":692,
    "gn:feature_class":"P",
    "gn:feature_code":"PPL",
    "gn:name":"Mglence",
    "gn:population":0,
    "gn:timezone":"Europe/Belgrade",
    "iso:country":"MK",
    "name:mkd_x_preferred":[
        "\u041c\u0433\u043b\u0435\u043d\u0446\u0435"
    ],
    "name:und_x_variant":[
        "Maglince",
        "Maglence",
        "Mglence"
    ],
    "wof:name":"Mglence",
    "wof:placetype":"locality"
},
  "geometry": {"coordinates":[21.95137,42.33727],"type":"Point"}
}