{
  "type": "Feature",
  "properties": {
    "gn:admin1_code":"22",
    "gn:asciiname":"Kurcii",
    "gn:country_code":"MK",
    "gn:dem":796,
    "gn:feature_class":"P",
    "gn:feature_code":"PPL",
    "gn:name":"\u1e30ur\u010dii",
    "gn:population":0,
    "gn:timezone":"Europe/Skopje",
    "iso:country":"MK",
    "name:mkd_x_preferred":[
        "\u1e30ur\u010dii"
    ],
    "name:mkd_x_variant":[
        "\u040c\u0443\u0440\u0447\u0438\u0438"
    ],
    "wof:name":"Kurcii",
    "wof:placetype":"locality"
},
  "geometry": {"coordinates":[22.79183,41.84963],"type":"Point"}
}