{
  "type": "Feature",
  "properties": {
    "gn:admin1_code":"85",
    "gn:asciiname":"Makoviste Maala",
    "gn:country_code":"MK",
    "gn:dem":691,
    "gn:feature_class":"P",
    "gn:feature_code":"PPL",
    "gn:name":"Makovi\u0161te Maala",
    "gn:population":0,
    "gn:timezone":"Europe/Skopje",
    "iso:country":"MK",
    "name:mkd_x_preferred":[
        "Makovi\u0161te Maala"
    ],
    "name:mkd_x_variant":[
        "\u041c\u0430\u043a\u043e\u0432\u0438\u0448\u0442\u0435 \u041c\u0430\u0430\u043b\u0430"
    ],
    "wof:name":"Makoviste Maala",
    "wof:placetype":"locality"
},
  "geometry": {"coordinates":[22.15177000000001,42.1285],"type":"Point"}
}