{
  "type": "Feature",
  "properties": {
    "gn:admin1_code":"00",
    "gn:asciiname":"Dolno Nerezi",
    "gn:cc2":"MK",
    "gn:country_code":"MK",
    "gn:dem":272,
    "gn:feature_class":"P",
    "gn:feature_code":"PPL",
    "gn:name":"\u0414\u043e\u043b\u043d\u043e \u041d\u0435\u0440\u0435\u0437\u0438",
    "gn:population":0,
    "gn:timezone":"Europe/Skopje",
    "iso:country":"MK",
    "name:und_x_variant":[
        "Dolno Nerez",
        "Dolno Nereze",
        "Dolni Nerezi",
        "Dolno Nerezi"
    ],
    "wof:name":"Dolno Nerezi",
    "wof:placetype":"locality"
},
  "geometry": {"coordinates":[21.37861,41.9975],"type":"Point"}
}