{
  "type": "Feature",
  "properties": {
    "gn:admin1_code":"46",
    "gn:asciiname":"Sokolovci",
    "gn:country_code":"MK",
    "gn:dem":858,
    "gn:feature_class":"P",
    "gn:feature_code":"PPL",
    "gn:name":"Sokolovci",
    "gn:population":0,
    "gn:timezone":"Europe/Skopje",
    "iso:country":"MK",
    "name:mkd_x_preferred":[
        "Sokolovci"
    ],
    "name:mkd_x_variant":[
        "\u0421\u043e\u043a\u043e\u043b\u043e\u0432\u0446\u0438"
    ],
    "wof:name":"Sokolovci",
    "wof:placetype":"locality"
},
  "geometry": {"coordinates":[22.47777,41.96348],"type":"Point"}
}