{
  "type": "Feature",
  "properties": {
    "gn:admin1_code":"97",
    "gn:asciiname":"Balcinci",
    "gn:country_code":"MK",
    "gn:dem":454,
    "gn:feature_class":"P",
    "gn:feature_code":"PPL",
    "gn:name":"Bal\u010dinci",
    "gn:population":0,
    "gn:timezone":"Europe/Skopje",
    "iso:country":"MK",
    "name:mkd_x_preferred":[
        "Bal\u010dinci"
    ],
    "name:mkd_x_variant":[
        "\u0411\u0430\u043b\u0447\u0438\u043d\u0446\u0438"
    ],
    "wof:name":"Balcinci",
    "wof:placetype":"locality"
},
  "geometry": {"coordinates":[21.85757000000001,42.2691],"type":"Point"}
}