{
  "type": "Feature",
  "properties": {
    "gn:country":"MK",
    "gn:fcode":"PPL",
    "gn:pop":37,
    "iso:country":"MK",
    "name:mkd_x_preferred":[
        "Barovo"
    ],
    "name:mkd_x_variant":[
        "\u0411\u0430\u0440\u043e\u0432\u043e"
    ],
    "qs:name":"Barovo",
    "qs:photos_9r":0,
    "qs:photos_sr":0,
    "qs:pop_sr":"1",
    "wd:wordcount":127,
    "wof:name":"Barovo",
    "wof:placetype":"locality",
    "wof:population":37
},
  "geometry": {"coordinates":[21.34484,41.94496],"type":"Point"}
}