{
  "type": "Feature",
  "properties": {
    "gn:country":"MK",
    "gn:fcode":"PPL",
    "gn:pop":37,
    "iso:country":"MK",
    "name:bul_x_preferred":[
        "\u0411\u0430\u0440\u043e\u0432\u043e"
    ],
    "name:eng_x_preferred":[
        "Barovo"
    ],
    "name:fra_x_preferred":[
        "Barovo"
    ],
    "name:kat_x_preferred":[
        "\u10d1\u10d0\u10e0\u10dd\u10d5\u10dd"
    ],
    "name:mkd_x_preferred":[
        "Barovo"
    ],
    "name:mkd_x_variant":[
        "\u0411\u0430\u0440\u043e\u0432\u043e"
    ],
    "name:nan_x_preferred":[
        "Barovo"
    ],
    "name:nld_x_preferred":[
        "Barovo"
    ],
    "name:por_x_preferred":[
        "Barovo"
    ],
    "name:sqi_x_preferred":[
        "Barova"
    ],
    "name:srp_x_preferred":[
        "\u0411\u0430\u0440\u043e\u0432\u043e"
    ],
    "qs:name":"Barovo",
    "qs:photos_9r":0,
    "qs:photos_sr":0,
    "qs:pop_sr":"1",
    "wd:wordcount":127,
    "wof:name":"Barovo",
    "wof:placetype":"locality",
    "wof:population":37
},
  "geometry": {"coordinates":[21.34484,41.94496],"type":"Point"}
}