{
  "type": "Feature",
  "properties": {
    "gn:admin1_code":"69",
    "gn:asciiname":"Kurija",
    "gn:country_code":"MK",
    "gn:dem":152,
    "gn:feature_class":"P",
    "gn:feature_code":"PPL",
    "gn:name":"Kurija",
    "gn:population":0,
    "gn:timezone":"Europe/Skopje",
    "iso:country":"MK",
    "name:mkd_x_preferred":[
        "\u041a\u0443\u0440\u0438\u0458\u0430"
    ],
    "wof:name":"Kurija",
    "wof:placetype":"locality"
},
  "geometry": {"coordinates":[22.01345,41.52623],"type":"Point"}
}