{
  "type": "Feature",
  "properties": {
    "gn:admin1_code":"69",
    "gn:asciiname":"Kurija",
    "gn:country_code":"MK",
    "gn:dem":152,
    "gn:feature_class":"P",
    "gn:feature_code":"PPL",
    "gn:name":"Kurija",
    "gn:population":0,
    "gn:timezone":"Europe/Skopje",
    "iso:country":"MK",
    "name:bul_x_preferred":[
        "\u041a\u0443\u0440\u0438\u044f"
    ],
    "name:ceb_x_preferred":[
        "Kurija"
    ],
    "name:fra_x_preferred":[
        "Kouriya"
    ],
    "name:kat_x_preferred":[
        "\u10d9\u10e3\u10e0\u10d8\u10d0"
    ],
    "name:mkd_x_preferred":[
        "\u041a\u0443\u0440\u0438\u0458\u0430"
    ],
    "name:sqi_x_preferred":[
        "Kuria"
    ],
    "name:srp_x_preferred":[
        "\u041a\u0443\u0440\u0438\u0458\u0430"
    ],
    "name:swe_x_preferred":[
        "Kurija"
    ],
    "wof:name":"Kurija",
    "wof:placetype":"locality"
},
  "geometry": {"coordinates":[22.01345,41.52623],"type":"Point"}
}