{
  "type": "Feature",
  "properties": {
    "gn:country":"MK",
    "gn:fcode":"PPL",
    "gn:pop":4,
    "iso:country":"MK",
    "name:mkd_x_preferred":[
        "\u0427\u0430\u0458\u043b\u0435"
    ],
    "name:unk_x_variant":[
        "\u010caile"
    ],
    "qs:name":"\u010cajle",
    "qs:photos_9r":0,
    "qs:photos_sr":0,
    "qs:pop_sr":"1",
    "wd:wordcount":199,
    "wof:name":"\u010cajle",
    "wof:placetype":"locality",
    "wof:population":4
},
  "geometry": {"coordinates":[20.9325,41.80194],"type":"Point"}
}