{
  "type": "Feature",
  "properties": {
    "gn:admin1_code":"98",
    "gn:asciiname":"Pocivalo",
    "gn:country_code":"MK",
    "gn:dem":936,
    "gn:feature_class":"P",
    "gn:feature_code":"PPL",
    "gn:name":"Po\u010divalo",
    "gn:population":0,
    "gn:timezone":"Europe/Skopje",
    "iso:country":"MK",
    "name:mkd_x_preferred":[
        "Po\u010divalo"
    ],
    "name:mkd_x_variant":[
        "\u041f\u043e\u0447\u0438\u0432\u0430\u043b\u043e"
    ],
    "wof:name":"Pocivalo",
    "wof:placetype":"locality"
},
  "geometry": {"coordinates":[22.38435,41.70473],"type":"Point"}
}