{
  "type": "Feature",
  "properties": {
    "gn:admin1_code":"97",
    "gn:asciiname":"Gazdevci",
    "gn:country_code":"MK",
    "gn:dem":523,
    "gn:feature_class":"P",
    "gn:feature_code":"PPL",
    "gn:name":"Gazdevci",
    "gn:population":0,
    "gn:timezone":"Europe/Skopje",
    "iso:country":"MK",
    "name:mkd_x_preferred":[
        "Gazdevci"
    ],
    "name:mkd_x_variant":[
        "\u0413\u0430\u0437\u0434\u0435\u0432\u0446\u0438"
    ],
    "wof:name":"Gazdevci",
    "wof:placetype":"locality"
},
  "geometry": {"coordinates":[21.98015,42.1332],"type":"Point"}
}