{
  "type": "Feature",
  "properties": {
    "gn:admin1_code":"B4",
    "gn:asciiname":"Klincarite",
    "gn:country_code":"MK",
    "gn:dem":427,
    "gn:feature_class":"P",
    "gn:feature_code":"PPL",
    "gn:name":"Klin\u010darite",
    "gn:population":0,
    "gn:timezone":"Europe/Skopje",
    "iso:country":"MK",
    "name:mkd_x_preferred":[
        "Klin\u010darite"
    ],
    "name:mkd_x_variant":[
        "\u041a\u043b\u0438\u043d\u0447\u0430\u0440\u0438\u0442\u0435"
    ],
    "wof:name":"Klincarite",
    "wof:placetype":"locality"
},
  "geometry": {"coordinates":[22.55871,41.95459],"type":"Point"}
}