{
  "type": "Feature",
  "properties": {
    "gn:admin1_code":"22",
    "gn:asciiname":"Turcinska Maala",
    "gn:country_code":"MK",
    "gn:dem":803,
    "gn:feature_class":"P",
    "gn:feature_code":"PPL",
    "gn:name":"Tur\u010dinska Maala",
    "gn:population":0,
    "gn:timezone":"Europe/Skopje",
    "iso:country":"MK",
    "name:mkd_x_preferred":[
        "Tur\u010dinska Maala"
    ],
    "name:mkd_x_variant":[
        "\u0422\u0443\u0440\u0447\u0438\u043d\u0441\u043a\u0430 \u041c\u0430\u0430\u043b\u0430"
    ],
    "wof:name":"Turcinska Maala",
    "wof:placetype":"locality"
},
  "geometry": {"coordinates":[22.76667,42.02947],"type":"Point"}
}