{
  "type": "Feature",
  "properties": {
    "gn:admin1_code":"F5",
    "gn:asciiname":"Trebenista",
    "gn:country_code":"MK",
    "gn:dem":720,
    "gn:feature_class":"P",
    "gn:feature_code":"PPL",
    "gn:name":"Trebeni\u0161ta",
    "gn:population":0,
    "gn:timezone":"Europe/Skopje",
    "iso:country":"MK",
    "name:bul_x_preferred":[
        "\u0422\u0440\u0435\u0431\u0435\u043d\u0438\u0449\u043a\u0438 \u043d\u0435\u043a\u0440\u043e\u043f\u043e\u043b"
    ],
    "name:ell_x_preferred":[
        "\u03a4\u03c1\u03b5\u03bc\u03c0\u03ad\u03bd\u03b9\u03c3\u03c4\u03b1"
    ],
    "name:mkd_x_preferred":[
        "\u0422\u0440\u0435\u0431\u0435\u043d\u0438\u0448\u0442\u0430"
    ],
    "name:rus_x_preferred":[
        "\u0422\u0440\u0435\u0431\u0435\u043d\u0438\u0448\u0442\u0430"
    ],
    "name:srp_x_preferred":[
        "\u0422\u0440\u0435\u0431\u0435\u043d\u0438\u0448\u0442\u0435"
    ],
    "name:ukr_x_preferred":[
        "\u0422\u0440\u0435\u0431\u0435\u043d\u0438\u0448\u0442\u0430"
    ],
    "name:und_x_variant":[
        "Trebeni\u0161te",
        "Trebeni\u0161ta"
    ],
    "wof:name":"Trebenista",
    "wof:placetype":"locality"
},
  "geometry": {"coordinates":[20.755,41.20639],"type":"Point"}
}