{
  "type": "Feature",
  "properties": {
    "gn:admin1_code":"43",
    "gn:asciiname":"Vidrani",
    "gn:country_code":"MK",
    "gn:dem":826,
    "gn:feature_class":"P",
    "gn:feature_code":"PPL",
    "gn:name":"Vidrani",
    "gn:population":0,
    "gn:timezone":"Europe/Skopje",
    "iso:country":"MK",
    "name:mkd_x_preferred":[
        "Vidrani"
    ],
    "name:mkd_x_variant":[
        "\u0412\u0438\u0434\u0440\u0430\u043d\u0438"
    ],
    "wof:name":"Vidrani",
    "wof:placetype":"locality"
},
  "geometry": {"coordinates":[20.90803,41.45926],"type":"Point"}
}