{
  "type": "Feature",
  "properties": {
    "gn:admin1_code":"97",
    "gn:asciiname":"Petralicani",
    "gn:country_code":"MK",
    "gn:dem":437,
    "gn:feature_class":"P",
    "gn:feature_code":"PPL",
    "gn:name":"Petrali\u010dani",
    "gn:population":0,
    "gn:timezone":"Europe/Skopje",
    "iso:country":"MK",
    "name:mkd_x_preferred":[
        "Petrali\u010dani"
    ],
    "name:mkd_x_variant":[
        "\u041f\u0435\u0442\u0440\u0430\u043b\u0438\u0447\u0430\u043d\u0438"
    ],
    "wof:name":"Petralicani",
    "wof:placetype":"locality"
},
  "geometry": {"coordinates":[21.77166,42.15373],"type":"Point"}
}