{
  "type": "Feature",
  "properties": {
    "gn:country":"MK",
    "gn:fcode":"PPL",
    "gn:pop":200,
    "iso:country":"MK",
    "name:mkd_x_preferred":[
        "Zrkle"
    ],
    "name:mkd_x_variant":[
        "\u0417\u0440\u043a\u043b\u0435"
    ],
    "qs:name":"Zrkle",
    "qs:name_adm0":"Macedonia",
    "qs:name_adm1":"Makedonski Brod",
    "qs:photos_9r":0,
    "qs:photos_sr":0,
    "qs:placetype":"Town",
    "qs:pop_sr":"1",
    "wd:wordcount":302,
    "wof:name":"Zrkle",
    "wof:placetype":"locality",
    "wof:population":200
},
  "geometry": {"coordinates":[21.15083,41.65861],"type":"Point"}
}