{
  "type": "Feature",
  "properties": {
    "gn:country":"MK",
    "gn:fcode":"PPL",
    "gn:population":200,
    "iso:country":"MK",
    "name:bul_x_preferred":[
        "\u0411\u0440\u043e\u0434"
    ],
    "name:ceb_x_preferred":[
        "Makedonski Brod"
    ],
    "name:fra_x_preferred":[
        "Makedonski Brod"
    ],
    "name:hrv_x_preferred":[
        "Op\u0107ina Gostivar"
    ],
    "name:ita_x_preferred":[
        "Makedonski Brod"
    ],
    "name:jpn_x_preferred":[
        "\u30de\u30b1\u30c9\u30f3\u30b9\u30ad\u30fb\u30d6\u30ed\u30c9"
    ],
    "name:kat_x_preferred":[
        "\u10db\u10d0\u10d9\u10d4\u10d3\u10dd\u10dc\u10e1\u10d9\u10d8-\u10d1\u10e0\u10dd\u10d3\u10d8\u10e1 \u10d7\u10d4\u10db\u10d8"
    ],
    "name:kor_x_preferred":[
        "\ub9c8\ucf00\ub3c8\uc2a4\ud0a4\ube0c\ub85c\ub4dc \uc2dc"
    ],
    "name:kor_x_variant":[
        "\ub9c8\ucf00\ub3c8\uc2a4\ud0a4\ube0c\ub85c\ub4dc\uc2dc"
    ],
    "name:lav_x_preferred":[
        "Makedonskij-Brodas pa\u0161vald\u012bba"
    ],
    "name:mkd_x_preferred":[
        "Zrkle"
    ],
    "name:mkd_x_variant":[
        "\u0417\u0440\u043a\u043b\u0435"
    ],
    "name:nld_x_preferred":[
        "Makedonski Brod"
    ],
    "name:nno_x_preferred":[
        "Makedonski Brod"
    ],
    "name:por_x_preferred":[
        "Makedonski Brod"
    ],
    "name:rus_x_preferred":[
        "\u041c\u0430\u043a\u0435\u0434\u043e\u043d\u0441\u043a\u0438-\u0411\u0440\u043e\u0434"
    ],
    "name:swe_x_preferred":[
        "Makedonski Brod"
    ],
    "name:tha_x_preferred":[
        "\u0e40\u0e17\u0e28\u0e1a\u0e32\u0e25\u0e21\u0e40\u0e01\u0e14\u0e2d\u0e19\u0e2a\u0e01\u0e34\u0e1a\u0e23\u0e2d\u0e14"
    ],
    "name:ukr_x_preferred":[
        "\u041c\u0430\u043a\u0435\u0434\u043e\u043d\u0441\u044c\u043a\u0438\u0439 \u0411\u0440\u043e\u0434"
    ],
    "name:zho_x_preferred":[
        "\u99ac\u5176\u9813\u5e03\u7f85\u5fb7\u5340"
    ],
    "name:zho_x_variant":[
        "\u9a6c\u5176\u987f\u5e03\u7f57\u5fb7\u5e02\u9547"
    ],
    "qs:name":"Zrkle",
    "qs:name_adm0":"Macedonia",
    "qs:name_adm1":"Makedonski Brod",
    "qs:photos_9r":0,
    "qs:photos_sr":0,
    "qs:placetype":"Town",
    "qs:pop_sr":"1",
    "wd:wordcount":302,
    "wof:name":"Zrkle",
    "wof:placetype":"locality",
    "wof:population":200
},
  "geometry": {"coordinates":[21.15083,41.65861],"type":"Point"}
}