{
  "type": "Feature",
  "properties": {
    "gn:admin1_code":"D7",
    "gn:asciiname":"Vak'v",
    "gn:country_code":"MK",
    "gn:dem":293,
    "gn:feature_class":"P",
    "gn:feature_code":"PPL",
    "gn:name":"Vak\u2019v",
    "gn:population":0,
    "gn:timezone":"Europe/Skopje",
    "iso:country":"MK",
    "name:mkd_x_preferred":[
        "Vak\u2019v"
    ],
    "name:mkd_x_variant":[
        "\u0412\u0430\u043a\u2019\u0432",
        "\u0412\u0430\u043a\u0430\u0432"
    ],
    "name:und_x_variant":[
        "Vakuf",
        "Vakav"
    ],
    "wof:name":"Vak'v",
    "wof:placetype":"locality"
},
  "geometry": {"coordinates":[21.74694,42.02278],"type":"Point"}
}