{
  "type": "Feature",
  "properties": {
    "gn:admin1_code":"B4",
    "gn:asciiname":"Tasovska Maala",
    "gn:country_code":"MK",
    "gn:dem":485,
    "gn:feature_class":"P",
    "gn:feature_code":"PPL",
    "gn:name":"Ta\u0161ovska Maala",
    "gn:population":0,
    "gn:timezone":"Europe/Skopje",
    "iso:country":"MK",
    "name:mkd_x_preferred":[
        "Ta\u0161ovska Maala"
    ],
    "name:mkd_x_variant":[
        "\u0422\u0430\u0448\u043e\u0432\u0441\u043a\u0430 \u041c\u0430\u0430\u043b\u0430"
    ],
    "wof:name":"Tasovska Maala",
    "wof:placetype":"locality"
},
  "geometry": {"coordinates":[22.53395,41.90589],"type":"Point"}
}