{
  "type": "Feature",
  "properties": {
    "gn:admin1_code":"52",
    "gn:asciiname":"Glincarci",
    "gn:country_code":"MK",
    "gn:dem":909,
    "gn:feature_class":"P",
    "gn:feature_code":"PPL",
    "gn:name":"Glin\u010darci",
    "gn:population":0,
    "gn:timezone":"Europe/Skopje",
    "iso:country":"MK",
    "name:mkd_x_preferred":[
        "Glin\u010darci"
    ],
    "name:mkd_x_variant":[
        "\u0413\u043b\u0438\u043d\u0447\u0430\u0440\u0446\u0438"
    ],
    "wof:name":"Glincarci",
    "wof:placetype":"locality"
},
  "geometry": {"coordinates":[22.30141,42.26659],"type":"Point"}
}