{
  "type": "Feature",
  "properties": {
    "gn:admin1_code":"40",
    "gn:asciiname":"Vrteska",
    "gn:country_code":"MK",
    "gn:dem":1031,
    "gn:feature_class":"P",
    "gn:feature_code":"PPL",
    "gn:name":"Vrte\u0161ka",
    "gn:population":0,
    "gn:timezone":"Europe/Skopje",
    "iso:country":"MK",
    "name:mkd_x_preferred":[
        "\u0412\u0440\u0442\u0435\u0448\u043a\u0430"
    ],
    "name:und_x_variant":[
        "Vrte\u0161ka"
    ],
    "wof:name":"Vrteska",
    "wof:placetype":"locality"
},
  "geometry": {"coordinates":[22.41896,41.7593],"type":"Point"}
}