{
  "type": "Feature",
  "properties": {
    "gn:admin1_code":"00",
    "gn:asciiname":"Golemi Bigor Dolenci",
    "gn:country_code":"MK",
    "gn:dem":885,
    "gn:feature_class":"P",
    "gn:feature_code":"PPL",
    "gn:name":"Golemi Bigor Dolenci",
    "gn:population":0,
    "gn:timezone":"Europe/Skopje",
    "iso:country":"MK",
    "wof:name":"Golemi Bigor Dolenci",
    "wof:placetype":"locality"
},
  "geometry": {"coordinates":[21.0075,41.50306],"type":"Point"}
}