{
  "type": "Feature",
  "properties": {
    "gn:admin1_code":"52",
    "gn:asciiname":"Kolipska Maala",
    "gn:country_code":"MK",
    "gn:dem":1164,
    "gn:feature_class":"P",
    "gn:feature_code":"PPL",
    "gn:name":"Kolipska Maala",
    "gn:population":0,
    "gn:timezone":"Europe/Skopje",
    "iso:country":"MK",
    "name:mkd_x_preferred":[
        "Kolipska Maala"
    ],
    "name:mkd_x_variant":[
        "\u041a\u043e\u043b\u0438\u043f\u0441\u043a\u0430 \u041c\u0430\u0430\u043b\u0430"
    ],
    "wof:name":"Kolipska Maala",
    "wof:placetype":"locality"
},
  "geometry": {"coordinates":[22.29361,42.33083],"type":"Point"}
}