{
  "type": "Feature",
  "properties": {
    "gn:admin1_code":"52",
    "gn:asciiname":"Ostrec",
    "gn:country_code":"MK",
    "gn:dem":1083,
    "gn:feature_class":"P",
    "gn:feature_code":"PPL",
    "gn:name":"Ostrec",
    "gn:population":0,
    "gn:timezone":"Europe/Skopje",
    "iso:country":"MK",
    "name:mkd_x_preferred":[
        "Ostrec"
    ],
    "name:mkd_x_variant":[
        "\u041e\u0441\u0442\u0440\u0435\u0446"
    ],
    "wof:name":"Ostrec",
    "wof:placetype":"locality"
},
  "geometry": {"coordinates":[22.25272,42.14133],"type":"Point"}
}