{
  "type": "Feature",
  "properties": {
    "gn:admin1_code":"D7",
    "gn:asciiname":"Gorno Konjare",
    "gn:country_code":"MK",
    "gn:dem":373,
    "gn:feature_class":"P",
    "gn:feature_code":"PPL",
    "gn:name":"Gorno Konjare",
    "gn:population":0,
    "gn:timezone":"Europe/Skopje",
    "iso:country":"MK",
    "name:bul_x_preferred":[
        "\u0413\u043e\u0440\u043d\u043e \u041a\u043e\u043d\u044f\u0440\u0435"
    ],
    "name:ceb_x_preferred":[
        "Gorno Konjare"
    ],
    "name:fra_x_preferred":[
        "Gorno Konyar\u00e9"
    ],
    "name:hun_x_preferred":[
        "Gorno Konyare"
    ],
    "name:mkd_x_preferred":[
        "Gorno Konjare"
    ],
    "name:mkd_x_variant":[
        "\u0413\u043e\u0440\u043d\u043e \u041a\u043e\u045a\u0430\u0440\u0435"
    ],
    "name:sqi_x_preferred":[
        "Kojnarja e Ep\u00ebrme"
    ],
    "name:srp_x_preferred":[
        "\u0413\u043e\u0440\u045a\u0435 \u041a\u043e\u045a\u0430\u0440\u0435"
    ],
    "name:swe_x_preferred":[
        "Gorno Konjare"
    ],
    "name:ukr_x_preferred":[
        "\u0413\u043e\u0440\u043d\u043e-\u041a\u043e\u043d\u044f\u0440\u0435"
    ],
    "wof:name":"Gorno Konjare",
    "wof:placetype":"locality"
},
  "geometry": {"coordinates":[21.7275,42.18167],"type":"Point"}
}