{
  "type": "Feature",
  "properties": {
    "gn:country":"MK",
    "gn:fcode":"PPL",
    "gn:pop":368,
    "iso:country":"MK",
    "name:mkd_x_preferred":[
        "Dolno Aglarci"
    ],
    "name:mkd_x_variant":[
        "\u0414\u043e\u043b\u043d\u043e \u0410\u0433\u043b\u0430\u0440\u0446\u0438"
    ],
    "qs:name":"Dolno Aglarci",
    "qs:photos_9r":0,
    "qs:photos_sr":0,
    "qs:pop_sr":"2",
    "wd:wordcount":133,
    "wof:name":"Dolno Aglarci",
    "wof:placetype":"locality",
    "wof:population":368
},
  "geometry": {"coordinates":[21.47028,41.0925],"type":"Point"}
}