{
  "type": "Feature",
  "properties": {
    "gn:country":"MK",
    "gn:fcode":"PPL",
    "gn:pop":63,
    "iso:country":"MK",
    "name:eng_x_preferred":[
        "Papradiste"
    ],
    "name:mkd_x_preferred":[
        "\u041f\u0430\u043f\u0440\u0430\u0434\u0438\u0448\u0442\u0435"
    ],
    "name:unk_x_variant":[
        "Papradi\u0161ta"
    ],
    "qs:name":"\u041f\u0430\u043f\u0440\u0430\u0434\u0438\u0448\u0442\u0435",
    "qs:photos_9r":0,
    "qs:photos_sr":0,
    "qs:pop_sr":"1",
    "wof:name":"\u041f\u0430\u043f\u0440\u0430\u0434\u0438\u0448\u0442\u0435",
    "wof:placetype":"locality",
    "wof:population":63
},
  "geometry": {"coordinates":[21.43944,41.64139],"type":"Point"}
}