{
  "type": "Feature",
  "properties": {
    "gn:admin1_code":"46",
    "gn:asciiname":"Gorno Gradce",
    "gn:country_code":"MK",
    "gn:dem":848,
    "gn:feature_class":"P",
    "gn:feature_code":"PPLL",
    "gn:name":"Gorno Grad\u010de",
    "gn:population":0,
    "gn:timezone":"Europe/Skopje",
    "iso:country":"MK",
    "name:mkd_x_preferred":[
        "Gorno Grad\u010de"
    ],
    "name:mkd_x_variant":[
        "\u0413\u043e\u0440\u043d\u043e \u0413\u0440\u0430\u0434\u0447\u0435"
    ],
    "wof:name":"Gorno Gradce",
    "wof:placetype":"locality"
},
  "geometry": {"coordinates":[22.42394,41.96855],"type":"Point"}
}