{
  "type": "Feature",
  "properties": {
    "gn:country":"MK",
    "gn:fcode":"PPLA",
    "gn:pop":15166,
    "iso:country":"MK",
    "name:ara_x_preferred":[
        "\u0628\u0648\u063a\u0648\u0641\u064a\u0646\u064a\u064a"
    ],
    "name:bul_x_preferred":[
        "\u0411\u043e\u0433\u043e\u0432\u0438\u043d\u0435"
    ],
    "name:cat_x_preferred":[
        "Bogovinje"
    ],
    "name:ces_x_preferred":[
        "Bogovinje"
    ],
    "name:deu_x_preferred":[
        "Bogovinje"
    ],
    "name:eng_x_preferred":[
        "Bogovinje"
    ],
    "name:fra_x_preferred":[
        "Bogovinje"
    ],
    "name:hun_x_preferred":[
        "Bogovinye"
    ],
    "name:ita_x_preferred":[
        "Bogovinje"
    ],
    "name:kat_x_preferred":[
        "\u10d1\u10dd\u10d2\u10dd\u10d5\u10d8\u10dc\u10d8\u10d4"
    ],
    "name:lit_x_preferred":[
        "Bogovinj\u0117"
    ],
    "name:mkd_x_preferred":[
        "\u0411\u043e\u0433\u043e\u0432\u0438\u045a\u0435"
    ],
    "name:nld_x_preferred":[
        "Bogovinje"
    ],
    "name:pol_x_preferred":[
        "Bogowi\u0144e"
    ],
    "name:rus_x_preferred":[
        "\u0411\u043e\u0433\u043e\u0432\u0438\u043d\u044c\u0435"
    ],
    "name:spa_x_preferred":[
        "Bogovinje"
    ],
    "name:sqi_x_preferred":[
        "Bogovina"
    ],
    "name:srp_x_preferred":[
        "\u0411\u043e\u0433\u043e\u0432\u0438\u045a\u0435"
    ],
    "name:tgk_x_preferred":[
        "\u0412\u0438\u043b\u043e\u044f\u0442\u0438 \u0411\u043e\u0433\u043e\u0432\u0438\u043d\u0435"
    ],
    "name:ukr_x_preferred":[
        "\u0411\u043e\u0433\u043e\u0432\u0438\u043d\u0454"
    ],
    "name:unk_x_variant":[
        "Bogovine"
    ],
    "qs:name":"Bogovinje",
    "qs:name_adm0":"Macedonia",
    "qs:name_adm1":"Bogovinje",
    "qs:photos_9r":0,
    "qs:photos_sr":0,
    "qs:placetype":"Town",
    "qs:pop_sr":"6",
    "wd:elevation":503.0,
    "wd:wordcount":61,
    "wof:name":"Bogovinje",
    "wof:placetype":"locality",
    "wof:population":15166
},
  "geometry": {"coordinates":[20.91361,41.92361],"type":"Point"}
}