{
  "type": "Feature",
  "properties": {
    "gn:country":"MK",
    "gn:fcode":"PPLA",
    "gn:pop":15166,
    "iso:country":"MK",
    "name:eng_x_preferred":[
        "Bogovinje"
    ],
    "name:mkd_x_preferred":[
        "\u0411\u043e\u0433\u043e\u0432\u0438\u045a\u0435"
    ],
    "name:unk_x_variant":[
        "Bogovine"
    ],
    "qs:name":"Bogovinje",
    "qs:name_adm0":"Macedonia",
    "qs:name_adm1":"Bogovinje",
    "qs:photos_9r":0,
    "qs:photos_sr":0,
    "qs:placetype":"Town",
    "qs:pop_sr":"6",
    "wd:elevation":503.0,
    "wd:wordcount":61,
    "wof:name":"Bogovinje",
    "wof:placetype":"locality",
    "wof:population":15166
},
  "geometry": {"coordinates":[20.91361,41.92361],"type":"Point"}
}