{
  "type": "Feature",
  "properties": {
    "gn:country":"MK",
    "gn:fcode":"PPL",
    "gn:pop":237,
    "iso:country":"MK",
    "name:mkd_x_preferred":[
        "\u0412\u0440\u0442\u0435\u043a\u0438\u0446\u0430"
    ],
    "name:unk_x_variant":[
        "Vrtakica"
    ],
    "qs:name":"Vrtekica",
    "qs:photos_9r":0,
    "qs:photos_sr":0,
    "qs:pop_sr":"2",
    "wd:wordcount":132,
    "wof:name":"Vrtekica",
    "wof:placetype":"locality",
    "wof:population":237
},
  "geometry": {"coordinates":[21.51056,41.885],"type":"Point"}
}