{
  "type": "Feature",
  "properties": {
    "gn:admin1_code":"00",
    "gn:asciiname":"Bardovci",
    "gn:cc2":"MK",
    "gn:country_code":"MK",
    "gn:dem":265,
    "gn:feature_class":"P",
    "gn:feature_code":"PPL",
    "gn:name":"\u0411\u0430\u0440\u0434\u043e\u0432\u0446\u0438",
    "gn:population":0,
    "gn:timezone":"Europe/Skopje",
    "iso:country":"MK",
    "name:bul_x_preferred":[
        "\u0411\u0430\u0440\u0434\u043e\u0432\u0446\u0438"
    ],
    "name:fra_x_preferred":[
        "Bardovtsi"
    ],
    "name:mkd_x_preferred":[
        "\u0411\u0440\u0430\u0434\u043e\u0432\u0446\u0435"
    ],
    "name:mkd_x_variant":[
        "\u0411\u0430\u0440\u0434\u043e\u0432\u0446\u0438"
    ],
    "name:sqi_x_preferred":[
        "Bardhoci"
    ],
    "name:srp_x_preferred":[
        "\u0411\u0430\u0440\u0434\u043e\u0432\u0446\u0438"
    ],
    "wof:name":"Bardovci",
    "wof:placetype":"locality"
},
  "geometry": {"coordinates":[21.37611,42.02694],"type":"Point"}
}