{
  "type": "Feature",
  "properties": {
    "gn:country":"MK",
    "gn:fcode":"PPL",
    "gn:population":40,
    "iso:country":"MK",
    "name:bul_x_preferred":[
        "\u041b\u0435\u043d\u0438\u0449\u0435"
    ],
    "name:eng_x_preferred":[
        "Leni\u0161te"
    ],
    "name:fra_x_preferred":[
        "Lenichta"
    ],
    "name:mkd_x_preferred":[
        "\u041b\u0435\u043d\u0438\u0448\u0442\u0435"
    ],
    "name:mkd_x_variant":[
        "\u041b\u0435\u043d\u0438\u0448\u0442\u0430"
    ],
    "name:nan_x_preferred":[
        "Lenichta"
    ],
    "name:sqi_x_preferred":[
        "Lenishta"
    ],
    "name:srp_x_preferred":[
        "\u041b\u0435\u043d\u0438\u0448\u0442\u0435"
    ],
    "qs:name":"Leni\u0161ta",
    "qs:photos_9r":0,
    "qs:photos_sr":0,
    "qs:pop_sr":"1",
    "wof:name":"Leni\u0161ta",
    "wof:placetype":"locality",
    "wof:population":40
},
  "geometry": {"coordinates":[21.62306,41.36028],"type":"Point"}
}