{
  "type": "Feature",
  "properties": {
    "gn:admin1_code":"85",
    "gn:asciiname":"Puckina Maala",
    "gn:country_code":"MK",
    "gn:dem":494,
    "gn:feature_class":"P",
    "gn:feature_code":"PPL",
    "gn:name":"Puckina Maala",
    "gn:population":0,
    "gn:timezone":"Europe/Skopje",
    "iso:country":"MK",
    "name:mkd_x_preferred":[
        "Puckina Maala"
    ],
    "name:mkd_x_variant":[
        "\u041f\u0443\u0446\u043a\u0438\u043d\u0430 \u041c\u0430\u0430\u043b\u0430"
    ],
    "wof:name":"Puckina Maala",
    "wof:placetype":"locality"
},
  "geometry": {"coordinates":[22.09604,42.15678],"type":"Point"}
}