{
  "type": "Feature",
  "properties": {
    "gn:admin1_code":"E6",
    "gn:asciiname":"Sum",
    "gn:country_code":"MK",
    "gn:dem":706,
    "gn:feature_class":"P",
    "gn:feature_code":"PPL",
    "gn:name":"\u0160um",
    "gn:population":0,
    "gn:timezone":"Europe/Skopje",
    "iso:country":"MK",
    "name:ceb_x_preferred":[
        "Sum"
    ],
    "name:deu_x_preferred":[
        "Sum"
    ],
    "name:fra_x_preferred":[
        "Sum"
    ],
    "name:kor_x_preferred":[
        "\uc228"
    ],
    "name:mkd_x_preferred":[
        "\u0160um"
    ],
    "name:mkd_x_variant":[
        "\u0428\u0443\u043c"
    ],
    "name:nld_x_preferred":[
        "Sum"
    ],
    "name:nor_x_preferred":[
        "Sum"
    ],
    "name:pol_x_preferred":[
        "Sum"
    ],
    "name:rus_x_preferred":[
        "\u0421\u0443\u043c"
    ],
    "name:swe_x_preferred":[
        "Sum"
    ],
    "name:ukr_x_preferred":[
        "\u0421\u0443\u043c"
    ],
    "name:xho_x_preferred":[
        "I-sum"
    ],
    "wof:name":"Sum",
    "wof:placetype":"locality"
},
  "geometry": {"coordinates":[20.63435,41.18673],"type":"Point"}
}