{
  "type": "Feature",
  "properties": {
    "gn:admin1_code":"06",
    "gn:asciiname":"Turska Malaa",
    "gn:country_code":"MK",
    "gn:dem":750,
    "gn:feature_class":"P",
    "gn:feature_code":"PPL",
    "gn:name":"Turska Malaa",
    "gn:population":0,
    "gn:timezone":"Europe/Skopje",
    "iso:country":"MK",
    "name:mkd_x_preferred":[
        "Turska Malaa"
    ],
    "name:mkd_x_variant":[
        "\u0422\u0443\u0440\u0441\u043a\u0430 \u041c\u0430\u0430\u043b\u0430",
        "Turska Mala"
    ],
    "wof:name":"Turska Malaa",
    "wof:placetype":"locality"
},
  "geometry": {"coordinates":[21.17083,41.09917],"type":"Point"}
}