{
  "type": "Feature",
  "properties": {
    "gn:admin1_code":"18",
    "gn:asciiname":"Dolno Melnicani",
    "gn:country_code":"MK",
    "gn:dem":746,
    "gn:feature_class":"P",
    "gn:feature_code":"PPL",
    "gn:name":"Dolno Melni\u010dani",
    "gn:population":0,
    "gn:timezone":"Europe/Skopje",
    "iso:country":"MK",
    "name:mkd_x_preferred":[
        "\u0414\u043e\u043b\u043d\u043e \u041c\u0435\u043b\u043d\u0438\u0447\u0430\u043d\u0438"
    ],
    "name:und_x_variant":[
        "Dolno Melini\u010dani",
        "Mjelnjicanje e Posht\u00ebme",
        "Dolno Melni\u010dani"
    ],
    "wof:name":"Dolno Melnicani",
    "wof:placetype":"locality"
},
  "geometry": {"coordinates":[20.57262,41.51671],"type":"Point"}
}