{
  "type": "Feature",
  "properties": {
    "gn:country":"MK",
    "gn:fcode":"PPL",
    "gn:pop":43,
    "iso:country":"MK",
    "name:mkd_x_preferred":[
        "\u040f\u0438\u0434\u0438\u043c\u0438\u0440\u0446\u0438"
    ],
    "name:unk_x_variant":[
        "D\u017eidimirce"
    ],
    "qs:name":"D\u017eidimirci",
    "qs:photos_9r":0,
    "qs:photos_sr":0,
    "qs:pop_sr":"1",
    "wof:name":"D\u017eidimirci",
    "wof:placetype":"locality",
    "wof:population":43
},
  "geometry": {"coordinates":[21.79111,41.89583],"type":"Point"}
}