{
  "type": "Feature",
  "properties": {
    "gn:admin1_code":"00",
    "gn:asciiname":"Dlabochica",
    "gn:cc2":"MK",
    "gn:country_code":"MK",
    "gn:dem":733,
    "gn:feature_class":"P",
    "gn:feature_code":"PPL",
    "gn:name":"\u0414\u043b\u0430\u0431\u043e\u0447\u0438\u0446\u0430",
    "gn:population":0,
    "gn:timezone":"Europe/Skopje",
    "iso:country":"MK",
    "name:eng_x_preferred":[
        "Dlabocica"
    ],
    "name:mkd_x_preferred":[
        "\u0414\u043b\u0430\u0431\u043e\u0447\u0438\u0446\u0430"
    ],
    "name:und_x_variant":[
        "Dubo\u010dica",
        "Dolbo\u010dica"
    ],
    "wof:name":"Dlabochica",
    "wof:placetype":"locality"
},
  "geometry": {"coordinates":[22.24139,42.19861],"type":"Point"}
}