{
  "type": "Feature",
  "properties": {
    "gn:admin1_code":"97",
    "gn:asciiname":"Dobraca",
    "gn:country_code":"MK",
    "gn:dem":486,
    "gn:feature_class":"P",
    "gn:feature_code":"PPLL",
    "gn:name":"Dobra\u010da",
    "gn:population":0,
    "gn:timezone":"Europe/Skopje",
    "iso:country":"MK",
    "name:mkd_x_preferred":[
        "Dobra\u010da"
    ],
    "name:mkd_x_variant":[
        "\u0414\u043e\u0431\u0440\u0430\u0447\u0430"
    ],
    "wof:name":"Dobraca",
    "wof:placetype":"locality"
},
  "geometry": {"coordinates":[21.90039,42.21788],"type":"Point"}
}