{
  "type": "Feature",
  "properties": {
    "gn:admin1_code":"D8",
    "gn:asciiname":"Suvodol",
    "gn:country_code":"MK",
    "gn:dem":532,
    "gn:feature_class":"P",
    "gn:feature_code":"PPL",
    "gn:name":"Suvodol",
    "gn:population":0,
    "gn:timezone":"Europe/Skopje",
    "iso:country":"MK",
    "name:mkd_x_preferred":[
        "\u0421\u0443\u0432\u043e\u0434\u043e\u043b"
    ],
    "name:und_x_variant":[
        "Suvi Dol",
        "Suvodol"
    ],
    "wof:name":"Suvodol",
    "wof:placetype":"locality"
},
  "geometry": {"coordinates":[21.23864,41.5206],"type":"Point"}
}