{
  "type": "Feature",
  "properties": {
    "gn:country":"MK",
    "gn:fcode":"PPLA",
    "gn:pop":11534,
    "iso:country":"MK",
    "name:eng_x_preferred":[
        "Dolneni"
    ],
    "name:mkd_x_preferred":[
        "\u0414\u043e\u043b\u043d\u0435\u043d\u0438"
    ],
    "name:unk_x_variant":[
        "Dolnjane"
    ],
    "qs:name":"\u0414\u043e\u043b\u043d\u0435\u043d\u0438",
    "qs:photos_9r":0,
    "qs:photos_sr":0,
    "qs:pop_sr":"6",
    "wd:wordcount":130,
    "wof:name":"\u0414\u043e\u043b\u043d\u0435\u043d\u0438",
    "wof:placetype":"locality",
    "wof:population":11534
},
  "geometry": {"coordinates":[21.45472,41.42528],"type":"Point"}
}