{
  "type": "Feature",
  "properties": {
    "gn:asciiname":"Zebarnjak",
    "gn:country_code":"MK",
    "gn:dem":442,
    "gn:feature_class":"P",
    "gn:feature_code":"PPL",
    "gn:name":"Zebarnjak",
    "gn:population":0,
    "gn:timezone":"Europe/Skopje",
    "iso:country":"MK",
    "wof:name":"Zebarnjak",
    "wof:placetype":"locality"
},
  "geometry": {"coordinates":[21.78739,42.14904],"type":"Point"}
}