{
  "type": "Feature",
  "properties": {
    "gn:country":"MK",
    "gn:fcode":"PPL",
    "gn:population":517,
    "iso:country":"MK",
    "name:bul_x_preferred":[
        "\u041b\u0430\u0432\u0446\u0438"
    ],
    "name:ceb_x_preferred":[
        "Lavci"
    ],
    "name:deu_x_preferred":[
        "Lavci"
    ],
    "name:eng_x_preferred":[
        "Lavci"
    ],
    "name:fra_x_preferred":[
        "Lavtsi"
    ],
    "name:hun_x_preferred":[
        "Lavci"
    ],
    "name:mkd_x_preferred":[
        "\u041b\u0430\u0432\u0446\u0438"
    ],
    "name:nan_x_preferred":[
        "Lavtsi"
    ],
    "name:nld_x_preferred":[
        "Lavci"
    ],
    "name:pol_x_preferred":[
        "\u0141awci"
    ],
    "name:sqi_x_preferred":[
        "Llaca"
    ],
    "name:srp_x_preferred":[
        "\u041b\u0430\u0432\u0446\u0438"
    ],
    "name:swe_x_preferred":[
        "Lavci"
    ],
    "name:ukr_x_preferred":[
        "\u041b\u0430\u0432\u0446\u0456"
    ],
    "name:und_x_variant":[
        "Lahci"
    ],
    "qs:name":"Lavci",
    "qs:photos_9r":0,
    "qs:photos_sr":0,
    "qs:pop_sr":"2",
    "wd:elevation":792.0,
    "wd:population":338,
    "wd:wordcount":66,
    "wof:name":"Lavci",
    "wof:placetype":"locality",
    "wof:population":338
},
  "geometry": {"coordinates":[21.3025,41.01472],"type":"Point"}
}