{
  "type": "Feature",
  "properties": {
    "gn:admin1_code":"00",
    "gn:asciiname":"Umin Dol",
    "gn:cc2":"MK",
    "gn:country_code":"MK",
    "gn:dem":509,
    "gn:feature_class":"P",
    "gn:feature_code":"PPL",
    "gn:name":"\u0423\u043c\u0438\u043d \u0414\u043e\u043b",
    "gn:population":0,
    "gn:timezone":"Europe/Skopje",
    "iso:country":"MK",
    "name:mkd_x_preferred":[
        "Umin Dol"
    ],
    "wof:name":"Umin Dol",
    "wof:placetype":"locality"
},
  "geometry": {"coordinates":[21.62528,42.08667],"type":"Point"}
}