{
  "type": "Feature",
  "properties": {
    "gn:country":"MK",
    "gn:fcode":"PPL",
    "gn:pop":1424,
    "iso:country":"MK",
    "name:alb_x_preferred":[
        "Llukova"
    ],
    "name:bul_x_preferred":[
        "\u041b\u0443\u043a\u043e\u0432\u043e"
    ],
    "name:dut_x_preferred":[
        "Lukovo"
    ],
    "name:eng_x_preferred":[
        "Lukovo"
    ],
    "name:fre_x_preferred":[
        "Loukovo"
    ],
    "name:ger_x_preferred":[
        "Lukovo"
    ],
    "name:hun_x_preferred":[
        "Lukovo"
    ],
    "name:mac_x_preferred":[
        "\u041b\u0443\u043a\u043e\u0432\u043e"
    ],
    "name:mkd_x_preferred":[
        "\u041b\u0443\u043a\u043e\u0432\u043e"
    ],
    "name:srp_x_preferred":[
        "\u041b\u0443\u043a\u043e\u0432\u043e"
    ],
    "name:unk_x_variant":[
        "Gorno Lukovo"
    ],
    "qs:name":"Lukovo",
    "qs:name_adm0":"Macedonia",
    "qs:name_adm1":"Struga",
    "qs:photos_9k":1,
    "qs:photos_9r":1,
    "qs:photos_all":1,
    "qs:photos_sr":0,
    "qs:placetype":"Town",
    "qs:pop_sr":"3",
    "wd:wordcount":52,
    "wof:name":"Lukovo",
    "wof:placetype":"locality",
    "wof:population":1424
},
  "geometry": {"coordinates":[20.60472,41.34944],"type":"Point"}
}