{
  "type": "Feature",
  "properties": {
    "gn:admin1_code":"52",
    "gn:asciiname":"Petakovci",
    "gn:country_code":"MK",
    "gn:dem":1186,
    "gn:feature_class":"P",
    "gn:feature_code":"PPL",
    "gn:name":"Petakovci",
    "gn:population":0,
    "gn:timezone":"Europe/Belgrade",
    "iso:country":"MK",
    "name:mkd_x_preferred":[
        "\u041f\u0435\u0442\u0430\u043a\u043e\u0432\u0446\u0438"
    ],
    "name:und_x_variant":[
        "Petakovci Mahala",
        "Petakovci"
    ],
    "wof:name":"Petakovci",
    "wof:placetype":"locality"
},
  "geometry": {"coordinates":[22.21479,42.31416],"type":"Point"}
}