{
  "type": "Feature",
  "properties": {
    "gn:country":"MK",
    "gn:fcode":"PPL",
    "gn:pop":357,
    "iso:country":"MK",
    "name:mkd_x_preferred":[
        "\u0413\u043e\u0440\u043d\u043e \u0426\u0440\u043d\u0438\u043b\u0438\u0448\u0442\u0435"
    ],
    "name:unk_x_variant":[
        "Veliko Crnili\u0161te"
    ],
    "qs:name":"Gorno Crnili\u0161te",
    "qs:photos_9r":0,
    "qs:photos_sr":0,
    "qs:pop_sr":"2",
    "wd:wordcount":126,
    "wof:name":"Gorno Crnili\u0161te",
    "wof:placetype":"locality",
    "wof:population":357
},
  "geometry": {"coordinates":[21.95556,41.81806],"type":"Point"}
}