{
  "type": "Feature",
  "properties": {
    "gn:admin1_code":"51",
    "gn:asciiname":"Sredna Maala",
    "gn:country_code":"MK",
    "gn:dem":553,
    "gn:feature_class":"P",
    "gn:feature_code":"PPL",
    "gn:name":"Sredna Maala",
    "gn:population":0,
    "gn:timezone":"Europe/Skopje",
    "iso:country":"MK",
    "name:mkd_x_preferred":[
        "Sredna Maala"
    ],
    "name:mkd_x_variant":[
        "\u0421\u0440\u0435\u0434\u043d\u0430 \u041c\u0430\u0430\u043b\u0430"
    ],
    "wof:name":"Sredna Maala",
    "wof:placetype":"locality"
},
  "geometry": {"coordinates":[22.12061,42.12632],"type":"Point"}
}