{
  "type": "Feature",
  "properties": {
    "gn:admin1_code":"85",
    "gn:asciiname":"German",
    "gn:country_code":"MK",
    "gn:dem":1324,
    "gn:feature_class":"P",
    "gn:feature_code":"PPLL",
    "gn:name":"German",
    "gn:population":0,
    "gn:timezone":"Europe/Skopje",
    "iso:country":"MK",
    "name:mkd_x_preferred":[
        "\u0413\u0435\u0440\u043c\u0430\u043d"
    ],
    "name:und_x_variant":[
        "\u00d0erman",
        "German"
    ],
    "wof:name":"German",
    "wof:placetype":"locality"
},
  "geometry": {"coordinates":[22.10333,42.27806],"type":"Point"}
}