{
  "type": "Feature",
  "properties": {
    "gn:country":"MK",
    "gn:fcode":"PPL",
    "gn:population":8646,
    "iso:country":"MK",
    "name:ara_x_preferred":[
        "\u0641\u064a\u0644\u064a\u0634\u062a\u0627\u060c \u0633\u062a\u0631\u0648\u063a\u0627"
    ],
    "name:ara_x_variant":[
        "\u0641\u064a\u0644\u064a\u0634\u062a\u0627"
    ],
    "name:bul_x_preferred":[
        "\u0412\u0435\u043b\u0435\u0449\u0430"
    ],
    "name:deu_x_preferred":[
        "Vele\u0161ta"
    ],
    "name:eng_x_preferred":[
        "Velesta"
    ],
    "name:eng_x_variant":[
        "Vele\u0161ta"
    ],
    "name:fra_x_preferred":[
        "Velechta"
    ],
    "name:hun_x_preferred":[
        "Velesta"
    ],
    "name:mkd_x_preferred":[
        "\u0412\u0435\u043b\u0435\u0448\u0442\u0430"
    ],
    "name:nan_x_preferred":[
        "Velechta"
    ],
    "name:nld_x_preferred":[
        "Vele\u0161ta"
    ],
    "name:pol_x_preferred":[
        "We\u0142eszta"
    ],
    "name:por_x_preferred":[
        "Vele\u0161ta"
    ],
    "name:sqi_x_preferred":[
        "Veleshta"
    ],
    "name:srp_x_preferred":[
        "\u0412\u0435\u043b\u0435\u0448\u0442\u0430"
    ],
    "name:und_x_variant":[
        "Vele\u0161te"
    ],
    "qs:name":"Velesta",
    "qs:photos_9r":0,
    "qs:photos_sr":0,
    "qs:pop_sr":"5",
    "wd:wordcount":49,
    "wof:name":"Velesta",
    "wof:placetype":"locality",
    "wof:population":8646
},
  "geometry": {"coordinates":[20.64389,41.24083],"type":"Point"}
}