{
  "type": "Feature",
  "properties": {
    "gn:country":"MK",
    "gn:fcode":"PPL",
    "gn:pop":105,
    "iso:country":"MK",
    "name:mkd_x_preferred":[
        "Gre\u0161nica"
    ],
    "name:mkd_x_variant":[
        "\u0413\u0440\u0435\u0448\u043d\u0438\u0446\u0430"
    ],
    "qs:name":"Gre\u0161nica",
    "qs:photos_9r":0,
    "qs:photos_sr":0,
    "qs:pop_sr":"1",
    "wof:name":"Gre\u0161nica",
    "wof:placetype":"locality",
    "wof:population":105
},
  "geometry": {"coordinates":[21.19028,41.56194],"type":"Point"}
}