{
  "type": "Feature",
  "properties": {
    "gn:admin1_code":"52",
    "gn:asciiname":"Mitrovska Maala",
    "gn:country_code":"MK",
    "gn:dem":725,
    "gn:feature_class":"P",
    "gn:feature_code":"PPL",
    "gn:name":"Mitrovska Maala",
    "gn:population":0,
    "gn:timezone":"Europe/Skopje",
    "iso:country":"MK",
    "name:mkd_x_preferred":[
        "Mitrovska Maala"
    ],
    "name:mkd_x_variant":[
        "\u041c\u0438\u0442\u0440\u043e\u0432\u0441\u043a\u0430 \u041c\u0430\u0430\u043b\u0430"
    ],
    "wof:name":"Mitrovska Maala",
    "wof:placetype":"locality"
},
  "geometry": {"coordinates":[22.24272,42.1986],"type":"Point"}
}