{
  "type": "Feature",
  "properties": {
    "gn:admin1_code":"97",
    "gn:asciiname":"Tutusanska Maala",
    "gn:country_code":"MK",
    "gn:dem":422,
    "gn:feature_class":"P",
    "gn:feature_code":"PPL",
    "gn:name":"Tutu\u0161anska Maala",
    "gn:population":0,
    "gn:timezone":"Europe/Skopje",
    "iso:country":"MK",
    "name:mkd_x_preferred":[
        "Tutu\u0161anska Maala"
    ],
    "name:mkd_x_variant":[
        "\u0422\u0443\u0442\u0443\u0448\u0430\u043d\u0441\u043a\u0430 \u041c\u0430\u0430\u043b\u0430"
    ],
    "wof:name":"Tutusanska Maala",
    "wof:placetype":"locality"
},
  "geometry": {"coordinates":[21.90681,42.15156],"type":"Point"}
}