{
  "type": "Feature",
  "properties": {
    "gn:country":"MK",
    "gn:fcode":"CMP",
    "gn:pop":70,
    "iso:country":"MK",
    "qs:name":"Ceples",
    "qs:photos_9r":0,
    "qs:photos_sr":0,
    "qs:pop_sr":"1",
    "wof:name":"Ceples",
    "wof:placetype":"locality",
    "wof:population":70
},
  "geometry": {"coordinates":[21.42855,41.66396],"type":"Point"}
}