{
  "type": "Feature",
  "properties": {
    "gn:country":"MK",
    "gn:fcode":"PPL",
    "gn:pop":78,
    "iso:country":"MK",
    "name:mkd_x_preferred":[
        "Kru\u0161evica"
    ],
    "name:mkd_x_variant":[
        "\u041a\u0440\u0443\u0448\u0435\u0432\u0438\u0446\u0430"
    ],
    "qs:name":"Kru\u0161evica",
    "qs:photos_9r":0,
    "qs:photos_sr":0,
    "qs:pop_sr":"1",
    "wd:wordcount":76,
    "wof:name":"Kru\u0161evica",
    "wof:placetype":"locality",
    "wof:population":78
},
  "geometry": {"coordinates":[21.88278,41.53306],"type":"Point"}
}