{
  "type": "Feature",
  "properties": {
    "gn:country":"MK",
    "gn:fcode":"PPL",
    "gn:population":74,
    "iso:country":"MK",
    "name:bos_x_preferred":[
        "Su\u0161ica"
    ],
    "name:ceb_x_preferred":[
        "Su\u0161ica"
    ],
    "name:fra_x_preferred":[
        "Su\u0161ica"
    ],
    "name:mkd_x_preferred":[
        "Su\u0161ica"
    ],
    "name:mkd_x_variant":[
        "\u0421\u0443\u0448\u0438\u0446\u0430"
    ],
    "name:nld_x_preferred":[
        "Su\u0161ica"
    ],
    "name:swe_x_preferred":[
        "Su\u0161ica"
    ],
    "qs:name":"Su\u0161ica",
    "qs:photos_9r":0,
    "qs:photos_sr":0,
    "qs:pop_sr":"1",
    "wd:wordcount":122,
    "wof:name":"Su\u0161ica",
    "wof:placetype":"locality",
    "wof:population":74
},
  "geometry": {"coordinates":[21.14,41.64139],"type":"Point"}
}