{
  "type": "Feature",
  "properties": {
    "gn:admin1_code":"51",
    "gn:asciiname":"Zeleznica",
    "gn:country_code":"MK",
    "gn:dem":837,
    "gn:feature_class":"P",
    "gn:feature_code":"PPLL",
    "gn:name":"\u017deleznica",
    "gn:population":0,
    "gn:timezone":"Europe/Skopje",
    "iso:country":"MK",
    "name:mkd_x_preferred":[
        "\u017deleznica"
    ],
    "name:mkd_x_variant":[
        "\u0416\u0435\u043b\u0435\u0437\u043d\u0438\u0446\u0430"
    ],
    "wof:name":"Zeleznica",
    "wof:placetype":"locality"
},
  "geometry": {"coordinates":[22.15664,42.09736],"type":"Point"}
}