{
  "type": "Feature",
  "properties": {
    "gn:country":"MK",
    "gn:fcode":"PPL",
    "gn:pop":86,
    "iso:country":"MK",
    "name:mkd_x_preferred":[
        "Krajnici"
    ],
    "name:mkd_x_variant":[
        "\u041a\u0440\u0430\u0458\u043d\u0438\u0446\u0438"
    ],
    "qs:name":"Krajnici",
    "qs:photos_9r":0,
    "qs:photos_sr":0,
    "qs:pop_sr":"1",
    "wd:wordcount":194,
    "wof:name":"Krajnici",
    "wof:placetype":"locality",
    "wof:population":86
},
  "geometry": {"coordinates":[21.77806,41.57083],"type":"Point"}
}