{
  "type": "Feature",
  "properties": {
    "gn:admin1_code":"43",
    "gn:asciiname":"Lesnica",
    "gn:country_code":"MK",
    "gn:dem":776,
    "gn:feature_class":"P",
    "gn:feature_code":"PPL",
    "gn:name":"Le\u0161nica",
    "gn:population":0,
    "gn:timezone":"Europe/Skopje",
    "iso:country":"MK",
    "name:mkd_x_preferred":[
        "Le\u0161nica"
    ],
    "name:mkd_x_variant":[
        "\u041b\u0435\u0448\u043d\u0438\u0446\u0430"
    ],
    "wof:name":"Lesnica",
    "wof:placetype":"locality"
},
  "geometry": {"coordinates":[20.90917,41.57139],"type":"Point"}
}