{
  "type": "Feature",
  "properties": {
    "gn:country":"MK",
    "gn:fcode":"PPL",
    "gn:pop":164,
    "iso:country":"MK",
    "name:mkd_x_preferred":[
        "\u041d\u043e\u0432\u043e \u0417\u043c\u0438\u0440\u043d\u0435\u0432\u043e"
    ],
    "name:unk_x_variant":[
        "Smirnovo"
    ],
    "qs:name":"Novo Zmirnevo",
    "qs:photos_9r":0,
    "qs:photos_sr":0,
    "qs:pop_sr":"1",
    "wof:name":"Novo Zmirnevo",
    "wof:placetype":"locality",
    "wof:population":164
},
  "geometry": {"coordinates":[21.31389,41.12139],"type":"Point"}
}