{
  "type": "Feature",
  "properties": {
    "gn:admin1_code":"84",
    "gn:asciiname":"Kodzalija",
    "gn:country_code":"MK",
    "gn:dem":874,
    "gn:feature_class":"P",
    "gn:feature_code":"PPL",
    "gn:name":"Kod\u017ealija",
    "gn:population":0,
    "gn:timezone":"Europe/Skopje",
    "iso:country":"MK",
    "name:mkd_x_preferred":[
        "\u041a\u043e\u045f\u0430\u043b\u0438\u0458\u0430"
    ],
    "name:und_x_variant":[
        "Kod\u017eali",
        "Kod\u017ealija"
    ],
    "wof:name":"Kodzalija",
    "wof:placetype":"locality"
},
  "geometry": {"coordinates":[22.42028,41.68944000000001],"type":"Point"}
}