{
  "type": "Feature",
  "properties": {
    "gn:country":"MK",
    "gn:fcode":"PPL",
    "gn:pop":699,
    "iso:country":"MK",
    "name:alb_x_preferred":[
        "Zhvani"
    ],
    "name:bul_x_preferred":[
        "\u0416\u0432\u0430\u043d"
    ],
    "name:dut_x_preferred":[
        "\u017dvan"
    ],
    "name:eng_x_preferred":[
        "\u017dvan"
    ],
    "name:fre_x_preferred":[
        "Jvan"
    ],
    "name:ger_x_preferred":[
        "\u017dvan"
    ],
    "name:hun_x_preferred":[
        "Zsvan"
    ],
    "name:mac_x_preferred":[
        "\u0416\u0432\u0430\u043d"
    ],
    "name:mkd_x_preferred":[
        "\u0416\u0432\u0430\u043d"
    ],
    "name:srp_x_preferred":[
        "\u0416\u0432\u0430\u043d"
    ],
    "name:swe_x_preferred":[
        "\u017dvan"
    ],
    "name:unk_x_variant":[
        "D\u017evan"
    ],
    "qs:name":"\u017dvan",
    "qs:name_adm0":"Macedonia",
    "qs:name_adm1":"Demir Hisar",
    "qs:photos_9r":0,
    "qs:photos_sr":0,
    "qs:placetype":"Town",
    "qs:pop_sr":"2",
    "wof:name":"\u017dvan",
    "wof:placetype":"locality",
    "wof:population":699
},
  "geometry": {"coordinates":[21.12083,41.28778],"type":"Point"}
}