{
  "type": "Feature",
  "properties": {
    "gn:country":"MK",
    "gn:fcode":"PPL",
    "gn:pop":715,
    "iso:country":"MK",
    "name:mkd_x_preferred":[
        "Kopa\u010din Dol"
    ],
    "name:mkd_x_variant":[
        "\u041a\u043e\u043f\u0430\u0447\u0438\u043d \u0414\u043e\u043b"
    ],
    "qs:name":"Kopa\u010din Dol",
    "qs:photos_9r":0,
    "qs:photos_sr":0,
    "qs:pop_sr":"2",
    "wof:name":"Kopa\u010din Dol",
    "wof:placetype":"locality",
    "wof:population":715
},
  "geometry": {"coordinates":[21.13861,41.95944],"type":"Point"}
}