{
  "type": "Feature",
  "properties": {
    "gn:admin1_code":"D7",
    "gn:asciiname":"Kosmatac",
    "gn:country_code":"MK",
    "gn:dem":412,
    "gn:feature_class":"P",
    "gn:feature_code":"PPL",
    "gn:name":"Kosmatac",
    "gn:population":0,
    "gn:timezone":"Europe/Skopje",
    "iso:country":"MK",
    "name:mkd_x_preferred":[
        "Kosmatac"
    ],
    "name:mkd_x_variant":[
        "\u041a\u043e\u0441\u043c\u0430\u0442\u0430\u0446"
    ],
    "wof:name":"Kosmatac",
    "wof:placetype":"locality"
},
  "geometry": {"coordinates":[21.87694,42.07139],"type":"Point"}
}