{
  "type": "Feature",
  "properties": {
    "gn:country":"MK",
    "gn:fcode":"PPLL",
    "gn:pop":178,
    "iso:country":"MK",
    "name:bul_x_preferred":[
        "\u0414\u043e\u0431\u0440\u0438\u043d\u043e"
    ],
    "name:eng_x_preferred":[
        "Dobrino"
    ],
    "name:fra_x_preferred":[
        "Dobrino"
    ],
    "name:mkd_x_preferred":[
        "Dobrino"
    ],
    "name:mkd_x_variant":[
        "\u0414\u043e\u0431\u0440\u0438\u043d\u043e"
    ],
    "name:sqi_x_preferred":[
        "Dobrina"
    ],
    "name:srp_x_preferred":[
        "\u0414\u043e\u0431\u0440\u0438\u043d\u043e"
    ],
    "name:swe_x_preferred":[
        "Dobrino"
    ],
    "qs:name":"Dobrino",
    "qs:photos_9r":0,
    "qs:photos_sr":0,
    "qs:pop_sr":"1",
    "wof:name":"Dobrino",
    "wof:placetype":"locality",
    "wof:population":178
},
  "geometry": {"coordinates":[21.60833,41.79861],"type":"Point"}
}