{
  "type": "Feature",
  "properties": {
    "gn:country":"MK",
    "gn:fcode":"PPL",
    "gn:pop":790,
    "iso:country":"MK",
    "name:bul_x_preferred":[
        "\u0411\u0440\u0443\u0441\u043d\u0438\u043a"
    ],
    "name:eng_x_preferred":[
        "Brusnik"
    ],
    "name:fra_x_preferred":[
        "Brousnik"
    ],
    "name:hun_x_preferred":[
        "Brusznik"
    ],
    "name:mkd_x_preferred":[
        "\u0411\u0440\u0443\u0441\u043d\u0438\u043a"
    ],
    "name:nan_x_preferred":[
        "Brousnik"
    ],
    "name:nld_x_preferred":[
        "Brusnik"
    ],
    "name:pol_x_preferred":[
        "Brusnik"
    ],
    "name:sqi_x_preferred":[
        "Brusniku"
    ],
    "name:srp_x_preferred":[
        "\u0411\u0440\u0443\u0441\u043d\u0438\u043a"
    ],
    "name:swe_x_preferred":[
        "Brusnik"
    ],
    "name:zho_x_preferred":[
        "\u5e03\u76e7\u7d72\u5c3c\u514b"
    ],
    "qs:name":"Brusnik",
    "qs:photos_9r":0,
    "qs:photos_sr":0,
    "qs:pop_sr":"2",
    "wd:wordcount":102,
    "wof:name":"Brusnik",
    "wof:placetype":"locality",
    "wof:population":790
},
  "geometry": {"coordinates":[21.28528,41.02306],"type":"Point"}
}