{
  "type": "Feature",
  "properties": {
    "gn:admin1_code":"97",
    "gn:asciiname":"Santerci",
    "gn:country_code":"MK",
    "gn:dem":395,
    "gn:feature_class":"P",
    "gn:feature_code":"PPL",
    "gn:name":"\u0160anterci",
    "gn:population":0,
    "gn:timezone":"Europe/Skopje",
    "iso:country":"MK",
    "name:mkd_x_preferred":[
        "\u0160anterci"
    ],
    "name:mkd_x_variant":[
        "\u0428\u0430\u043d\u0442\u0435\u0440\u0446\u0438"
    ],
    "wof:name":"Santerci",
    "wof:placetype":"locality"
},
  "geometry": {"coordinates":[21.86419,42.19934],"type":"Point"}
}