{
  "type": "Feature",
  "properties": {
    "gn:admin1_code":"85",
    "gn:asciiname":"Kolerska Maala",
    "gn:country_code":"MK",
    "gn:dem":871,
    "gn:feature_class":"P",
    "gn:feature_code":"PPL",
    "gn:name":"Kolerska Maala",
    "gn:population":0,
    "gn:timezone":"Europe/Skopje",
    "iso:country":"MK",
    "name:mkd_x_preferred":[
        "Kolerska Maala"
    ],
    "name:mkd_x_variant":[
        "\u041a\u043e\u043b\u0435\u0440\u0441\u043a\u0430 \u041c\u0430\u0430\u043b\u0430"
    ],
    "wof:name":"Kolerska Maala",
    "wof:placetype":"locality"
},
  "geometry": {"coordinates":[22.19198,42.22181],"type":"Point"}
}