{
  "type": "Feature",
  "properties": {
    "gn:admin1_code":"D7",
    "gn:asciiname":"Jacinska Maala",
    "gn:country_code":"MK",
    "gn:dem":309,
    "gn:feature_class":"P",
    "gn:feature_code":"PPL",
    "gn:name":"Ja\u010dinska Maala",
    "gn:population":0,
    "gn:timezone":"Europe/Skopje",
    "iso:country":"MK",
    "name:mkd_x_preferred":[
        "Ja\u010dinska Maala"
    ],
    "name:mkd_x_variant":[
        "\u0408\u0430\u0447\u0438\u043d\u0441\u043a\u0430 \u041c\u0430\u0430\u043b\u0430"
    ],
    "wof:name":"Jacinska Maala",
    "wof:placetype":"locality"
},
  "geometry": {"coordinates":[21.87164,42.12402],"type":"Point"}
}