{
  "type": "Feature",
  "properties": {
    "gn:admin1_code":"52",
    "gn:asciiname":"Cukarci",
    "gn:country_code":"MK",
    "gn:dem":1017,
    "gn:feature_class":"P",
    "gn:feature_code":"PPL",
    "gn:name":"\u010cukarci",
    "gn:population":0,
    "gn:timezone":"Europe/Skopje",
    "iso:country":"MK",
    "name:mkd_x_preferred":[
        "\u010cukarci"
    ],
    "name:mkd_x_variant":[
        "\u0427\u0443\u043a\u0430\u0440\u0446\u0438"
    ],
    "wof:name":"Cukarci",
    "wof:placetype":"locality"
},
  "geometry": {"coordinates":[22.31303,42.27816],"type":"Point"}
}