{
  "type": "Feature",
  "properties": {
    "gn:country":"MK",
    "gn:fcode":"PPL",
    "gn:population":8,
    "iso:country":"MK",
    "name:bos_x_preferred":[
        "Polo\u0161ka kotlina"
    ],
    "name:bul_x_preferred":[
        "\u041f\u043e\u043b\u043e\u0433"
    ],
    "name:ell_x_preferred":[
        "\u039a\u03bf\u03b9\u03bb\u03ac\u03b4\u03b1 \u03a0\u03cc\u03bb\u03bf\u03b3\u03ba"
    ],
    "name:eng_x_preferred":[
        "Polog"
    ],
    "name:fra_x_preferred":[
        "Polog"
    ],
    "name:hrv_x_preferred":[
        "Polo\u0161ka kotlina"
    ],
    "name:jpn_x_preferred":[
        "\u30dd\u30ed\u30af"
    ],
    "name:mkd_x_preferred":[
        "Polog"
    ],
    "name:mkd_x_variant":[
        "\u041f\u043e\u043b\u043e\u0433",
        "\u041f\u043e\u043b\u043e\u0448\u043a\u0430 \u041a\u043e\u0442\u043b\u0438\u043d\u0430"
    ],
    "name:nld_x_preferred":[
        "Polog"
    ],
    "name:rus_x_preferred":[
        "\u041f\u043e\u043b\u043e\u0433"
    ],
    "name:spa_x_preferred":[
        "Polog"
    ],
    "name:srp_x_preferred":[
        "\u041f\u043e\u043b\u043e\u0448\u043a\u0430 \u043a\u043e\u0442\u043b\u0438\u043d\u0430"
    ],
    "name:ukr_x_preferred":[
        "\u041f\u043e\u043b\u043e\u0433"
    ],
    "qs:name":"Polog",
    "qs:photos_9r":0,
    "qs:photos_sr":0,
    "qs:pop_sr":"1",
    "wd:wordcount":79,
    "wof:name":"Polog",
    "wof:placetype":"locality",
    "wof:population":8
},
  "geometry": {"coordinates":[21.61467,41.00922],"type":"Point"}
}