{
  "type": "Feature",
  "properties": {
    "gn:country":"MK",
    "gn:fcode":"PPL",
    "gn:pop":8,
    "iso:country":"MK",
    "name:mkd_x_preferred":[
        "Polog"
    ],
    "name:mkd_x_variant":[
        "\u041f\u043e\u043b\u043e\u0433"
    ],
    "qs:name":"Polog",
    "qs:photos_9r":0,
    "qs:photos_sr":0,
    "qs:pop_sr":"1",
    "wd:wordcount":79,
    "wof:name":"Polog",
    "wof:placetype":"locality",
    "wof:population":8
},
  "geometry": {"coordinates":[21.61467,41.00922],"type":"Point"}
}