{
  "type": "Feature",
  "properties": {
    "gn:country":"MK",
    "gn:fcode":"PPL",
    "gn:pop":423,
    "iso:country":"MK",
    "name:bul_x_preferred":[
        "\u0421\u0435\u043a\u0438\u0440\u0446\u0438"
    ],
    "name:eng_x_preferred":[
        "Sekirci"
    ],
    "name:fra_x_preferred":[
        "Sekirtsi"
    ],
    "name:mkd_x_preferred":[
        "Sekirci"
    ],
    "name:mkd_x_variant":[
        "\u0421\u0435\u043a\u0438\u0440\u0446\u0438"
    ],
    "name:nld_x_preferred":[
        "Sekirci"
    ],
    "name:sqi_x_preferred":[
        "Sekirca"
    ],
    "name:srp_x_preferred":[
        "\u0421\u0435\u043a\u0438\u0440\u0446\u0438"
    ],
    "name:swe_x_preferred":[
        "Sekirci"
    ],
    "qs:name":"Sekirci",
    "qs:photos_9r":0,
    "qs:photos_sr":0,
    "qs:pop_sr":"2",
    "wd:wordcount":37,
    "wof:name":"Sekirci",
    "wof:placetype":"locality",
    "wof:population":423
},
  "geometry": {"coordinates":[21.4125,41.47889],"type":"Point"}
}