{
  "type": "Feature",
  "properties": {
    "gn:admin1_code":"E9",
    "gn:asciiname":"Plavus",
    "gn:country_code":"MK",
    "gn:dem":513,
    "gn:feature_class":"P",
    "gn:feature_code":"PPL",
    "gn:name":"Plavu\u0161",
    "gn:population":0,
    "gn:timezone":"Europe/Skopje",
    "iso:country":"MK",
    "name:mkd_x_preferred":[
        "Plavu\u0161"
    ],
    "name:mkd_x_variant":[
        "\u041f\u043b\u0430\u0432\u0443\u0448"
    ],
    "wof:name":"Plavus",
    "wof:placetype":"locality"
},
  "geometry": {"coordinates":[22.50139,41.37944],"type":"Point"}
}