{
  "type": "Feature",
  "properties": {
    "gn:admin1_code":"43",
    "gn:asciiname":"Osoj",
    "gn:country_code":"MK",
    "gn:dem":696,
    "gn:feature_class":"P",
    "gn:feature_code":"PPL",
    "gn:name":"Osoj",
    "gn:population":0,
    "gn:timezone":"Europe/Skopje",
    "iso:country":"MK",
    "name:mkd_x_preferred":[
        "Osoj"
    ],
    "name:mkd_x_variant":[
        "\u041e\u0441\u043e\u0458"
    ],
    "wof:name":"Osoj",
    "wof:placetype":"locality"
},
  "geometry": {"coordinates":[20.93518,41.53234000000001],"type":"Point"}
}