{
  "type": "Feature",
  "properties": {
    "gn:admin1_code":"97",
    "gn:asciiname":"Rubejci",
    "gn:country_code":"MK",
    "gn:dem":513,
    "gn:feature_class":"P",
    "gn:feature_code":"PPL",
    "gn:name":"Rubejci",
    "gn:population":0,
    "gn:timezone":"Europe/Skopje",
    "iso:country":"MK",
    "name:mkd_x_preferred":[
        "Rubejci"
    ],
    "name:mkd_x_variant":[
        "\u0420\u0443\u0431\u0435\u0458\u0446\u0438"
    ],
    "wof:name":"Rubejci",
    "wof:placetype":"locality"
},
  "geometry": {"coordinates":[21.88515,42.25519],"type":"Point"}
}