{
  "type": "Feature",
  "properties": {
    "gn:country":"MK",
    "gn:fcode":"PPL",
    "gn:population":552,
    "iso:country":"MK",
    "name:mkd_x_preferred":[
        "\u0415\u0434\u0438\u043d\u0430\u043a\u043e\u0432\u0446\u0438"
    ],
    "name:und_x_variant":[
        "Edinakovce"
    ],
    "qs:name":"Edinakovo",
    "qs:photos_9r":0,
    "qs:photos_sr":0,
    "qs:pop_sr":"2",
    "wof:name":"Edinakovo",
    "wof:placetype":"locality",
    "wof:population":552
},
  "geometry": {"coordinates":[21.24694,41.26139],"type":"Point"}
}