{
  "type": "Feature",
  "properties": {
    "gn:admin1_code":"00",
    "gn:asciiname":"Milochovci",
    "gn:country_code":"MK",
    "gn:dem":1024,
    "gn:feature_class":"P",
    "gn:feature_code":"PPL",
    "gn:name":"\u041c\u0438\u043b\u043e\u0447\u043e\u0432\u0446\u0438",
    "gn:population":0,
    "gn:timezone":"Europe/Skopje",
    "iso:country":"MK",
    "name:eng_x_preferred":[
        "Milocovci"
    ],
    "name:mkd_x_preferred":[
        "\u041c\u0438\u043b\u043e\u0447\u043e\u0432\u0446\u0438"
    ],
    "wof:name":"Milochovci",
    "wof:placetype":"locality"
},
  "geometry": {"coordinates":[22.18778,42.23028],"type":"Point"}
}