{
  "type": "Feature",
  "properties": {
    "gn:country":"MK",
    "gn:fcode":"PPL",
    "gn:population":42,
    "iso:country":"MK",
    "name:mkd_x_preferred":[
        "\u041f\u0430\u0442\u0435\u0446"
    ],
    "name:mkd_x_variant":[
        "\u041f\u0430\u0442\u0435\u0435\u0446"
    ],
    "name:und_x_variant":[
        "Patejc"
    ],
    "qs:name":"Patec",
    "qs:photos_9r":0,
    "qs:photos_sr":0,
    "qs:pop_sr":"1",
    "wof:name":"Patec",
    "wof:placetype":"locality",
    "wof:population":42
},
  "geometry": {"coordinates":[21.11222,41.54222],"type":"Point"}
}