{
  "type": "Feature",
  "properties": {
    "gn:admin1_code":"06",
    "gn:asciiname":"Krstoar",
    "gn:country_code":"MK",
    "gn:dem":680,
    "gn:feature_class":"P",
    "gn:feature_code":"PPL",
    "gn:name":"Krstoar",
    "gn:population":0,
    "gn:timezone":"Europe/Skopje",
    "iso:country":"MK",
    "name:mkd_x_preferred":[
        "Krstoar"
    ],
    "name:mkd_x_variant":[
        "\u041a\u0440\u0441\u0442\u043e\u0430\u0440"
    ],
    "name:und_x_variant":[
        "Krstioar",
        "Hristifor",
        "Krstaor",
        "Krstor"
    ],
    "wof:name":"Krstoar",
    "wof:placetype":"locality"
},
  "geometry": {"coordinates":[21.34648,40.99209000000001],"type":"Point"}
}