{
  "type": "Feature",
  "properties": {
    "gn:admin1_code":"46",
    "gn:asciiname":"Ramno Niviste",
    "gn:country_code":"MK",
    "gn:dem":941,
    "gn:feature_class":"P",
    "gn:feature_code":"PPL",
    "gn:name":"Ramno Nivi\u0161te",
    "gn:population":0,
    "gn:timezone":"Europe/Skopje",
    "iso:country":"MK",
    "name:mkd_x_preferred":[
        "Ramno Nivi\u0161te"
    ],
    "name:mkd_x_variant":[
        "\u0420\u0430\u043c\u043d\u043e \u041d\u0438\u0432\u0438\u0448\u0442\u0435"
    ],
    "wof:name":"Ramno Niviste",
    "wof:placetype":"locality"
},
  "geometry": {"coordinates":[22.42871,42.03975],"type":"Point"}
}