{
  "type": "Feature",
  "properties": {
    "gn:admin1_code":"51",
    "gn:asciiname":"Kitanovska Maala",
    "gn:country_code":"MK",
    "gn:dem":539,
    "gn:feature_class":"P",
    "gn:feature_code":"PPL",
    "gn:name":"Kitanovska Maala",
    "gn:population":0,
    "gn:timezone":"Europe/Skopje",
    "iso:country":"MK",
    "name:mkd_x_preferred":[
        "Kitanovska Maala"
    ],
    "name:mkd_x_variant":[
        "\u041a\u0438\u0442\u0430\u043d\u043e\u0432\u0441\u043a\u0430 \u041c\u0430\u0430\u043b\u0430"
    ],
    "wof:name":"Kitanovska Maala",
    "wof:placetype":"locality"
},
  "geometry": {"coordinates":[22.0033,42.06214],"type":"Point"}
}