{
  "type": "Feature",
  "properties": {
    "gn:admin1_code":"97",
    "gn:asciiname":"Boskovci",
    "gn:country_code":"MK",
    "gn:dem":403,
    "gn:feature_class":"P",
    "gn:feature_code":"PPL",
    "gn:name":"Bo\u0161kovci",
    "gn:population":0,
    "gn:timezone":"Europe/Skopje",
    "iso:country":"MK",
    "name:mkd_x_preferred":[
        "Bo\u0161kovci"
    ],
    "name:mkd_x_variant":[
        "\u0411\u043e\u0448\u043a\u043e\u0432\u0446\u0438"
    ],
    "wof:name":"Boskovci",
    "wof:placetype":"locality"
},
  "geometry": {"coordinates":[21.85195,42.24353],"type":"Point"}
}