{
  "type": "Feature",
  "properties": {
    "gn:admin1_code":"52",
    "gn:asciiname":"Ciflik",
    "gn:country_code":"MK",
    "gn:dem":661,
    "gn:feature_class":"P",
    "gn:feature_code":"PPL",
    "gn:name":"\u010ciflik",
    "gn:population":0,
    "gn:timezone":"Europe/Skopje",
    "iso:country":"MK",
    "name:mkd_x_preferred":[
        "\u010ciflik"
    ],
    "name:mkd_x_variant":[
        "\u0427\u0438\u0444\u043b\u0438\u043a"
    ],
    "wof:name":"Ciflik",
    "wof:placetype":"locality"
},
  "geometry": {"coordinates":[22.29311,42.1829],"type":"Point"}
}