{
  "type": "Feature",
  "properties": {
    "gn:admin1_code":"A5",
    "gn:asciiname":"Brezno",
    "gn:country_code":"MK",
    "gn:dem":963,
    "gn:feature_class":"P",
    "gn:feature_code":"PPL",
    "gn:name":"Brezno",
    "gn:population":0,
    "gn:timezone":"Europe/Skopje",
    "iso:country":"MK",
    "name:ara_x_preferred":[
        "\u0628\u0631\u0632\u0646\u0648"
    ],
    "name:aze_x_preferred":[
        "Brezno"
    ],
    "name:bel_x_preferred":[
        "\u0411\u0440\u044d\u0437\u043d\u0430"
    ],
    "name:cat_x_preferred":[
        "Brezno"
    ],
    "name:ceb_x_preferred":[
        "Brezno"
    ],
    "name:ces_x_preferred":[
        "Brezno"
    ],
    "name:chv_x_preferred":[
        "\u0411\u0440\u0435\u0437\u043d\u043e"
    ],
    "name:dan_x_preferred":[
        "Brezno"
    ],
    "name:deu_x_preferred":[
        "Brezno"
    ],
    "name:epo_x_preferred":[
        "Brezno"
    ],
    "name:eus_x_preferred":[
        "Brezno"
    ],
    "name:fas_x_preferred":[
        "\u0628\u0631\u0632\u0646\u0648"
    ],
    "name:fin_x_preferred":[
        "Brezno"
    ],
    "name:fra_x_preferred":[
        "Brezno"
    ],
    "name:hrv_x_preferred":[
        "Brezno"
    ],
    "name:hun_x_preferred":[
        "Brezn\u00f3b\u00e1nya"
    ],
    "name:ind_x_preferred":[
        "Brezno"
    ],
    "name:ita_x_preferred":[
        "Brezno"
    ],
    "name:kor_x_preferred":[
        "\ube0c\ub808\uc988\ub178"
    ],
    "name:lav_x_preferred":[
        "Brezno"
    ],
    "name:lez_x_preferred":[
        "\u0411\u0440\u0435\u0437\u043d\u043e"
    ],
    "name:lim_x_preferred":[
        "Brezno"
    ],
    "name:lit_x_preferred":[
        "Breznas"
    ],
    "name:mkd_x_preferred":[
        "Brezno"
    ],
    "name:mkd_x_variant":[
        "\u0411\u0440\u0435\u0437\u043d\u043e"
    ],
    "name:msa_x_preferred":[
        "Brezno"
    ],
    "name:nld_x_preferred":[
        "Brezno"
    ],
    "name:pol_x_preferred":[
        "Brezno"
    ],
    "name:ron_x_preferred":[
        "Brezno"
    ],
    "name:rus_x_preferred":[
        "\u0411\u0440\u0435\u0437\u043d\u043e"
    ],
    "name:slk_x_preferred":[
        "Brezno"
    ],
    "name:spa_x_preferred":[
        "Brezno"
    ],
    "name:srp_x_preferred":[
        "\u0411\u0440\u0435\u0437\u043d\u043e"
    ],
    "name:swe_x_preferred":[
        "Brezno"
    ],
    "name:tur_x_preferred":[
        "Brezno"
    ],
    "name:ukr_x_preferred":[
        "\u0411\u0440\u0435\u0437\u043d\u043e"
    ],
    "name:vie_x_preferred":[
        "Brezno"
    ],
    "name:war_x_preferred":[
        "Brezno"
    ],
    "name:yid_x_preferred":[
        "\u05d1\u05e8\u05e2\u05d6\u05e0\u05d0"
    ],
    "name:zho_x_preferred":[
        "\u5e03\u96f7\u8332\u8afe"
    ],
    "wof:name":"Brezno",
    "wof:placetype":"locality"
},
  "geometry": {"coordinates":[21.03879,42.08684],"type":"Point"}
}