{
  "type": "Feature",
  "properties": {
    "gn:admin1_code":"A5",
    "gn:asciiname":"Brezno",
    "gn:country_code":"MK",
    "gn:dem":963,
    "gn:feature_class":"P",
    "gn:feature_code":"PPL",
    "gn:name":"Brezno",
    "gn:population":0,
    "gn:timezone":"Europe/Skopje",
    "iso:country":"MK",
    "name:mkd_x_preferred":[
        "Brezno"
    ],
    "name:mkd_x_variant":[
        "\u0411\u0440\u0435\u0437\u043d\u043e"
    ],
    "wof:name":"Brezno",
    "wof:placetype":"locality"
},
  "geometry": {"coordinates":[21.03879,42.08684],"type":"Point"}
}