{
  "type": "Feature",
  "properties": {
    "gn:admin1_code":"51",
    "gn:asciiname":"Tanasovci",
    "gn:country_code":"MK",
    "gn:dem":624,
    "gn:feature_class":"P",
    "gn:feature_code":"PPL",
    "gn:name":"Tanasovci",
    "gn:population":0,
    "gn:timezone":"Europe/Skopje",
    "iso:country":"MK",
    "name:mkd_x_preferred":[
        "Tanasovci"
    ],
    "name:mkd_x_variant":[
        "\u0422\u0430\u043d\u0430\u0441\u043e\u0432\u0446\u0438"
    ],
    "wof:name":"Tanasovci",
    "wof:placetype":"locality"
},
  "geometry": {"coordinates":[22.0205,42.13311],"type":"Point"}
}