{
  "type": "Feature",
  "properties": {
    "gn:admin1_code":"59",
    "gn:asciiname":"Maljok Maalo",
    "gn:country_code":"MK",
    "gn:dem":962,
    "gn:feature_class":"P",
    "gn:feature_code":"PPL",
    "gn:name":"Maljok Maalo",
    "gn:population":0,
    "gn:timezone":"Europe/Skopje",
    "iso:country":"MK",
    "name:mkd_x_preferred":[
        "\u041c\u0430\u0459\u043e\u043a \u041c\u0430\u0430\u043b\u043e"
    ],
    "name:und_x_variant":[
        "Maljok Mahala",
        "Maljok Maalo"
    ],
    "wof:name":"Maljok Maalo",
    "wof:placetype":"locality"
},
  "geometry": {"coordinates":[21.51887,42.21272],"type":"Point"}
}