{
  "type": "Feature",
  "properties": {
    "gn:admin1_code":"46",
    "gn:asciiname":"Jastrebnik",
    "gn:country_code":"MK",
    "gn:dem":989,
    "gn:feature_class":"P",
    "gn:feature_code":"PPLL",
    "gn:name":"Jastrebnik",
    "gn:population":0,
    "gn:timezone":"Europe/Skopje",
    "iso:country":"MK",
    "name:bos_x_preferred":[
        "Jastrebnik"
    ],
    "name:mkd_x_preferred":[
        "Jastrebnik"
    ],
    "name:mkd_x_variant":[
        "\u0408\u0430\u0441\u0442\u0440\u0435\u0431\u043d\u0438\u043a"
    ],
    "name:nld_x_preferred":[
        "Jastrebnik"
    ],
    "name:pol_x_preferred":[
        "Jastrebnik"
    ],
    "name:ron_x_preferred":[
        "Jastrebnik"
    ],
    "name:slv_x_preferred":[
        "Jastrebnik"
    ],
    "name:ukr_x_preferred":[
        "\u042f\u0441\u0442\u0440\u0435\u0431\u043d\u0438\u043a"
    ],
    "name:urd_x_preferred":[
        "\u062c\u0633\u062a\u0631\u0628\u0646\u06a9"
    ],
    "wof:name":"Jastrebnik",
    "wof:placetype":"locality"
},
  "geometry": {"coordinates":[22.40047,41.99992],"type":"Point"}
}