{
  "type": "Feature",
  "properties": {
    "gn:admin1_code":"20",
    "gn:asciiname":"Kaorivetm Maala",
    "gn:country_code":"MK",
    "gn:dem":1081,
    "gn:feature_class":"P",
    "gn:feature_code":"PPL",
    "gn:name":"Kaorivetm Maala",
    "gn:population":0,
    "gn:timezone":"Europe/Skopje",
    "iso:country":"MK",
    "name:mkd_x_preferred":[
        "\u041a\u0430\u043e\u0440\u0438\u0432\u0435\u0442\u043c \u041c\u0430\u0430\u043b\u0430"
    ],
    "name:und_x_variant":[
        "Kaorivetm Mahala",
        "Kaorivetm Maala"
    ],
    "wof:name":"Kaorivetm Maala",
    "wof:placetype":"locality"
},
  "geometry": {"coordinates":[21.5112,42.18155],"type":"Point"}
}