{
  "type": "Feature",
  "properties": {
    "gn:admin1_code":"E2",
    "gn:asciiname":"Raskrs",
    "gn:country_code":"MK",
    "gn:dem":864,
    "gn:feature_class":"P",
    "gn:feature_code":"PPL",
    "gn:name":"Raskrs",
    "gn:population":0,
    "gn:timezone":"Europe/Skopje",
    "iso:country":"MK",
    "name:mkd_x_preferred":[
        "Raskrs"
    ],
    "name:mkd_x_variant":[
        "\u0420\u0430\u0441\u043a\u0440\u0441"
    ],
    "wof:name":"Raskrs",
    "wof:placetype":"locality"
},
  "geometry": {"coordinates":[20.85863,41.22194],"type":"Point"}
}