{
  "type": "Feature",
  "properties": {
    "gn:admin1_code":"18",
    "gn:asciiname":"Elevci",
    "gn:country_code":"MK",
    "gn:dem":1102,
    "gn:feature_class":"P",
    "gn:feature_code":"PPL",
    "gn:name":"Elevci",
    "gn:population":0,
    "gn:timezone":"Europe/Skopje",
    "iso:country":"MK",
    "name:bul_x_preferred":[
        "\u0415\u043b\u0435\u0432\u0446\u0438"
    ],
    "name:fra_x_preferred":[
        "Elevtsi"
    ],
    "name:hun_x_preferred":[
        "Elevci"
    ],
    "name:mkd_x_preferred":[
        "Elevci"
    ],
    "name:mkd_x_variant":[
        "\u0415\u043b\u0435\u0432\u0446\u0438"
    ],
    "name:sqi_x_preferred":[
        "Elevca"
    ],
    "name:srp_x_preferred":[
        "\u0415\u043b\u0435\u0432\u0446\u0438"
    ],
    "wof:name":"Elevci",
    "wof:placetype":"locality"
},
  "geometry": {"coordinates":[20.62343,41.42019000000001],"type":"Point"}
}