{
  "type": "Feature",
  "properties": {
    "gn:country":"MK",
    "gn:fcode":"PPL",
    "gn:pop":205,
    "iso:country":"MK",
    "name:mkd_x_preferred":[
        "Novo Selo"
    ],
    "name:mkd_x_variant":[
        "\u041d\u043e\u0432\u043e \u0421\u0435\u043b\u043e"
    ],
    "qs:name":"Novo Selo",
    "qs:photos_9r":0,
    "qs:photos_sr":0,
    "qs:pop_sr":"2",
    "wd:wordcount":872,
    "wof:name":"Novo Selo",
    "wof:placetype":"locality",
    "wof:population":205
},
  "geometry": {"coordinates":[21.6225,41.85444],"type":"Point"}
}