{
  "type": "Feature",
  "properties": {
    "gn:country":"MK",
    "gn:fcode":"PPL",
    "gn:pop":1281,
    "iso:country":"MK",
    "name:bul_x_preferred":[
        "\u041a\u043e\u0441\u0435\u043b"
    ],
    "name:eng_x_preferred":[
        "Kosel"
    ],
    "name:fra_x_preferred":[
        "Kosel"
    ],
    "name:hun_x_preferred":[
        "Koszel"
    ],
    "name:mkd_x_preferred":[
        "\u041a\u043e\u0441\u0435\u043b"
    ],
    "name:nld_x_preferred":[
        "Kosel"
    ],
    "name:pol_x_preferred":[
        "Kose\u0142"
    ],
    "name:srp_x_preferred":[
        "\u041a\u043e\u0441\u0435\u043b"
    ],
    "name:swe_x_preferred":[
        "Kosel"
    ],
    "name:unk_x_variant":[
        "Koselj"
    ],
    "qs:name":"Kosel",
    "qs:photos_9r":0,
    "qs:photos_sr":0,
    "qs:pop_sr":"3",
    "wd:wordcount":41,
    "wof:name":"Kosel",
    "wof:placetype":"locality",
    "wof:population":1281
},
  "geometry": {"coordinates":[20.83556,41.17444],"type":"Point"}
}