{
  "type": "Feature",
  "properties": {
    "gn:country":"MK",
    "gn:fcode":"PPL",
    "gn:population":60,
    "iso:country":"MK",
    "name:eng_x_preferred":[
        "Blace"
    ],
    "name:mkd_x_preferred":[
        "\u0411\u043b\u0430\u0446\u0435"
    ],
    "qs:name":"\u0411\u043b\u0430\u0446\u0435",
    "qs:photos_9r":0,
    "qs:photos_sr":0,
    "qs:pop_sr":"1",
    "wof:name":"\u0411\u043b\u0430\u0446\u0435",
    "wof:placetype":"locality",
    "wof:population":60
},
  "geometry": {"coordinates":[21.665,41.87139],"type":"Point"}
}