{
  "type": "Feature",
  "properties": {
    "gn:country":"MK",
    "gn:fcode":"PPL",
    "gn:population":186,
    "iso:country":"MK",
    "name:bos_x_preferred":[
        "Breznica"
    ],
    "name:bul_x_preferred":[
        "\u0411\u0440\u0435\u0437\u043d\u0438\u0446\u0430"
    ],
    "name:ceb_x_preferred":[
        "Breznica"
    ],
    "name:ces_x_preferred":[
        "Breznica"
    ],
    "name:deu_x_preferred":[
        "Breznica"
    ],
    "name:eng_x_preferred":[
        "Breznica"
    ],
    "name:epo_x_preferred":[
        "Breznica"
    ],
    "name:fra_x_preferred":[
        "Breznica"
    ],
    "name:hrv_x_preferred":[
        "Breznica"
    ],
    "name:hun_x_preferred":[
        "Breznica"
    ],
    "name:ita_x_preferred":[
        "Breznica"
    ],
    "name:mkd_x_preferred":[
        "\u0411\u0440\u0435\u0437\u043d\u0438\u0446\u0430"
    ],
    "name:nld_x_preferred":[
        "Breznica"
    ],
    "name:pol_x_preferred":[
        "Breznica"
    ],
    "name:rus_x_preferred":[
        "\u0411\u0440\u0435\u0437\u043d\u0438\u0446\u0430"
    ],
    "name:slk_x_preferred":[
        "Breznica"
    ],
    "name:slv_x_preferred":[
        "Breznica"
    ],
    "name:sqi_x_preferred":[
        "Breznica"
    ],
    "name:srp_x_preferred":[
        "\u0411\u0440\u0435\u0437\u043d\u0438\u0446\u0430"
    ],
    "name:swe_x_preferred":[
        "Breznica"
    ],
    "name:ukr_x_preferred":[
        "\u0411\u0440\u0435\u0437\u043d\u0438\u0446\u044f"
    ],
    "name:und_x_variant":[
        "Bresnica"
    ],
    "qs:name":"Breznica",
    "qs:photos_9r":0,
    "qs:photos_sr":0,
    "qs:pop_sr":"1",
    "wd:wordcount":105,
    "wof:name":"Breznica",
    "wof:placetype":"locality",
    "wof:population":186
},
  "geometry": {"coordinates":[21.22639,41.73667],"type":"Point"}
}