{
  "type": "Feature",
  "properties": {
    "gn:country":"MK",
    "gn:fcode":"PPL",
    "gn:pop":186,
    "iso:country":"MK",
    "name:mkd_x_preferred":[
        "\u0411\u0440\u0435\u0437\u043d\u0438\u0446\u0430"
    ],
    "name:unk_x_variant":[
        "Bresnica"
    ],
    "qs:name":"Breznica",
    "qs:photos_9r":0,
    "qs:photos_sr":0,
    "qs:pop_sr":"1",
    "wd:wordcount":105,
    "wof:name":"Breznica",
    "wof:placetype":"locality",
    "wof:population":186
},
  "geometry": {"coordinates":[21.22639,41.73667],"type":"Point"}
}