{
  "type": "Feature",
  "properties": {
    "gn:admin1_code":"52",
    "gn:asciiname":"Popadeska Maala",
    "gn:country_code":"MK",
    "gn:dem":1012,
    "gn:feature_class":"P",
    "gn:feature_code":"PPL",
    "gn:name":"Popadeska Maala",
    "gn:population":0,
    "gn:timezone":"Europe/Skopje",
    "iso:country":"MK",
    "name:mkd_x_preferred":[
        "Popadeska Maala"
    ],
    "name:mkd_x_variant":[
        "\u041f\u043e\u043f\u0430\u0434\u0435\u0441\u043a\u0430 \u041c\u0430\u0430\u043b\u0430"
    ],
    "wof:name":"Popadeska Maala",
    "wof:placetype":"locality"
},
  "geometry": {"coordinates":[22.28389,42.31694],"type":"Point"}
}