{
  "type": "Feature",
  "properties": {
    "gn:country":"MK",
    "gn:fcode":"PPL",
    "gn:population":196,
    "iso:country":"MK",
    "name:bul_x_preferred":[
        "\u0410\u043b\u0438\u043d\u0446\u0438"
    ],
    "name:ceb_x_preferred":[
        "Alinci"
    ],
    "name:deu_x_preferred":[
        "Alinci"
    ],
    "name:eng_x_preferred":[
        "Alinci"
    ],
    "name:fra_x_preferred":[
        "Alintsi"
    ],
    "name:hun_x_preferred":[
        "Alinci"
    ],
    "name:mkd_x_preferred":[
        "\u0410\u043b\u0438\u043d\u0446\u0438"
    ],
    "name:nan_x_preferred":[
        "Alintsi"
    ],
    "name:nld_x_preferred":[
        "Alinci"
    ],
    "name:sqi_x_preferred":[
        "Alinci"
    ],
    "name:srp_x_preferred":[
        "\u0410\u043b\u0438\u043d\u0446\u0438"
    ],
    "name:swe_x_preferred":[
        "Alinci"
    ],
    "name:und_x_variant":[
        "Ali Oba"
    ],
    "qs:name":"Alinci",
    "qs:photos_9r":0,
    "qs:photos_sr":0,
    "qs:pop_sr":"1",
    "wd:wordcount":89,
    "wof:name":"Alinci",
    "wof:placetype":"locality",
    "wof:population":196
},
  "geometry": {"coordinates":[21.50528,41.15111],"type":"Point"}
}