{
  "type": "Feature",
  "properties": {
    "gn:country":"MK",
    "gn:fcode":"PPL",
    "gn:pop":196,
    "iso:country":"MK",
    "name:mkd_x_preferred":[
        "\u0410\u043b\u0438\u043d\u0446\u0438"
    ],
    "name:unk_x_variant":[
        "Ali Oba"
    ],
    "qs:name":"Alinci",
    "qs:photos_9r":0,
    "qs:photos_sr":0,
    "qs:pop_sr":"1",
    "wd:wordcount":89,
    "wof:name":"Alinci",
    "wof:placetype":"locality",
    "wof:population":196
},
  "geometry": {"coordinates":[21.50528,41.15111],"type":"Point"}
}