{
  "type": "Feature",
  "properties": {
    "gn:country":"MK",
    "gn:fcode":"PPL",
    "gn:population":2110,
    "iso:country":"MK",
    "name:bul_x_preferred":[
        "\u0421\u043e\u043f\u043e\u0442\u043d\u0438\u0446\u0430"
    ],
    "name:ceb_x_preferred":[
        "Sopotnica"
    ],
    "name:ces_x_preferred":[
        "Sopotnica"
    ],
    "name:deu_x_preferred":[
        "Sopotnica"
    ],
    "name:eng_x_preferred":[
        "Sopotnica"
    ],
    "name:epo_x_preferred":[
        "Sopotnica"
    ],
    "name:fra_x_preferred":[
        "Sopotnitsa"
    ],
    "name:hun_x_preferred":[
        "Sopotnica"
    ],
    "name:ita_x_preferred":[
        "Sopotnica"
    ],
    "name:mkd_x_preferred":[
        "\u0421\u043e\u043f\u043e\u0442\u043d\u0438\u0446\u0430"
    ],
    "name:nan_x_preferred":[
        "Sopotnitsa"
    ],
    "name:nld_x_preferred":[
        "Sopotnica"
    ],
    "name:nno_x_preferred":[
        "Sopotnitsa"
    ],
    "name:pol_x_preferred":[
        "Sopotnica"
    ],
    "name:por_x_preferred":[
        "Sopotnica"
    ],
    "name:ron_x_preferred":[
        "Sopotnica"
    ],
    "name:slk_x_preferred":[
        "Sopotnica"
    ],
    "name:spa_x_preferred":[
        "Sopotnica"
    ],
    "name:sqi_x_preferred":[
        "Sopotnica"
    ],
    "name:srp_x_preferred":[
        "\u0421\u043e\u043f\u043e\u0442\u043d\u0438\u0446\u0430"
    ],
    "name:swe_x_preferred":[
        "Sopotnica"
    ],
    "qs:name":"Sopotnica",
    "qs:name_adm0":"Macedonia",
    "qs:name_adm1":"Demir Hisar",
    "qs:photos_9r":0,
    "qs:photos_sr":0,
    "qs:placetype":"Town",
    "qs:pop_sr":"4",
    "wd:wordcount":75,
    "wof:name":"Sopotnica",
    "wof:placetype":"locality",
    "wof:population":2110
},
  "geometry": {"coordinates":[21.155,41.29472],"type":"Point"}
}