{
  "type": "Feature",
  "properties": {
    "gn:admin1_code":"52",
    "gn:asciiname":"Durcica Maala",
    "gn:country_code":"MK",
    "gn:dem":1074,
    "gn:feature_class":"P",
    "gn:feature_code":"PPL",
    "gn:name":"Dur\u010dica Maala",
    "gn:population":0,
    "gn:timezone":"Europe/Skopje",
    "iso:country":"MK",
    "name:mkd_x_preferred":[
        "Dur\u010dica Maala"
    ],
    "name:mkd_x_variant":[
        "\u0414\u0443\u0440\u0447\u0438\u0446\u0430 \u041c\u0430\u0430\u043b\u0430"
    ],
    "wof:name":"Durcica Maala",
    "wof:placetype":"locality"
},
  "geometry": {"coordinates":[22.3789,42.25909],"type":"Point"}
}