{
  "type": "Feature",
  "properties": {
    "gn:admin1_code":"51",
    "gn:asciiname":"Talasmance",
    "gn:country_code":"MK",
    "gn:dem":619,
    "gn:feature_class":"P",
    "gn:feature_code":"PPLL",
    "gn:name":"Tala\u0161mance",
    "gn:population":0,
    "gn:timezone":"Europe/Skopje",
    "iso:country":"MK",
    "name:mkd_x_preferred":[
        "\u0422\u0430\u043b\u0430\u0448\u043c\u0430\u043d\u0446\u0435"
    ],
    "name:und_x_variant":[
        "Tala\u0161manci",
        "Tala\u0161mance"
    ],
    "wof:name":"Talasmance",
    "wof:placetype":"locality"
},
  "geometry": {"coordinates":[22.12417,42.10556],"type":"Point"}
}