{
  "type": "Feature",
  "properties": {
    "gn:admin1_code":"52",
    "gn:asciiname":"Toranica",
    "gn:country_code":"MK",
    "gn:dem":1445,
    "gn:feature_class":"P",
    "gn:feature_code":"PPL",
    "gn:name":"Toranica",
    "gn:population":0,
    "gn:timezone":"Europe/Skopje",
    "iso:country":"MK",
    "name:mkd_x_preferred":[
        "Toranica"
    ],
    "name:mkd_x_variant":[
        "\u0422\u043e\u0440\u0430\u043d\u0438\u0446\u0430"
    ],
    "wof:name":"Toranica",
    "wof:placetype":"locality"
},
  "geometry": {"coordinates":[22.48327,42.16765],"type":"Point"}
}