{
  "type": "Feature",
  "properties": {
    "gn:admin1_code":"86",
    "gn:asciiname":"Ilino",
    "gn:country_code":"MK",
    "gn:dem":1060,
    "gn:feature_class":"P",
    "gn:feature_code":"PPL",
    "gn:name":"Ilino",
    "gn:population":0,
    "gn:timezone":"Europe/Skopje",
    "iso:country":"MK",
    "name:mkd_x_preferred":[
        "Ilino"
    ],
    "name:mkd_x_variant":[
        "\u0418\u043b\u0438\u043d\u043e"
    ],
    "wof:name":"Ilino",
    "wof:placetype":"locality"
},
  "geometry": {"coordinates":[20.95889,41.15],"type":"Point"}
}