{
  "type": "Feature",
  "properties": {
    "gn:country":"MK",
    "gn:fcode":"PPL",
    "gn:pop":110,
    "iso:country":"MK",
    "name:mkd_x_preferred":[
        "\u041a\u043e\u0447\u0438\u0448\u0442\u0435"
    ],
    "name:unk_x_variant":[
        "Ko\u010di\u0161ta"
    ],
    "qs:name":"Ko\u010di\u0161te",
    "qs:photos_9r":0,
    "qs:photos_sr":0,
    "qs:pop_sr":"1",
    "wd:wordcount":194,
    "wof:name":"Ko\u010di\u0161te",
    "wof:placetype":"locality",
    "wof:population":110
},
  "geometry": {"coordinates":[21.1725,41.34444],"type":"Point"}
}