{
  "type": "Feature",
  "properties": {
    "gn:admin1_code":"52",
    "gn:asciiname":"Kiselica Maala",
    "gn:country_code":"MK",
    "gn:dem":1060,
    "gn:feature_class":"P",
    "gn:feature_code":"PPL",
    "gn:name":"Kiselica Maala",
    "gn:population":0,
    "gn:timezone":"Europe/Skopje",
    "iso:country":"MK",
    "name:mkd_x_preferred":[
        "Kiselica Maala"
    ],
    "name:mkd_x_variant":[
        "\u041a\u0438\u0441\u0435\u043b\u0438\u0446\u0430 \u041c\u0430\u0430\u043b\u0430"
    ],
    "wof:name":"Kiselica Maala",
    "wof:placetype":"locality"
},
  "geometry": {"coordinates":[22.23018,42.14203],"type":"Point"}
}