{
  "type": "Feature",
  "properties": {
    "gn:admin1_code":"C3",
    "gn:asciiname":"Trebos",
    "gn:country_code":"MK",
    "gn:dem":423,
    "gn:feature_class":"P",
    "gn:feature_code":"PPL",
    "gn:name":"Trebo\u0161",
    "gn:population":0,
    "gn:timezone":"Europe/Skopje",
    "iso:country":"MK",
    "name:mkd_x_preferred":[
        "Trebo\u0161"
    ],
    "name:mkd_x_variant":[
        "\u0422\u0440\u0435\u0431\u043e\u0448"
    ],
    "wof:name":"Trebos",
    "wof:placetype":"locality"
},
  "geometry": {"coordinates":[21.03175,42.01335],"type":"Point"}
}