{
  "type": "Feature",
  "properties": {
    "gn:country":"MK",
    "gn:fcode":"PPL",
    "gn:population":500,
    "iso:country":"MK",
    "name:bul_x_preferred":[
        "\u041f\u0435\u0449\u0430\u043b\u0435\u0432\u043e"
    ],
    "name:ceb_x_preferred":[
        "Pe\u0161talevo"
    ],
    "name:eng_x_preferred":[
        "Pe\u0161talevo"
    ],
    "name:fra_x_preferred":[
        "Pechtalevo"
    ],
    "name:hun_x_preferred":[
        "Pestalevo"
    ],
    "name:mkd_x_preferred":[
        "\u041f\u0435\u0448\u0442\u0430\u043b\u0435\u0432\u043e"
    ],
    "name:nan_x_preferred":[
        "Pechtalevo"
    ],
    "name:nld_x_preferred":[
        "Pe\u0161talevo"
    ],
    "name:sqi_x_preferred":[
        "Peshtaleva"
    ],
    "name:srp_x_preferred":[
        "\u041f\u0435\u0448\u0442\u0430\u0459\u0435\u0432\u043e"
    ],
    "name:swe_x_preferred":[
        "Pesjtalevo"
    ],
    "name:und_x_variant":[
        "Pe\u0161taljevo"
    ],
    "qs:name":"Pe\u0161talevo",
    "qs:photos_9r":0,
    "qs:photos_sr":0,
    "qs:pop_sr":"2",
    "wd:wordcount":44,
    "wof:name":"Pe\u0161talevo",
    "wof:placetype":"locality",
    "wof:population":500
},
  "geometry": {"coordinates":[21.39667,41.46194],"type":"Point"}
}