{
  "type": "Feature",
  "properties": {
    "gn:admin1_code":"97",
    "gn:asciiname":"Dlabocica",
    "gn:country_code":"MK",
    "gn:dem":881,
    "gn:feature_class":"P",
    "gn:feature_code":"PPLL",
    "gn:name":"Dlabo\u010dica",
    "gn:population":0,
    "gn:timezone":"Europe/Skopje",
    "iso:country":"MK",
    "name:mkd_x_preferred":[
        "\u0414\u043b\u0430\u0431\u043e\u0447\u0438\u0446\u0430"
    ],
    "name:und_x_variant":[
        "Dlabo\u010dia",
        "Dlbo\u010dica",
        "Dolbo\u010dica",
        "Dubo\u010dica",
        "Dlabo\u010dica"
    ],
    "wof:name":"Dlabocica",
    "wof:placetype":"locality"
},
  "geometry": {"coordinates":[22.0425,42.29028],"type":"Point"}
}