{
  "type": "Feature",
  "properties": {
    "gn:country":"MK",
    "gn:fcode":"PPL",
    "gn:population":1466,
    "iso:country":"MK",
    "name:und_x_variant":[
        "Kadino Selo"
    ],
    "qs:name":"\u041a\u0430\u0434\u0438\u043d\u043e",
    "qs:photos_9r":0,
    "qs:photos_sr":0,
    "qs:pop_sr":"3",
    "wof:name":"\u041a\u0430\u0434\u0438\u043d\u043e",
    "wof:placetype":"locality",
    "wof:population":1466
},
  "geometry": {"coordinates":[21.60139,41.96889],"type":"Point"}
}