{
  "type": "Feature",
  "properties": {
    "gn:country":"MK",
    "gn:fcode":"PPL",
    "gn:population":250,
    "iso:country":"MK",
    "name:bul_x_preferred":[
        "\u0412\u0435\u043b\u0435\u0441"
    ],
    "name:deu_x_preferred":[
        "Op\u0161tina Veles"
    ],
    "name:ell_x_preferred":[
        "\u0394\u03ae\u03bc\u03bf\u03c2 \u0392\u03b5\u03bb\u03b5\u03c3\u03ac"
    ],
    "name:eng_x_preferred":[
        "Veles Municipality"
    ],
    "name:fas_x_preferred":[
        "\u0648\u0644\u0633 \u0645\u0648\u0646\u06cc\u06a9\u06cc\u067e\u0644\u06cc\u062a\u06cc"
    ],
    "name:fra_x_preferred":[
        "V\u00e9l\u00e8s"
    ],
    "name:hrv_x_preferred":[
        "Op\u0107ina Veles"
    ],
    "name:hye_x_preferred":[
        "\u054e\u0565\u056c\u0565\u057d\u056b \u0570\u0561\u0574\u0561\u0575\u0576\u0584"
    ],
    "name:ind_x_preferred":[
        "Munisipalitas Veles"
    ],
    "name:ita_x_preferred":[
        "Veles"
    ],
    "name:kat_x_preferred":[
        "\u10d5\u10d4\u10da\u10d4\u10e1\u10d8\u10e1 \u10d7\u10d4\u10db\u10d8"
    ],
    "name:kor_x_preferred":[
        "\ubca8\ub808\uc2a4 \uc2dc"
    ],
    "name:mkd_x_preferred":[
        "\u041e\u0442\u043e\u0432\u0438\u0446\u0430"
    ],
    "name:mkd_x_variant":[
        "\u041e\u043f\u0448\u0442\u0438\u043d\u0430 \u0412\u0435\u043b\u0435\u0441"
    ],
    "name:nan_x_preferred":[
        "Veles Chh\u012b"
    ],
    "name:nld_x_preferred":[
        "Veles"
    ],
    "name:ron_x_preferred":[
        "Veles"
    ],
    "name:rus_x_preferred":[
        "\u0412\u0435\u043b\u0435\u0441"
    ],
    "name:srp_x_preferred":[
        "\u041e\u043f\u0448\u0442\u0438\u043d\u0430 \u0412\u0435\u043b\u0435\u0441"
    ],
    "name:tgk_x_preferred":[
        "\u0412\u0438\u043b\u043e\u044f\u0442\u0438 \u0412\u0435\u043b\u0435\u0441"
    ],
    "name:ukr_x_preferred":[
        "\u0412\u0435\u043b\u0435\u0441"
    ],
    "name:und_x_variant":[
        "Otavica"
    ],
    "name:urd_x_preferred":[
        "\u0648\u06cc\u0644\u06cc\u0633 \u0628\u0644\u062f\u06cc\u06c1"
    ],
    "name:zho_x_preferred":[
        "\u97cb\u840a\u65af\u5340"
    ],
    "qs:name":"Otovica",
    "qs:photos_9r":0,
    "qs:photos_sr":0,
    "qs:pop_sr":"2",
    "wd:wordcount":153,
    "wof:name":"Otovica",
    "wof:placetype":"locality",
    "wof:population":250
},
  "geometry": {"coordinates":[21.77778,41.77333],"type":"Point"}
}