{
  "type": "Feature",
  "properties": {
    "gn:country":"MK",
    "gn:fcode":"PPL",
    "gn:pop":250,
    "iso:country":"MK",
    "name:mkd_x_preferred":[
        "\u041e\u0442\u043e\u0432\u0438\u0446\u0430"
    ],
    "name:unk_x_variant":[
        "Otavica"
    ],
    "qs:name":"Otovica",
    "qs:photos_9r":0,
    "qs:photos_sr":0,
    "qs:pop_sr":"2",
    "wd:wordcount":153,
    "wof:name":"Otovica",
    "wof:placetype":"locality",
    "wof:population":250
},
  "geometry": {"coordinates":[21.77778,41.77333],"type":"Point"}
}