{
  "type": "Feature",
  "properties": {
    "gn:admin1_code":"97",
    "gn:asciiname":"Dzembasci",
    "gn:country_code":"MK",
    "gn:dem":564,
    "gn:feature_class":"P",
    "gn:feature_code":"PPL",
    "gn:name":"D\u017eembasci",
    "gn:population":0,
    "gn:timezone":"Europe/Skopje",
    "iso:country":"MK",
    "name:mkd_x_preferred":[
        "D\u017eembasci"
    ],
    "name:mkd_x_variant":[
        "\u040f\u0435\u043c\u0431\u0430\u0441\u0446\u0438"
    ],
    "wof:name":"Dzembasci",
    "wof:placetype":"locality"
},
  "geometry": {"coordinates":[21.96698,42.2078],"type":"Point"}
}