{
  "type": "Feature",
  "properties": {
    "gn:admin1_code":"97",
    "gn:asciiname":"Smiljcevci",
    "gn:country_code":"MK",
    "gn:dem":426,
    "gn:feature_class":"P",
    "gn:feature_code":"PPL",
    "gn:name":"Smilj\u010devci",
    "gn:population":0,
    "gn:timezone":"Europe/Skopje",
    "iso:country":"MK",
    "name:mkd_x_preferred":[
        "Smilj\u010devci"
    ],
    "name:mkd_x_variant":[
        "\u0421\u043c\u0438\u0459\u0447\u0435\u0432\u0446\u0438"
    ],
    "wof:name":"Smiljcevci",
    "wof:placetype":"locality"
},
  "geometry": {"coordinates":[21.79371,42.17518],"type":"Point"}
}