{
  "type": "Feature",
  "properties": {
    "gn:admin1_code":"51",
    "gn:asciiname":"Musinci",
    "gn:country_code":"MK",
    "gn:dem":525,
    "gn:feature_class":"P",
    "gn:feature_code":"PPL",
    "gn:name":"Musinci",
    "gn:population":0,
    "gn:timezone":"Europe/Skopje",
    "iso:country":"MK",
    "name:bul_x_preferred":[
        "\u041c\u0443\u0441\u0438\u043d\u0446\u0438"
    ],
    "name:ceb_x_preferred":[
        "Musinci"
    ],
    "name:fra_x_preferred":[
        "Mousintsi"
    ],
    "name:mkd_x_preferred":[
        "Musinci"
    ],
    "name:mkd_x_variant":[
        "\u041c\u0443\u0441\u0438\u043d\u0446\u0438"
    ],
    "name:sqi_x_preferred":[
        "Musinca"
    ],
    "name:srp_x_preferred":[
        "\u041c\u0443\u0441\u0438\u043d\u0446\u0438"
    ],
    "name:swe_x_preferred":[
        "Musinci"
    ],
    "wof:name":"Musinci",
    "wof:placetype":"locality"
},
  "geometry": {"coordinates":[22.11218,42.11522],"type":"Point"}
}