{
  "type": "Feature",
  "properties": {
    "gn:admin1_code":"D7",
    "gn:asciiname":"Vilipovci",
    "gn:country_code":"MK",
    "gn:dem":558,
    "gn:feature_class":"P",
    "gn:feature_code":"PPL",
    "gn:name":"Vilipovci",
    "gn:population":0,
    "gn:timezone":"Europe/Skopje",
    "iso:country":"MK",
    "name:mkd_x_preferred":[
        "Vilipovci"
    ],
    "name:mkd_x_variant":[
        "\u0412\u0438\u043b\u0438\u043f\u043e\u0432\u0446\u0438"
    ],
    "wof:name":"Vilipovci",
    "wof:placetype":"locality"
},
  "geometry": {"coordinates":[21.9351,42.03447],"type":"Point"}
}