{
  "type": "Feature",
  "properties": {
    "gn:country":"MK",
    "gn:fcode":"PPL",
    "gn:population":552,
    "iso:country":"MK",
    "name:afr_x_preferred":[
        "Novo Selo"
    ],
    "name:arg_x_preferred":[
        "Novo Selo"
    ],
    "name:bos_x_preferred":[
        "Novo Selo"
    ],
    "name:bre_x_preferred":[
        "Novo Selo"
    ],
    "name:bul_x_preferred":[
        "\u041d\u043e\u0432\u043e \u0441\u0435\u043b\u043e"
    ],
    "name:cat_x_preferred":[
        "Novo Selo"
    ],
    "name:ceb_x_preferred":[
        "Novo Selo"
    ],
    "name:ces_x_preferred":[
        "Novo Selo"
    ],
    "name:dan_x_preferred":[
        "Novo Selo"
    ],
    "name:deu_x_preferred":[
        "Novo Selo"
    ],
    "name:eng_x_preferred":[
        "Novo Selo"
    ],
    "name:epo_x_preferred":[
        "Novo Selo"
    ],
    "name:est_x_preferred":[
        "Novo Selo"
    ],
    "name:eus_x_preferred":[
        "Novo Selo"
    ],
    "name:fin_x_preferred":[
        "Novo Selo"
    ],
    "name:fra_x_preferred":[
        "Novo Selo"
    ],
    "name:gle_x_preferred":[
        "Novo Selo"
    ],
    "name:glg_x_preferred":[
        "Novo Selo"
    ],
    "name:gsw_x_preferred":[
        "Novo Selo"
    ],
    "name:hrv_x_preferred":[
        "Novo Selo"
    ],
    "name:hun_x_preferred":[
        "Novo Selo"
    ],
    "name:isl_x_preferred":[
        "Novo Selo"
    ],
    "name:ita_x_preferred":[
        "Novo Selo"
    ],
    "name:jpn_x_preferred":[
        "\u30ce\u30f4\u30a9\u30fb\u30bb\u30ed"
    ],
    "name:kaz_x_preferred":[
        "Novo Selo"
    ],
    "name:lit_x_preferred":[
        "Novo Selo"
    ],
    "name:lmo_x_preferred":[
        "Novo Selo"
    ],
    "name:ltz_x_preferred":[
        "Novo Selo"
    ],
    "name:mkd_x_preferred":[
        "Novo Selo"
    ],
    "name:mkd_x_variant":[
        "\u041d\u043e\u0432\u043e \u0421\u0435\u043b\u043e"
    ],
    "name:nld_x_preferred":[
        "Novo Selo"
    ],
    "name:nno_x_preferred":[
        "Novo Selo"
    ],
    "name:nob_x_preferred":[
        "Novo Selo"
    ],
    "name:pms_x_preferred":[
        "Novo Selo"
    ],
    "name:pol_x_preferred":[
        "Nowo Se\u0142o"
    ],
    "name:por_x_preferred":[
        "Novo Selo"
    ],
    "name:ron_x_preferred":[
        "Novo Selo"
    ],
    "name:rus_x_preferred":[
        "\u041d\u043e\u0432\u043e-\u0421\u0435\u043b\u043e"
    ],
    "name:slk_x_preferred":[
        "Novo Selo"
    ],
    "name:slv_x_preferred":[
        "Novo Selo"
    ],
    "name:spa_x_preferred":[
        "Novo Selo"
    ],
    "name:sqi_x_preferred":[
        "Novo Selo"
    ],
    "name:srp_x_preferred":[
        "\u041d\u043e\u0432\u043e \u0421\u0435\u043b\u043e"
    ],
    "name:swe_x_preferred":[
        "Novo Selo"
    ],
    "name:tur_x_preferred":[
        "Novo Selo"
    ],
    "name:ukr_x_preferred":[
        "\u041d\u043e\u0432\u043e-\u0421\u0435\u043b\u043e"
    ],
    "name:wln_x_preferred":[
        "Novo Selo"
    ],
    "qs:name":"Novo Selo",
    "qs:photos_9r":0,
    "qs:photos_sr":0,
    "qs:pop_sr":"2",
    "wd:wordcount":872,
    "wof:name":"Novo Selo",
    "wof:placetype":"locality",
    "wof:population":552
},
  "geometry": {"coordinates":[21.15889,41.96389],"type":"Point"}
}