{
  "type": "Feature",
  "properties": {
    "gn:country":"MK",
    "gn:fcode":"PPL",
    "gn:pop":144,
    "iso:country":"MK",
    "name:mkd_x_preferred":[
        "\u0420\u0430\u043c\u043d\u0438 \u0413\u0430\u0431\u0435\u0440"
    ],
    "name:unk_x_variant":[
        "Ramni Gader"
    ],
    "qs:name":"Ramni Gaber",
    "qs:photos_9r":0,
    "qs:photos_sr":0,
    "qs:pop_sr":"1",
    "wd:wordcount":132,
    "wof:name":"Ramni Gaber",
    "wof:placetype":"locality",
    "wof:population":144
},
  "geometry": {"coordinates":[21.51944,41.86389],"type":"Point"}
}