{
  "type": "Feature",
  "properties": {
    "gn:admin1_code":"97",
    "gn:asciiname":"Bujek",
    "gn:country_code":"MK",
    "gn:dem":912,
    "gn:feature_class":"P",
    "gn:feature_code":"PPL",
    "gn:name":"Bujek",
    "gn:population":0,
    "gn:timezone":"Europe/Belgrade",
    "iso:country":"MK",
    "name:mkd_x_preferred":[
        "Bujek"
    ],
    "name:mkd_x_variant":[
        "\u0411\u0443\u0458\u0435\u043a"
    ],
    "wof:name":"Bujek",
    "wof:placetype":"locality"
},
  "geometry": {"coordinates":[21.9546,42.31571],"type":"Point"}
}