{
  "type": "Feature",
  "properties": {
    "gn:admin1_code":"F5",
    "gn:asciiname":"Slatino",
    "gn:country_code":"MK",
    "gn:dem":850,
    "gn:feature_class":"P",
    "gn:feature_code":"PPL",
    "gn:name":"Slatino",
    "gn:population":0,
    "gn:timezone":"Europe/Skopje",
    "iso:country":"MK",
    "name:mkd_x_preferred":[
        "\u0421\u043b\u0430\u0442\u0438\u043d\u043e"
    ],
    "wof:name":"Slatino",
    "wof:placetype":"locality"
},
  "geometry": {"coordinates":[20.86639,41.34833],"type":"Point"}
}