{
  "type": "Feature",
  "properties": {
    "gn:admin1_code":"86",
    "gn:asciiname":"Ezerani",
    "gn:country_code":"MK",
    "gn:dem":858,
    "gn:feature_class":"P",
    "gn:feature_code":"PPL",
    "gn:name":"Ezerani",
    "gn:population":0,
    "gn:timezone":"Europe/Skopje",
    "iso:country":"MK",
    "name:mkd_x_preferred":[
        "\u0415\u0437\u0435\u0440\u0430\u043d\u0438"
    ],
    "name:und_x_variant":[
        "Ezereni",
        "Jezerane",
        "Ezerani"
    ],
    "wof:name":"Ezerani",
    "wof:placetype":"locality"
},
  "geometry": {"coordinates":[21.02198,41.02819],"type":"Point"}
}