{
  "type": "Feature",
  "properties": {
    "gn:admin1_code":"59",
    "gn:admin2_code":"Kosovo",
    "gn:asciiname":"Salaska Maala",
    "gn:country_code":"MK",
    "gn:dem":884,
    "gn:feature_class":"P",
    "gn:feature_code":"PPL",
    "gn:name":"Salaska Maala",
    "gn:population":0,
    "gn:timezone":"Europe/Skopje",
    "iso:country":"MK",
    "name:mkd_x_preferred":[
        "\u0421\u0430\u043b\u0430\u0441\u043a\u0430 \u041c\u0430\u0430\u043b\u0430"
    ],
    "name:srp_x_preferred":[
        "Salaska Maala"
    ],
    "name:und_x_variant":[
        "Salaska Mahala"
    ],
    "wof:name":"Salaska Maala",
    "wof:placetype":"locality"
},
  "geometry": {"coordinates":[21.56235,42.23416],"type":"Point"}
}