{
  "type": "Feature",
  "properties": {
    "gn:admin1_code":"97",
    "gn:asciiname":"Strezovce",
    "gn:country_code":"MK",
    "gn:dem":348,
    "gn:feature_class":"P",
    "gn:feature_code":"PPLL",
    "gn:name":"Strezovce",
    "gn:population":0,
    "gn:timezone":"Europe/Skopje",
    "iso:country":"MK",
    "name:bul_x_preferred":[
        "\u0421\u0442\u0440\u0435\u0437\u043e\u0432\u0446\u0435"
    ],
    "name:ceb_x_preferred":[
        "Strezovce"
    ],
    "name:deu_x_preferred":[
        "Strezovce"
    ],
    "name:fra_x_preferred":[
        "Strezovce"
    ],
    "name:mkd_x_preferred":[
        "Strezovce"
    ],
    "name:mkd_x_variant":[
        "\u0421\u0442\u0440\u0435\u0437\u043e\u0432\u0446\u0435"
    ],
    "name:msa_x_preferred":[
        "Strezovce"
    ],
    "name:por_x_preferred":[
        "Strezovce"
    ],
    "name:slv_x_preferred":[
        "Strezovce"
    ],
    "name:sqi_x_preferred":[
        "Strezoci"
    ],
    "name:srp_x_preferred":[
        "\u0421\u0442\u0440\u0435\u0437\u043e\u0432\u0446\u0435"
    ],
    "wof:name":"Strezovce",
    "wof:placetype":"locality"
},
  "geometry": {"coordinates":[21.88917,42.14667],"type":"Point"}
}