{
  "type": "Feature",
  "properties": {
    "gn:country":"MK",
    "gn:fcode":"PPL",
    "gn:pop":4798,
    "iso:country":"MK",
    "name:ara_x_preferred":[
        "\u0628\u064a\u0633\u062a\u0631\u064a\u0643\u0627\u060c \u0628\u064a\u062a\u0648\u0644\u0627"
    ],
    "name:ara_x_variant":[
        "\u0628\u064a\u0633\u062a\u0631\u064a\u0643\u0627"
    ],
    "name:bul_x_preferred":[
        "\u0411\u0438\u0441\u0442\u0440\u0438\u0446\u0430"
    ],
    "name:ceb_x_preferred":[
        "Bistrica"
    ],
    "name:eng_x_preferred":[
        "Bistrica"
    ],
    "name:fra_x_preferred":[
        "Bistritsa"
    ],
    "name:hun_x_preferred":[
        "Bisztrica"
    ],
    "name:mkd_x_preferred":[
        "\u0411\u0438\u0441\u0442\u0440\u0438\u0446\u0430"
    ],
    "name:nan_x_preferred":[
        "Bistritsa"
    ],
    "name:nld_x_preferred":[
        "Bistrica"
    ],
    "name:pol_x_preferred":[
        "Bistrica"
    ],
    "name:sqi_x_preferred":[
        "Bistrica"
    ],
    "name:srp_x_preferred":[
        "\u0411\u0438\u0441\u0442\u0440\u0438\u0446\u0430"
    ],
    "name:swe_x_preferred":[
        "Bistrica"
    ],
    "name:unk_x_variant":[
        "Feistritz"
    ],
    "name:zho_x_preferred":[
        "\u67e5\u4ec0\u5361\u533a"
    ],
    "qs:name":"\u0411\u0438\u0441\u0442\u0440\u0438\u0446\u0430",
    "qs:photos_9r":0,
    "qs:photos_sr":0,
    "qs:pop_sr":"4",
    "wof:name":"\u0411\u0438\u0441\u0442\u0440\u0438\u0446\u0430",
    "wof:placetype":"locality",
    "wof:population":4798
},
  "geometry": {"coordinates":[21.36667,40.98333],"type":"Point"}
}