{
  "type": "Feature",
  "properties": {
    "gn:country":"MK",
    "gn:fcode":"PPL",
    "gn:pop":507,
    "iso:country":"MK",
    "name:alb_x_preferred":[
        "Arvati"
    ],
    "name:bul_x_preferred":[
        "\u042a\u0440\u0432\u0430\u0442\u0438"
    ],
    "name:dut_x_preferred":[
        "Arvati"
    ],
    "name:eng_x_preferred":[
        "Arvati"
    ],
    "name:fre_x_preferred":[
        "Arvati"
    ],
    "name:hrv_x_preferred":[
        "Hrvati"
    ],
    "name:mac_x_preferred":[
        "\u0410\u0440\u0432\u0430\u0442\u0438"
    ],
    "name:mkd_x_preferred":[
        "Arvati"
    ],
    "name:mkd_x_variant":[
        "\u0410\u0440\u0432\u0430\u0442\u0438"
    ],
    "name:por_x_preferred":[
        "Arvati"
    ],
    "name:srp_x_preferred":[
        "\u0425\u0440\u0432\u0430\u0442\u0438"
    ],
    "name:swe_x_preferred":[
        "Arvati"
    ],
    "qs:name":"Arvati",
    "qs:photos_9r":0,
    "qs:photos_sr":0,
    "qs:pop_sr":"2",
    "wd:elevation":1005.0,
    "wd:wordcount":304,
    "wof:name":"Arvati",
    "wof:placetype":"locality",
    "wof:population":507
},
  "geometry": {"coordinates":[21.1152,40.94443],"type":"Point"}
}