{
  "type": "Feature",
  "properties": {
    "gn:country":"MK",
    "gn:fcode":"PPL",
    "gn:population":2573,
    "iso:country":"MK",
    "name:bel_x_preferred":[
        "\u041c\u0456\u0440\u0430\u045e\u0446\u044b"
    ],
    "name:bul_x_preferred":[
        "\u041c\u0438\u0440\u0430\u0432\u0446\u0438"
    ],
    "name:ceb_x_preferred":[
        "Miravci"
    ],
    "name:deu_x_preferred":[
        "Miravci"
    ],
    "name:eng_x_preferred":[
        "Miravci"
    ],
    "name:fra_x_preferred":[
        "Miravtsi"
    ],
    "name:hun_x_preferred":[
        "Miravci"
    ],
    "name:lit_x_preferred":[
        "Miravcai"
    ],
    "name:mkd_x_preferred":[
        "\u041c\u0438\u0440\u0430\u0432\u0446\u0438"
    ],
    "name:nan_x_preferred":[
        "Miravtsi"
    ],
    "name:nld_x_preferred":[
        "Miravci"
    ],
    "name:rus_x_preferred":[
        "\u041c\u0438\u0440\u0430\u0432\u0446\u044b"
    ],
    "name:sqi_x_preferred":[
        "Miraci"
    ],
    "name:srp_x_preferred":[
        "\u041c\u0438\u0440\u0430\u0432\u0446\u0438"
    ],
    "name:swe_x_preferred":[
        "Miravci"
    ],
    "name:ukr_x_preferred":[
        "\u041c\u0456\u0440\u0430\u0432\u0446\u0456"
    ],
    "name:und_x_variant":[
        "Mirovca"
    ],
    "qs:name":"Miravci",
    "qs:name_adm0":"Macedonia",
    "qs:name_adm1":"Gevgelija",
    "qs:photos":8,
    "qs:photos_1k":2,
    "qs:photos_9k":1,
    "qs:photos_9r":1,
    "qs:photos_all":8,
    "qs:photos_sr":1,
    "qs:placetype":"Town",
    "qs:pop_sr":"4",
    "wd:elevation":68.0,
    "wd:wordcount":621,
    "wof:name":"Miravci",
    "wof:placetype":"locality",
    "wof:population":2573
},
  "geometry": {"coordinates":[22.435,41.30778],"type":"Point"}
}