{
  "type": "Feature",
  "properties": {
    "gn:admin1_code":"04",
    "gn:asciiname":"Mitrasinci",
    "gn:country_code":"MK",
    "gn:dem":814,
    "gn:feature_class":"P",
    "gn:feature_code":"PPL",
    "gn:name":"Mitra\u0161inci",
    "gn:population":0,
    "gn:timezone":"Europe/Skopje",
    "iso:country":"MK",
    "name:bul_x_preferred":[
        "\u041c\u0438\u0442\u0440\u0430\u0448\u0438\u043d\u0446\u0438"
    ],
    "name:fra_x_preferred":[
        "Mitrachintsi"
    ],
    "name:hun_x_preferred":[
        "Mitrasinci"
    ],
    "name:mkd_x_preferred":[
        "\u041c\u0438\u0442\u0440\u0430\u0448\u0438\u043d\u0446\u0438"
    ],
    "name:por_x_preferred":[
        "Mitra\u0161inci"
    ],
    "name:rus_x_preferred":[
        "\u041c\u0438\u0442\u0440\u0430\u0448\u0438\u043d\u0446\u0438"
    ],
    "name:sqi_x_preferred":[
        "Mitrashinca"
    ],
    "name:srp_x_preferred":[
        "\u041c\u0438\u0442\u0440\u0430\u0448\u0438\u043d\u0446\u0438"
    ],
    "name:ukr_x_preferred":[
        "\u041c\u0438\u0442\u0440\u0430\u0448\u0438\u043d\u0446\u0456"
    ],
    "name:und_x_variant":[
        "Mitro\u0161inci",
        "Mitra\u0161inci"
    ],
    "wof:name":"Mitrasinci",
    "wof:placetype":"locality"
},
  "geometry": {"coordinates":[22.73978,41.77647],"type":"Point"}
}