{
  "type": "Feature",
  "properties": {
    "gn:admin1_code":"22",
    "gn:asciiname":"Karadzaska Maala",
    "gn:country_code":"MK",
    "gn:dem":771,
    "gn:feature_class":"P",
    "gn:feature_code":"PPL",
    "gn:name":"Karad\u017easka Maala",
    "gn:population":0,
    "gn:timezone":"Europe/Skopje",
    "iso:country":"MK",
    "name:mkd_x_preferred":[
        "Karad\u017easka Maala"
    ],
    "name:mkd_x_variant":[
        "\u041a\u0430\u0440\u0430\u045f\u0430\u0441\u043a\u0430 \u041c\u0430\u0430\u043b\u0430"
    ],
    "wof:name":"Karadzaska Maala",
    "wof:placetype":"locality"
},
  "geometry": {"coordinates":[22.67843,41.95879],"type":"Point"}
}