{
  "type": "Feature",
  "properties": {
    "gn:country":"MK",
    "gn:fcode":"PPL",
    "gn:pop":2095,
    "iso:country":"MK",
    "name:alb_x_preferred":[
        "Vaksinca"
    ],
    "name:bul_x_preferred":[
        "\u0412\u0430\u043a\u0441\u0438\u043d\u0446\u0435"
    ],
    "name:dut_x_preferred":[
        "Vaksince"
    ],
    "name:eng_x_preferred":[
        "Vaksince"
    ],
    "name:fre_x_preferred":[
        "Vaksints\u00e9"
    ],
    "name:ger_x_preferred":[
        "Vaksince"
    ],
    "name:mac_x_preferred":[
        "\u0412\u0430\u043a\u0441\u0438\u043d\u0446\u0435"
    ],
    "name:mkd_x_preferred":[
        "\u0412\u0430\u043a\u0441\u0438\u043d\u0446\u0435"
    ],
    "name:srp_x_preferred":[
        "\u0412\u0430\u043a\u0441\u0438\u043d\u0446\u0435"
    ],
    "name:swe_x_preferred":[
        "Vaksince"
    ],
    "name:ukr_x_preferred":[
        "\u0412\u0430\u043a\u0441\u0438\u043d\u0446\u0435"
    ],
    "name:unk_x_variant":[
        "Vaksinc"
    ],
    "qs:name":"\u0412\u0430\u043a\u0441\u0438\u043d\u0446\u0435",
    "qs:photos_9r":0,
    "qs:photos_sr":0,
    "qs:pop_sr":"4",
    "wd:wordcount":237,
    "wof:name":"\u0412\u0430\u043a\u0441\u0438\u043d\u0446\u0435",
    "wof:placetype":"locality",
    "wof:population":2095
},
  "geometry": {"coordinates":[21.66306,42.20611],"type":"Point"}
}