{
  "type": "Feature",
  "properties": {
    "gn:admin1_code":"D6",
    "gn:asciiname":"Bohula",
    "gn:country_code":"MK",
    "gn:dem":638,
    "gn:feature_class":"P",
    "gn:feature_code":"PPL",
    "gn:name":"Bohula",
    "gn:population":0,
    "gn:timezone":"Europe/Skopje",
    "iso:country":"MK",
    "name:mkd_x_preferred":[
        "\u0411\u043e\u0445\u0443\u043b\u0430"
    ],
    "name:und_x_variant":[
        "Boula",
        "Bohula"
    ],
    "wof:name":"Bohula",
    "wof:placetype":"locality"
},
  "geometry": {"coordinates":[22.1626,41.28744],"type":"Point"}
}