{
  "type": "Feature",
  "properties": {
    "gn:country":"MK",
    "gn:fcode":"PPL",
    "gn:population":15,
    "iso:country":"MK",
    "name:bul_x_preferred":[
        "\u0422\u043e\u043f\u043b\u0438\u0446\u0430"
    ],
    "name:eng_x_preferred":[
        "Toplica"
    ],
    "name:fra_x_preferred":[
        "Toplitsa"
    ],
    "name:mkd_x_preferred":[
        "Toplica"
    ],
    "name:mkd_x_variant":[
        "\u0422\u043e\u043f\u043b\u0438\u0446\u0430"
    ],
    "name:nan_x_preferred":[
        "Toplitsa"
    ],
    "name:sqi_x_preferred":[
        "Toplica"
    ],
    "name:srp_x_preferred":[
        "\u0422\u043e\u043f\u043b\u0438\u0446\u0430"
    ],
    "qs:name":"Toplica",
    "qs:photos_9r":0,
    "qs:photos_sr":0,
    "qs:pop_sr":"1",
    "wd:wordcount":46,
    "wof:name":"Toplica",
    "wof:placetype":"locality",
    "wof:population":15
},
  "geometry": {"coordinates":[21.74194,41.40056],"type":"Point"}
}