{
  "type": "Feature",
  "properties": {
    "gn:admin1_code":"59",
    "gn:asciiname":"Trucska Maala",
    "gn:country_code":"MK",
    "gn:dem":622,
    "gn:feature_class":"P",
    "gn:feature_code":"PPL",
    "gn:name":"Tru\u010dska Maala",
    "gn:population":0,
    "gn:timezone":"Europe/Skopje",
    "iso:country":"MK",
    "name:mkd_x_preferred":[
        "Tru\u010dska Maala"
    ],
    "name:mkd_x_variant":[
        "\u0422\u0440\u0443\u0447\u0441\u043a\u0430 \u041c\u0430\u0430\u043b\u0430"
    ],
    "name:srp_x_preferred":[
        "Tru\u010dska Mahala"
    ],
    "wof:name":"Trucska Maala",
    "wof:placetype":"locality"
},
  "geometry": {"coordinates":[21.61281,42.21718],"type":"Point"}
}