{
  "type": "Feature",
  "properties": {
    "gn:admin1_code":"52",
    "gn:asciiname":"Gurendapska Maala",
    "gn:country_code":"MK",
    "gn:dem":966,
    "gn:feature_class":"P",
    "gn:feature_code":"PPL",
    "gn:name":"\u01f4urendapska Maala",
    "gn:population":0,
    "gn:timezone":"Europe/Skopje",
    "iso:country":"MK",
    "name:mkd_x_preferred":[
        "\u01f4urendapska Maala"
    ],
    "name:mkd_x_variant":[
        "\u0403\u0443\u0440\u0435\u043d\u0434\u0430\u043f\u0441\u043a\u0430 \u041c\u0430\u0430\u043b\u0430"
    ],
    "wof:name":"Gurendapska Maala",
    "wof:placetype":"locality"
},
  "geometry": {"coordinates":[22.38701,42.21569],"type":"Point"}
}