{
  "type": "Feature",
  "properties": {
    "gn:country":"MK",
    "gn:fcode":"PPL",
    "gn:pop":225,
    "iso:country":"MK",
    "name:mkd_x_preferred":[
        "\u0421\u0442\u0440\u0430\u0445\u043e\u0458\u0430\u0434\u0438\u0446\u0430"
    ],
    "name:unk_x_variant":[
        "Strahodacica"
    ],
    "qs:name":"Strahojadica",
    "qs:photos_9r":0,
    "qs:photos_sr":0,
    "qs:pop_sr":"2",
    "wof:name":"Strahojadica",
    "wof:placetype":"locality",
    "wof:population":225
},
  "geometry": {"coordinates":[21.60639,41.86],"type":"Point"}
}