{
  "type": "Feature",
  "properties": {
    "gn:country":"MK",
    "gn:fcode":"PPLA",
    "gn:pop":3798,
    "iso:country":"MK",
    "name:ara_x_preferred":[
        "\u0641\u0627\u0644\u0627\u0646\u062f\u0648\u0641\u0648"
    ],
    "name:bul_x_preferred":[
        "\u0412\u0430\u043b\u0430\u043d\u0434\u043e\u0432\u043e"
    ],
    "name:chu_x_preferred":[
        "\u0412\u0430\u043b\u0430\u043d\u0434\u043e\u0432\u043e"
    ],
    "name:eng_x_preferred":[
        "Valandovo"
    ],
    "name:fas_x_preferred":[
        "\u0641\u0627\u0644\u0627\u0646\u062f\u0648\u0641\u0648"
    ],
    "name:kat_x_preferred":[
        "\u10d5\u10d0\u10da\u10d0\u10dc\u10d3\u10dd\u10d5\u10dd"
    ],
    "name:kaz_x_preferred":[
        "\u0412\u0430\u043b\u0430\u043d\u0434\u043e\u0432\u043e"
    ],
    "name:kor_x_preferred":[
        "\ubc1c\ub780\ub3c4\ubcf4"
    ],
    "name:lit_x_preferred":[
        "Valandovas"
    ],
    "name:mkd_x_preferred":[
        "\u0412\u0430\u043b\u0430\u043d\u0434\u043e\u0432\u043e"
    ],
    "name:nld_x_preferred":[
        "Valandovo"
    ],
    "name:pol_x_preferred":[
        "Wa\u0142andowo"
    ],
    "name:rus_x_preferred":[
        "\u0412\u0430\u043b\u0430\u043d\u0434\u043e\u0432\u043e"
    ],
    "name:sqi_x_preferred":[
        "Vallandova"
    ],
    "name:srp_x_preferred":[
        "\u0412\u0430\u043b\u0430\u043d\u0434\u043e\u0432\u043e"
    ],
    "name:swe_x_preferred":[
        "Valandovo"
    ],
    "name:ukr_x_preferred":[
        "\u0412\u0430\u043b\u0430\u043d\u0434\u043e\u0432\u043e"
    ],
    "name:unk_x_variant":[
        "Valandova"
    ],
    "name:zho_x_preferred":[
        "\u74e6\u862d\u591a\u6c83"
    ],
    "qs:name":"Valandovo",
    "qs:name_adm0":"Macedonia",
    "qs:name_adm1":"Valandovo",
    "qs:photos_9k":1,
    "qs:photos_9r":1,
    "qs:photos_all":2,
    "qs:photos_sr":0,
    "qs:placetype":"Town",
    "qs:pop_sr":"4",
    "wd:wordcount":865,
    "wof:name":"Valandovo",
    "wof:placetype":"locality",
    "wof:population":3798
},
  "geometry": {"coordinates":[22.56111,41.31694],"type":"Point"}
}