{
  "type": "Feature",
  "properties": {
    "gn:admin1_code":"E7",
    "gn:asciiname":"Bansko",
    "gn:country_code":"MK",
    "gn:dem":280,
    "gn:feature_class":"P",
    "gn:feature_code":"PPL",
    "gn:name":"Bansko",
    "gn:population":0,
    "gn:timezone":"Europe/Skopje",
    "iso:country":"MK",
    "name:mkd_x_preferred":[
        "\u0411\u0430\u043d\u0441\u043a\u043e"
    ],
    "name:und_x_variant":[
        "Banjsko",
        "Bansko"
    ],
    "wof:name":"Bansko",
    "wof:placetype":"locality"
},
  "geometry": {"coordinates":[22.74361,41.38389],"type":"Point"}
}