{
  "type": "Feature",
  "properties": {
    "gn:admin1_code":"46",
    "gn:asciiname":"Ramno Brdo",
    "gn:country_code":"MK",
    "gn:dem":1066,
    "gn:feature_class":"P",
    "gn:feature_code":"PPL",
    "gn:name":"Ramno Brdo",
    "gn:population":0,
    "gn:timezone":"Europe/Skopje",
    "iso:country":"MK",
    "name:mkd_x_preferred":[
        "Ramno Brdo"
    ],
    "name:mkd_x_variant":[
        "\u0420\u0430\u043c\u043d\u043e \u0411\u0440\u0434\u043e"
    ],
    "wof:name":"Ramno Brdo",
    "wof:placetype":"locality"
},
  "geometry": {"coordinates":[22.40028,42.05306],"type":"Point"}
}