{
  "type": "Feature",
  "properties": {
    "gn:country":"MK",
    "gn:fcode":"PPL",
    "gn:pop":87,
    "iso:country":"MK",
    "name:mkd_x_preferred":[
        "Modri\u0161te"
    ],
    "name:mkd_x_variant":[
        "\u041c\u043e\u0434\u0440\u0438\u0448\u0442\u0435"
    ],
    "qs:name":"Modri\u0161te",
    "qs:photos_9r":0,
    "qs:photos_sr":0,
    "qs:pop_sr":"1",
    "wd:wordcount":302,
    "wof:name":"Modri\u0161te",
    "wof:placetype":"locality",
    "wof:population":87
},
  "geometry": {"coordinates":[21.24361,41.64],"type":"Point"}
}