{
  "type": "Feature",
  "properties": {
    "gn:admin1_code":"52",
    "gn:asciiname":"Cukovci",
    "gn:country_code":"MK",
    "gn:dem":1023,
    "gn:feature_class":"P",
    "gn:feature_code":"PPL",
    "gn:name":"\u010cukovci",
    "gn:population":0,
    "gn:timezone":"Europe/Skopje",
    "iso:country":"MK",
    "name:mkd_x_preferred":[
        "\u010cukovci"
    ],
    "name:mkd_x_variant":[
        "\u0427\u0443\u043a\u043e\u0432\u0446\u0438"
    ],
    "wof:name":"Cukovci",
    "wof:placetype":"locality"
},
  "geometry": {"coordinates":[22.25091,42.24937],"type":"Point"}
}