{
  "type": "Feature",
  "properties": {
    "gn:admin1_code":"11",
    "gn:asciiname":"Saraj",
    "gn:country_code":"MK",
    "gn:dem":230,
    "gn:feature_class":"P",
    "gn:feature_code":"PPL",
    "gn:name":"Saraj",
    "gn:population":0,
    "gn:timezone":"Europe/Skopje",
    "iso:country":"MK",
    "name:mkd_x_preferred":[
        "Saraj"
    ],
    "name:mkd_x_variant":[
        "\u0421\u0430\u0440\u0430\u0458"
    ],
    "wof:name":"Saraj",
    "wof:placetype":"locality"
},
  "geometry": {"coordinates":[22.70303,41.47569],"type":"Point"}
}