{
  "type": "Feature",
  "properties": {
    "gn:admin1_code":"11",
    "gn:asciiname":"Saraj",
    "gn:country_code":"MK",
    "gn:dem":230,
    "gn:feature_class":"P",
    "gn:feature_code":"PPL",
    "gn:name":"Saraj",
    "gn:population":0,
    "gn:timezone":"Europe/Skopje",
    "iso:country":"MK",
    "name:ara_x_preferred":[
        "\u0633\u0631\u0627\u062c"
    ],
    "name:ben_x_preferred":[
        "\u09b8\u09b0\u099c"
    ],
    "name:heb_x_preferred":[
        "\u05e1\u05d0\u05e8\u05d0\u05d2'"
    ],
    "name:hin_x_preferred":[
        "\u0938\u0930\u091c"
    ],
    "name:hun_x_preferred":[
        "Saraj"
    ],
    "name:jpn_x_preferred":[
        "\u30b5\u30e9\u30e4"
    ],
    "name:mkd_x_preferred":[
        "Saraj"
    ],
    "name:mkd_x_variant":[
        "\u0421\u0430\u0440\u0430\u0458"
    ],
    "name:vie_x_preferred":[
        "Saraj"
    ],
    "wof:name":"Saraj",
    "wof:placetype":"locality"
},
  "geometry": {"coordinates":[22.70303,41.47569],"type":"Point"}
}