{
  "type": "Feature",
  "properties": {
    "gn:admin1_code":"51",
    "gn:asciiname":"Civlevci",
    "gn:country_code":"MK",
    "gn:dem":620,
    "gn:feature_class":"P",
    "gn:feature_code":"PPL",
    "gn:name":"\u010civlevci",
    "gn:population":0,
    "gn:timezone":"Europe/Skopje",
    "iso:country":"MK",
    "name:mkd_x_preferred":[
        "\u010civlevci"
    ],
    "name:mkd_x_variant":[
        "\u0427\u0438\u0432\u043b\u0435\u0432\u0446\u0438"
    ],
    "wof:name":"Civlevci",
    "wof:placetype":"locality"
},
  "geometry": {"coordinates":[22.03511,42.15893],"type":"Point"}
}