{
  "type": "Feature",
  "properties": {
    "gn:country":"MK",
    "gn:fcode":"PPL",
    "gn:pop":167,
    "iso:country":"MK",
    "name:bul_x_preferred":[
        "\u0414\u0435\u043c\u0438\u0440 \u0425\u0438\u0441\u0430\u0440"
    ],
    "name:ceb_x_preferred":[
        "Demir Hisar"
    ],
    "name:deu_x_preferred":[
        "Op\u0161tina Demir Hisar"
    ],
    "name:ell_x_preferred":[
        "\u0394\u03ae\u03bc\u03bf\u03c2 \u039d\u03c4\u03b5\u03bc\u03af\u03c1 \u03a7\u03b9\u03c3\u03ac\u03c1"
    ],
    "name:eng_x_preferred":[
        "Demir Hisar Municipality"
    ],
    "name:fas_x_preferred":[
        "\u062f\u0645\u06cc\u0631 \u0647\u0633\u0627\u0631"
    ],
    "name:fra_x_preferred":[
        "Demir Hisar"
    ],
    "name:hrv_x_preferred":[
        "Op\u0107ina Demir Hisar"
    ],
    "name:hun_x_preferred":[
        "Demir Hiszar"
    ],
    "name:ind_x_preferred":[
        "Munisipalitas Demir Hisar"
    ],
    "name:ita_x_preferred":[
        "Demir Hisar"
    ],
    "name:jpn_x_preferred":[
        "\u30c7\u30df\u30eb\u30fb\u30d2\u30b5\u30eb"
    ],
    "name:kat_x_preferred":[
        "\u10d3\u10d4\u10db\u10d8\u10e0-\u10f0\u10d8\u10e1\u10d0\u10e0\u10d8\u10e1 \u10d7\u10d4\u10db\u10d8"
    ],
    "name:kor_x_preferred":[
        "\ub370\ubbf8\ub974\ud788\uc0ac\ub974 \uc2dc"
    ],
    "name:mkd_x_preferred":[
        "Malo Ilino"
    ],
    "name:mkd_x_variant":[
        "\u041c\u0430\u043b\u043e \u0418\u043b\u0438\u043d\u043e",
        "\u041e\u043f\u0448\u0442\u0438\u043d\u0430 \u0414\u0435\u043c\u0438\u0440 \u0425\u0438\u0441\u0430\u0440"
    ],
    "name:nan_x_preferred":[
        "Demir Hisar Chh\u012b"
    ],
    "name:nld_x_preferred":[
        "Demir Hisar"
    ],
    "name:pol_x_preferred":[
        "Gmina Demir Hisar"
    ],
    "name:rus_x_preferred":[
        "\u0414\u0435\u043c\u0438\u0440-\u0425\u0438\u0441\u0430\u0440"
    ],
    "name:sqi_x_preferred":[
        "Komuna e Demir Hisarit"
    ],
    "name:srp_x_preferred":[
        "\u041e\u043f\u0448\u0442\u0438\u043d\u0430 \u0414\u0435\u043c\u0438\u0440 \u0425\u0438\u0441\u0430\u0440"
    ],
    "name:swe_x_preferred":[
        "Demir Hisar"
    ],
    "name:tgk_x_preferred":[
        "\u0412\u0438\u043b\u043e\u044f\u0442\u0438 \u0414\u0435\u043c\u0438\u0440 \u0425\u0438\u0441\u0430\u0440"
    ],
    "name:tur_x_preferred":[
        "Demir Hisar Belediyesi"
    ],
    "name:ukr_x_preferred":[
        "\u0414\u0435\u043c\u0438\u0440-\u0425\u0438\u0441\u0430\u0440"
    ],
    "name:urd_x_preferred":[
        "\u062f\u06cc\u0645\u06cc\u0631 \u062d\u0633\u0627\u0631 \u0628\u0644\u062f\u06cc\u06c1"
    ],
    "name:zho_x_preferred":[
        "\u5fb7\u7c73\u5c14\u5e0c\u8428\u5c14\u533a"
    ],
    "qs:name":"Malo Ilino",
    "qs:photos_9r":0,
    "qs:photos_sr":0,
    "qs:pop_sr":"1",
    "wd:wordcount":194,
    "wof:name":"Malo Ilino",
    "wof:placetype":"locality",
    "wof:population":167
},
  "geometry": {"coordinates":[21.03694,41.2975],"type":"Point"}
}