{
  "type": "Feature",
  "properties": {
    "gn:country":"MK",
    "gn:fcode":"PPL",
    "gn:pop":167,
    "iso:country":"MK",
    "name:mkd_x_preferred":[
        "Malo Ilino"
    ],
    "name:mkd_x_variant":[
        "\u041c\u0430\u043b\u043e \u0418\u043b\u0438\u043d\u043e"
    ],
    "qs:name":"Malo Ilino",
    "qs:photos_9r":0,
    "qs:photos_sr":0,
    "qs:pop_sr":"1",
    "wd:wordcount":194,
    "wof:name":"Malo Ilino",
    "wof:placetype":"locality",
    "wof:population":167
},
  "geometry": {"coordinates":[21.03694,41.2975],"type":"Point"}
}