{
  "type": "Feature",
  "properties": {
    "gn:admin1_code":"62",
    "gn:asciiname":"Paunkovska Maala",
    "gn:country_code":"MK",
    "gn:dem":732,
    "gn:feature_class":"P",
    "gn:feature_code":"PPL",
    "gn:name":"Paunkovska Maala",
    "gn:population":0,
    "gn:timezone":"Europe/Skopje",
    "iso:country":"MK",
    "name:mkd_x_preferred":[
        "Paunkovska Maala"
    ],
    "name:mkd_x_variant":[
        "\u041f\u0430\u0443\u043d\u043a\u043e\u0432\u0441\u043a\u0430 \u041c\u0430\u0430\u043b\u0430"
    ],
    "wof:name":"Paunkovska Maala",
    "wof:placetype":"locality"
},
  "geometry": {"coordinates":[22.60322,42.04498],"type":"Point"}
}