{
  "type": "Feature",
  "properties": {
    "gn:admin1_code":"84",
    "gn:asciiname":"Kalauzlija",
    "gn:country_code":"MK",
    "gn:dem":653,
    "gn:feature_class":"P",
    "gn:feature_code":"PPL",
    "gn:name":"Kalauzlija",
    "gn:population":0,
    "gn:timezone":"Europe/Skopje",
    "iso:country":"MK",
    "name:mkd_x_preferred":[
        "\u041a\u0430\u043b\u0430\u0443\u0437\u043b\u0438\u0458\u0430"
    ],
    "name:und_x_variant":[
        "Kalauzli",
        "Kalauzlija"
    ],
    "wof:name":"Kalauzlija",
    "wof:placetype":"locality"
},
  "geometry": {"coordinates":[22.49361,41.67],"type":"Point"}
}