{
  "type": "Feature",
  "properties": {
    "gn:admin1_code":"D8",
    "gn:asciiname":"Lag",
    "gn:country_code":"MK",
    "gn:dem":493,
    "gn:feature_class":"P",
    "gn:feature_code":"PPL",
    "gn:name":"Lag",
    "gn:population":0,
    "gn:timezone":"Europe/Skopje",
    "iso:country":"MK",
    "name:mkd_x_preferred":[
        "Lag"
    ],
    "name:mkd_x_variant":[
        "\u041b\u0430\u0433"
    ],
    "wof:name":"Lag",
    "wof:placetype":"locality"
},
  "geometry": {"coordinates":[21.23142,41.63431],"type":"Point"}
}