{
  "type": "Feature",
  "properties": {
    "gn:admin1_code":"D8",
    "gn:asciiname":"Lag",
    "gn:country_code":"MK",
    "gn:dem":493,
    "gn:feature_class":"P",
    "gn:feature_code":"PPL",
    "gn:name":"Lag",
    "gn:population":0,
    "gn:timezone":"Europe/Skopje",
    "iso:country":"MK",
    "name:ara_x_preferred":[
        "\u0643\u0645\u0648\u0646\u064a\u0629"
    ],
    "name:deu_x_preferred":[
        "Lag"
    ],
    "name:fin_x_preferred":[
        "Viive"
    ],
    "name:fra_x_preferred":[
        "Latence"
    ],
    "name:heb_x_preferred":[
        "\u05dc\u05d0\u05d2"
    ],
    "name:ita_x_preferred":[
        "Lag"
    ],
    "name:mkd_x_preferred":[
        "Lag"
    ],
    "name:mkd_x_variant":[
        "\u041b\u0430\u0433"
    ],
    "name:nld_x_preferred":[
        "Lag"
    ],
    "name:pol_x_preferred":[
        "Op\u00f3\u017anienie"
    ],
    "name:por_x_preferred":[
        "Lag"
    ],
    "name:ron_x_preferred":[
        "Lag"
    ],
    "name:rus_x_preferred":[
        "\u041b\u0430\u0433"
    ],
    "name:spa_x_preferred":[
        "Retardo"
    ],
    "name:tha_x_preferred":[
        "\u0e41\u0e25\u0e47\u0e01"
    ],
    "name:ukr_x_preferred":[
        "\u041b\u0430\u0433"
    ],
    "name:zho_x_preferred":[
        "\u5ef6\u9072"
    ],
    "wof:name":"Lag",
    "wof:placetype":"locality"
},
  "geometry": {"coordinates":[21.23142,41.63431],"type":"Point"}
}