{
  "type": "Feature",
  "properties": {
    "gn:admin1_code":"00",
    "gn:asciiname":"Strachinci",
    "gn:cc2":"MK",
    "gn:country_code":"MK",
    "gn:dem":376,
    "gn:feature_class":"P",
    "gn:feature_code":"PPL",
    "gn:name":"\u0421\u0442\u0440\u0430\u0447\u0438\u043d\u0446\u0438",
    "gn:population":0,
    "gn:timezone":"Europe/Skopje",
    "iso:country":"MK",
    "name:und_x_variant":[
        "Stra\u010dince",
        "Stra\u010dinci"
    ],
    "wof:name":"Strachinci",
    "wof:placetype":"locality"
},
  "geometry": {"coordinates":[21.53222,42.04611],"type":"Point"}
}