{
  "type": "Feature",
  "properties": {
    "gn:admin1_code":"00",
    "gn:asciiname":"Grushino",
    "gn:cc2":"MK",
    "gn:country_code":"MK",
    "gn:dem":440,
    "gn:feature_class":"P",
    "gn:feature_code":"PPL",
    "gn:name":"\u0413\u0440\u0443\u0448\u0438\u043d\u043e",
    "gn:population":0,
    "gn:timezone":"Europe/Skopje",
    "iso:country":"MK",
    "name:und_x_variant":[
        "Gru\u0161ince"
    ],
    "wof:name":"Grushino",
    "wof:placetype":"locality"
},
  "geometry": {"coordinates":[21.62056,42.06083],"type":"Point"}
}