{
  "type": "Feature",
  "properties": {
    "gn:country":"MK",
    "gn:fcode":"PPLA",
    "gn:pop":34258,
    "iso:country":"MK",
    "name:bos_x_preferred":[
        "Ko\u010dani"
    ],
    "name:bul_x_preferred":[
        "\u041a\u043e\u0447\u0430\u043d\u0438"
    ],
    "name:deu_x_preferred":[
        "Ko\u010dani"
    ],
    "name:eng_x_preferred":[
        "Ko\u010dani"
    ],
    "name:hbs_x_preferred":[
        "Ko\u010dani"
    ],
    "name:hrv_x_preferred":[
        "Ko\u010dani"
    ],
    "name:mkd_x_preferred":[
        "\u041a\u043e\u0447\u0430\u043d\u0438"
    ],
    "name:nld_x_preferred":[
        "Ko\u010dani"
    ],
    "name:srp_x_preferred":[
        "\u041a\u043e\u0447\u0430\u043d\u0438"
    ],
    "name:swe_x_preferred":[
        "Kocani"
    ],
    "name:unk_x_variant":[
        "Ko\u010dane"
    ],
    "qs:name":"Ko\u010dani",
    "qs:name_adm0":"Macedonia",
    "qs:name_adm1":"Ko\u010dani",
    "qs:photos":88,
    "qs:photos_1k":18,
    "qs:photos_9k":1,
    "qs:photos_9r":3,
    "qs:photos_all":88,
    "qs:photos_sr":3,
    "qs:placetype":"Town",
    "qs:pop_sr":"7",
    "wd:wordcount":798,
    "wof:name":"Ko\u010dani",
    "wof:placetype":"locality",
    "wof:population":34258
},
  "geometry": {"coordinates":[22.41278,41.91639],"type":"Point"}
}