{
  "type": "Feature",
  "properties": {
    "gn:admin1_code":"52",
    "gn:asciiname":"Stanoevci",
    "gn:country_code":"MK",
    "gn:dem":1195,
    "gn:feature_class":"P",
    "gn:feature_code":"PPL",
    "gn:name":"Stanoevci",
    "gn:population":0,
    "gn:timezone":"Europe/Skopje",
    "iso:country":"MK",
    "name:mkd_x_preferred":[
        "Stanoevci"
    ],
    "name:mkd_x_variant":[
        "\u0421\u0442\u0430\u043d\u043e\u0435\u0432\u0446\u0438"
    ],
    "wof:name":"Stanoevci",
    "wof:placetype":"locality"
},
  "geometry": {"coordinates":[22.32092,42.16432],"type":"Point"}
}