{
  "type": "Feature",
  "properties": {
    "gn:admin1_code":"11",
    "gn:asciiname":"Radovo",
    "gn:country_code":"MK",
    "gn:dem":221,
    "gn:feature_class":"P",
    "gn:feature_code":"PPL",
    "gn:name":"Radovo",
    "gn:population":0,
    "gn:timezone":"Europe/Skopje",
    "iso:country":"MK",
    "name:bul_x_preferred":[
        "\u0420\u0430\u0434\u043e\u0432\u043e"
    ],
    "name:ceb_x_preferred":[
        "Radovo"
    ],
    "name:fra_x_preferred":[
        "Radovo"
    ],
    "name:hun_x_preferred":[
        "Radovo"
    ],
    "name:mkd_x_preferred":[
        "\u0420\u0430\u0434\u043e\u0432\u043e"
    ],
    "name:sqi_x_preferred":[
        "Radova"
    ],
    "name:srp_x_preferred":[
        "\u0420\u0430\u0434\u043e\u0432\u043e"
    ],
    "name:swe_x_preferred":[
        "Radovo"
    ],
    "wof:name":"Radovo",
    "wof:placetype":"locality"
},
  "geometry": {"coordinates":[22.76677,41.45106],"type":"Point"}
}