{
  "type": "Feature",
  "properties": {
    "gn:admin1_code":"62",
    "gn:asciiname":"Bukoravenci",
    "gn:country_code":"MK",
    "gn:dem":1054,
    "gn:feature_class":"P",
    "gn:feature_code":"PPL",
    "gn:name":"Bukoravenci",
    "gn:population":0,
    "gn:timezone":"Europe/Skopje",
    "iso:country":"MK",
    "name:mkd_x_preferred":[
        "Bukoravenci"
    ],
    "name:mkd_x_variant":[
        "\u0411\u0443\u043a\u043e\u0440\u0430\u0432\u0435\u043d\u0446\u0438"
    ],
    "wof:name":"Bukoravenci",
    "wof:placetype":"locality"
},
  "geometry": {"coordinates":[22.55228,42.09444000000001],"type":"Point"}
}