{
  "type": "Feature",
  "properties": {
    "gn:admin1_code":"97",
    "gn:asciiname":"Pelince",
    "gn:country_code":"MK",
    "gn:dem":380,
    "gn:feature_class":"P",
    "gn:feature_code":"PPL",
    "gn:name":"Pelince",
    "gn:population":0,
    "gn:timezone":"Europe/Skopje",
    "iso:country":"MK",
    "name:bul_x_preferred":[
        "\u041f\u0435\u043b\u0438\u043d\u0446\u0435"
    ],
    "name:ceb_x_preferred":[
        "Pelince"
    ],
    "name:fra_x_preferred":[
        "Pelints\u00e9"
    ],
    "name:mkd_x_preferred":[
        "\u041f\u0435\u043b\u0438\u043d\u0446\u0435"
    ],
    "name:sqi_x_preferred":[
        "Pelinca"
    ],
    "name:srp_x_preferred":[
        "\u041f\u0435\u043b\u0438\u043d\u0446\u0435"
    ],
    "name:swe_x_preferred":[
        "Pelince"
    ],
    "name:und_x_variant":[
        "Pelinci",
        "Pelince"
    ],
    "wof:name":"Pelince",
    "wof:placetype":"locality"
},
  "geometry": {"coordinates":[21.85611,42.2875],"type":"Point"}
}