{
  "type": "Feature",
  "properties": {
    "gn:country":"MK",
    "gn:fcode":"PPL",
    "gn:pop":198,
    "iso:country":"MK",
    "name:alb_x_preferred":[
        "Kostinci"
    ],
    "name:bul_x_preferred":[
        "\u041a\u043e\u0441\u0442\u0438\u043d\u0446\u0438"
    ],
    "name:dut_x_preferred":[
        "Kostinci"
    ],
    "name:eng_x_preferred":[
        "Kostinci"
    ],
    "name:fre_x_preferred":[
        "Kostintsi"
    ],
    "name:hun_x_preferred":[
        "Kosztinci"
    ],
    "name:mac_x_preferred":[
        "\u041a\u043e\u0441\u0442\u0438\u043d\u0446\u0438"
    ],
    "name:mkd_x_preferred":[
        "Kostinci"
    ],
    "name:mkd_x_variant":[
        "\u041a\u043e\u0441\u0442\u0438\u043d\u0446\u0438"
    ],
    "name:rus_x_preferred":[
        "\u041a\u043e\u0441\u0442\u0438\u043d\u0446\u0438"
    ],
    "name:srp_x_preferred":[
        "\u041a\u043e\u0441\u0442\u0438\u043d\u0446\u0438"
    ],
    "name:swe_x_preferred":[
        "Kostinci"
    ],
    "qs:name":"Kostinci",
    "qs:photos_9r":0,
    "qs:photos_sr":0,
    "qs:pop_sr":"1",
    "wd:elevation":618.0,
    "wd:wordcount":37,
    "wof:name":"Kostinci",
    "wof:placetype":"locality",
    "wof:population":198
},
  "geometry": {"coordinates":[21.40694,41.50167],"type":"Point"}
}