{
  "type": "Feature",
  "properties": {
    "gn:admin1_code":"98",
    "gn:asciiname":"Goracino",
    "gn:country_code":"MK",
    "gn:dem":500,
    "gn:feature_class":"P",
    "gn:feature_code":"PPL",
    "gn:name":"Gora\u010dino",
    "gn:population":0,
    "gn:timezone":"Europe/Skopje",
    "iso:country":"MK",
    "name:mkd_x_preferred":[
        "Gora\u010dino"
    ],
    "name:mkd_x_variant":[
        "\u0413\u043e\u0440\u0430\u0447\u0438\u043d\u043e"
    ],
    "wof:name":"Goracino",
    "wof:placetype":"locality"
},
  "geometry": {"coordinates":[22.2784,41.64152],"type":"Point"}
}