{
  "type": "Feature",
  "properties": {
    "gn:admin1_code":"59",
    "gn:asciiname":"Runica",
    "gn:country_code":"MK",
    "gn:dem":612,
    "gn:feature_class":"P",
    "gn:feature_code":"PPLL",
    "gn:name":"Runica",
    "gn:population":0,
    "gn:timezone":"Europe/Skopje",
    "iso:country":"MK",
    "name:bul_x_preferred":[
        "\u0420\u0443\u0433\u0438\u043d\u0446\u0435"
    ],
    "name:fra_x_preferred":[
        "Rounitsa"
    ],
    "name:hun_x_preferred":[
        "Runica"
    ],
    "name:mkd_x_preferred":[
        "Runica"
    ],
    "name:mkd_x_variant":[
        "\u0420\u0443\u043d\u0438\u0446\u0430"
    ],
    "name:sqi_x_preferred":[
        "Runica"
    ],
    "name:srp_x_preferred":[
        "Rugince"
    ],
    "name:srp_x_variant":[
        "\u0420\u0443\u043d\u0438\u0446\u0430"
    ],
    "wof:name":"Runica",
    "wof:placetype":"locality"
},
  "geometry": {"coordinates":[21.60604,42.21724],"type":"Point"}
}