{
  "type": "Feature",
  "properties": {
    "gn:admin1_code":"40",
    "gn:asciiname":"Odzalija",
    "gn:country_code":"MK",
    "gn:dem":656,
    "gn:feature_class":"P",
    "gn:feature_code":"PPL",
    "gn:name":"Od\u017ealija",
    "gn:population":0,
    "gn:timezone":"Europe/Skopje",
    "iso:country":"MK",
    "name:mkd_x_preferred":[
        "\u041e\u045f\u0430\u043b\u0438\u0458\u0430"
    ],
    "name:und_x_variant":[
        "Ord\u017eeli",
        "Od\u017eelija",
        "Od\u017ealija"
    ],
    "wof:name":"Odzalija",
    "wof:placetype":"locality"
},
  "geometry": {"coordinates":[22.32889,41.75472],"type":"Point"}
}