{
  "type": "Feature",
  "properties": {
    "gn:country":"MK",
    "gn:fcode":"PPL",
    "gn:population":0,
    "iso:country":"MK",
    "name:arz_x_preferred":[
        "\u0644\u064a\u0633\u0643\u0648\u064a\u0643"
    ],
    "name:bul_x_preferred":[
        "\u041b\u0435\u0441\u043a\u043e\u0435\u0446"
    ],
    "name:ceb_x_preferred":[
        "Leskoec"
    ],
    "name:deu_x_preferred":[
        "Leskoec"
    ],
    "name:ell_x_preferred":[
        "\u039b\u03ad\u03c3\u03ba\u03bf\u03b5\u03c4\u03c2"
    ],
    "name:eng_x_preferred":[
        "Leskoec"
    ],
    "name:fra_x_preferred":[
        "Leskoets"
    ],
    "name:hun_x_preferred":[
        "Leskoec"
    ],
    "name:kat_x_preferred":[
        "\u10da\u10d4\u10e1\u10d9\u10dd\u10d4\u10ea\u10d8"
    ],
    "name:mkd_x_preferred":[
        "\u041b\u0435\u0441\u043a\u043e\u0435\u0446"
    ],
    "name:nan_x_preferred":[
        "Leskoets"
    ],
    "name:nld_x_preferred":[
        "Leskoec"
    ],
    "name:nno_x_preferred":[
        "Leskoets"
    ],
    "name:pol_x_preferred":[
        "\u0141eskoec"
    ],
    "name:por_x_preferred":[
        "Leskoec"
    ],
    "name:sqi_x_preferred":[
        "Leskoveci"
    ],
    "name:srp_x_preferred":[
        "\u041b\u0435\u0441\u043a\u043e\u0435\u0446"
    ],
    "name:swe_x_preferred":[
        "Leskoec"
    ],
    "name:und_x_variant":[
        "Leskovec"
    ],
    "qs:name":"Leskoec",
    "qs:name_adm0":"Macedonia",
    "qs:name_adm1":"Resen",
    "qs:photos":67,
    "qs:photos_1k":14,
    "qs:photos_9k":1,
    "qs:photos_9r":2,
    "qs:photos_all":67,
    "qs:photos_sr":2,
    "qs:placetype":"Town",
    "qs:pop_sr":"0",
    "wd:elevation":741.0,
    "wd:wordcount":56,
    "wof:name":"Leskoec",
    "wof:placetype":"locality",
    "wof:population":0
},
  "geometry": {"coordinates":[20.87564,40.95716],"type":"Point"}
}