{
  "type": "Feature",
  "properties": {
    "gn:country":"MK",
    "gn:fcode":"PPL",
    "gn:pop":0,
    "iso:country":"MK",
    "name:mkd_x_preferred":[
        "\u041b\u0435\u0441\u043a\u043e\u0435\u0446"
    ],
    "name:unk_x_variant":[
        "Leskovec"
    ],
    "qs:name":"Leskoec",
    "qs:name_adm0":"Macedonia",
    "qs:name_adm1":"Resen",
    "qs:photos":67,
    "qs:photos_1k":14,
    "qs:photos_9k":1,
    "qs:photos_9r":2,
    "qs:photos_all":67,
    "qs:photos_sr":2,
    "qs:placetype":"Town",
    "qs:pop_sr":"0",
    "wd:elevation":741.0,
    "wd:wordcount":56,
    "wof:name":"Leskoec",
    "wof:placetype":"locality",
    "wof:population":0
},
  "geometry": {"coordinates":[20.87564,40.95716],"type":"Point"}
}