{
  "type": "Feature",
  "properties": {
    "gn:country":"MK",
    "gn:fcode":"PPL",
    "gn:population":336,
    "iso:country":"MK",
    "name:bul_x_preferred":[
        "\u0420\u0435\u0441\u0430\u0432\u0430"
    ],
    "name:ceb_x_preferred":[
        "Resava"
    ],
    "name:deu_x_preferred":[
        "Resava"
    ],
    "name:mkd_x_preferred":[
        "Resava"
    ],
    "name:mkd_x_variant":[
        "\u0420\u0435\u0441\u0430\u0432\u0430"
    ],
    "name:srp_x_preferred":[
        "\u0420\u0435\u0441\u0430\u0432\u0430"
    ],
    "name:swe_x_preferred":[
        "Resava"
    ],
    "qs:name":"Resava",
    "qs:photos_9r":0,
    "qs:photos_sr":0,
    "qs:pop_sr":"2",
    "wd:wordcount":70,
    "wof:name":"Resava",
    "wof:placetype":"locality",
    "wof:population":336
},
  "geometry": {"coordinates":[21.97806,41.38806],"type":"Point"}
}