{
  "type": "Feature",
  "properties": {
    "gn:admin1_code":"F6",
    "gn:asciiname":"Sula",
    "gn:country_code":"MK",
    "gn:dem":380,
    "gn:feature_class":"P",
    "gn:feature_code":"PPL",
    "gn:name":"\u0160ula",
    "gn:population":0,
    "gn:timezone":"Europe/Skopje",
    "iso:country":"MK",
    "name:bel_x_preferred":[
        "\u0421\u0443\u043b\u0430"
    ],
    "name:bul_x_preferred":[
        "\u0421\u0443\u043b\u0430"
    ],
    "name:cat_x_preferred":[
        "Sula"
    ],
    "name:ceb_x_preferred":[
        "Sula"
    ],
    "name:ces_x_preferred":[
        "Sula"
    ],
    "name:dan_x_preferred":[
        "Sula"
    ],
    "name:deu_x_preferred":[
        "Sula"
    ],
    "name:fin_x_preferred":[
        "Sula"
    ],
    "name:fra_x_preferred":[
        "Sula"
    ],
    "name:hun_x_preferred":[
        "Szula"
    ],
    "name:hye_x_preferred":[
        "\u054d\u0578\u0582\u056c\u0561"
    ],
    "name:isl_x_preferred":[
        "S\u00fala"
    ],
    "name:ita_x_preferred":[
        "Sula"
    ],
    "name:lav_x_preferred":[
        "Sula"
    ],
    "name:lim_x_preferred":[
        "Sula"
    ],
    "name:lit_x_preferred":[
        "Sula"
    ],
    "name:mkd_x_preferred":[
        "\u0160ula"
    ],
    "name:mkd_x_variant":[
        "\u0428\u0443\u043b\u0430"
    ],
    "name:nld_x_preferred":[
        "Sula"
    ],
    "name:nno_x_preferred":[
        "Sula"
    ],
    "name:nor_x_preferred":[
        "Sula"
    ],
    "name:pol_x_preferred":[
        "Sula"
    ],
    "name:por_x_preferred":[
        "Sula"
    ],
    "name:rus_x_preferred":[
        "\u0421\u0443\u043b\u0430"
    ],
    "name:slk_x_preferred":[
        "Sula"
    ],
    "name:swe_x_preferred":[
        "Sula"
    ],
    "name:ukr_x_preferred":[
        "\u0421\u0443\u043b\u0430"
    ],
    "wof:name":"Sula",
    "wof:placetype":"locality"
},
  "geometry": {"coordinates":[21.20938,41.97707],"type":"Point"}
}