{
  "type": "Feature",
  "properties": {
    "gn:admin1_code":"F6",
    "gn:asciiname":"Sula",
    "gn:country_code":"MK",
    "gn:dem":380,
    "gn:feature_class":"P",
    "gn:feature_code":"PPL",
    "gn:name":"\u0160ula",
    "gn:population":0,
    "gn:timezone":"Europe/Skopje",
    "iso:country":"MK",
    "name:mkd_x_preferred":[
        "\u0160ula"
    ],
    "name:mkd_x_variant":[
        "\u0428\u0443\u043b\u0430"
    ],
    "wof:name":"Sula",
    "wof:placetype":"locality"
},
  "geometry": {"coordinates":[21.20938,41.97707],"type":"Point"}
}