{
  "type": "Feature",
  "properties": {
    "gn:country":"MK",
    "gn:fcode":"PPLL",
    "gn:population":41,
    "iso:country":"MK",
    "name:mkd_x_preferred":[
        "Kozi\u010dino"
    ],
    "name:mkd_x_variant":[
        "\u041a\u043e\u0437\u0438\u0447\u0438\u043d\u043e"
    ],
    "qs:name":"Kozi\u010dino",
    "qs:photos_9r":0,
    "qs:photos_sr":0,
    "qs:pop_sr":"1",
    "wof:name":"Kozi\u010dino",
    "wof:placetype":"locality",
    "wof:population":41
},
  "geometry": {"coordinates":[21.08972,41.53278],"type":"Point"}
}