{
  "type": "Feature",
  "properties": {
    "gn:country":"MK",
    "gn:fcode":"PPL",
    "gn:pop":106,
    "iso:country":"MK",
    "name:ceb_x_preferred":[
        "Topolnica"
    ],
    "name:fra_x_preferred":[
        "Topolnica"
    ],
    "name:mkd_x_preferred":[
        "Topolnica"
    ],
    "name:mkd_x_variant":[
        "\u0422\u043e\u043f\u043e\u043b\u043d\u0438\u0446\u0430"
    ],
    "name:pol_x_preferred":[
        "Topolnica"
    ],
    "name:swe_x_preferred":[
        "Topolnica"
    ],
    "qs:name":"Topolnica",
    "qs:photos_9r":0,
    "qs:photos_sr":0,
    "qs:pop_sr":"1",
    "wd:wordcount":24,
    "wof:name":"Topolnica",
    "wof:placetype":"locality",
    "wof:population":106
},
  "geometry": {"coordinates":[21.16667,41.61528],"type":"Point"}
}