{
  "type": "Feature",
  "properties": {
    "gn:country":"MK",
    "gn:fcode":"PPL",
    "gn:population":15,
    "iso:country":"MK",
    "name:mkd_x_preferred":[
        "Gali\u0161te"
    ],
    "name:mkd_x_variant":[
        "\u0413\u0430\u043b\u0438\u0448\u0442\u0435"
    ],
    "qs:name":"Gali\u0161te",
    "qs:photos_9r":0,
    "qs:photos_sr":0,
    "qs:pop_sr":"1",
    "wof:name":"Gali\u0161te",
    "wof:placetype":"locality",
    "wof:population":15
},
  "geometry": {"coordinates":[21.86389,41.32111],"type":"Point"}
}