{
  "type": "Feature",
  "properties": {
    "gn:country":"MK",
    "gn:fcode":"PPL",
    "gn:pop":195,
    "iso:country":"MK",
    "name:bul_x_preferred":[
        "\u0414\u043e\u043b\u0433\u0430\u0435\u0446"
    ],
    "name:cat_x_preferred":[
        "Dolgaec"
    ],
    "name:ceb_x_preferred":[
        "Dolgaec"
    ],
    "name:deu_x_preferred":[
        "Dolgaec"
    ],
    "name:eng_x_preferred":[
        "Dolgaec"
    ],
    "name:fra_x_preferred":[
        "Dolgaets"
    ],
    "name:hun_x_preferred":[
        "Dolgaec"
    ],
    "name:mkd_x_preferred":[
        "\u0414\u043e\u043b\u0433\u0430\u0435\u0446"
    ],
    "name:nan_x_preferred":[
        "Dolgaets"
    ],
    "name:nld_x_preferred":[
        "Dolgaec"
    ],
    "name:sqi_x_preferred":[
        "Dollgaeci"
    ],
    "name:srp_x_preferred":[
        "\u0414\u043e\u043b\u0433\u0430\u0435\u0446"
    ],
    "name:swe_x_preferred":[
        "Dolgaec"
    ],
    "name:unk_x_variant":[
        "Dolgavec"
    ],
    "qs:name":"Dolgaec",
    "qs:photos_9r":0,
    "qs:photos_sr":0,
    "qs:pop_sr":"1",
    "wd:wordcount":31,
    "wof:name":"Dolgaec",
    "wof:placetype":"locality",
    "wof:population":195
},
  "geometry": {"coordinates":[21.37556,41.53528],"type":"Point"}
}