{
  "type": "Feature",
  "properties": {
    "gn:admin1_code":"19",
    "gn:asciiname":"Teranci",
    "gn:country_code":"MK",
    "gn:dem":372,
    "gn:feature_class":"P",
    "gn:feature_code":"PPL",
    "gn:name":"Teranci",
    "gn:population":0,
    "gn:timezone":"Europe/Skopje",
    "iso:country":"MK",
    "name:mkd_x_preferred":[
        "\u0422\u0435\u0440\u0430\u043d\u0446\u0438"
    ],
    "name:und_x_variant":[
        "Taranci",
        "Teranci"
    ],
    "wof:name":"Teranci",
    "wof:placetype":"locality"
},
  "geometry": {"coordinates":[22.35496,41.85057000000001],"type":"Point"}
}