{
  "type": "Feature",
  "properties": {
    "gn:admin1_code":"85",
    "gn:asciiname":"Misinska Maala",
    "gn:country_code":"MK",
    "gn:dem":822,
    "gn:feature_class":"P",
    "gn:feature_code":"PPL",
    "gn:name":"Mi\u0161inska Maala",
    "gn:population":0,
    "gn:timezone":"Europe/Skopje",
    "iso:country":"MK",
    "name:mkd_x_preferred":[
        "Mi\u0161inska Maala"
    ],
    "name:mkd_x_variant":[
        "\u041c\u0438\u0448\u0438\u043d\u0441\u043a\u0430 \u041c\u0430\u0430\u043b\u0430"
    ],
    "wof:name":"Misinska Maala",
    "wof:placetype":"locality"
},
  "geometry": {"coordinates":[22.06044,42.21654],"type":"Point"}
}