{
  "type": "Feature",
  "properties": {
    "gn:admin1_code":"E4",
    "gn:asciiname":"Niviste",
    "gn:country_code":"MK",
    "gn:dem":1192,
    "gn:feature_class":"P",
    "gn:feature_code":"PPL",
    "gn:name":"Nivi\u0161te",
    "gn:population":0,
    "gn:timezone":"Europe/Skopje",
    "iso:country":"MK",
    "name:mkd_x_preferred":[
        "\u041d\u0438\u0432\u0438\u0448\u0442\u0435"
    ],
    "name:und_x_variant":[
        "Njijvi\u0161te",
        "Nivishta",
        "Nivi\u0161ta",
        "Nivi\u0161te"
    ],
    "wof:name":"Niviste",
    "wof:placetype":"locality"
},
  "geometry": {"coordinates":[20.59139,41.73056],"type":"Point"}
}