{
  "type": "Feature",
  "properties": {
    "gn:admin1_code":"62",
    "gn:asciiname":"Mutavdziska Maala",
    "gn:country_code":"MK",
    "gn:dem":1092,
    "gn:feature_class":"P",
    "gn:feature_code":"PPL",
    "gn:name":"Mutavd\u017eiska Maala",
    "gn:population":0,
    "gn:timezone":"Europe/Skopje",
    "iso:country":"MK",
    "name:mkd_x_preferred":[
        "Mutavd\u017eiska Maala"
    ],
    "name:mkd_x_variant":[
        "\u041c\u0443\u0442\u0430\u0432\u045f\u0438\u0441\u043a\u0430 \u041c\u0430\u0430\u043b\u0430"
    ],
    "wof:name":"Mutavdziska Maala",
    "wof:placetype":"locality"
},
  "geometry": {"coordinates":[22.52476,42.0518],"type":"Point"}
}