{
  "type": "Feature",
  "properties": {
    "gn:admin1_code":"97",
    "gn:asciiname":"Travuljaci",
    "gn:country_code":"MK",
    "gn:dem":367,
    "gn:feature_class":"P",
    "gn:feature_code":"PPL",
    "gn:name":"Travuljaci",
    "gn:population":0,
    "gn:timezone":"Europe/Skopje",
    "iso:country":"MK",
    "name:mkd_x_preferred":[
        "Travuljaci"
    ],
    "name:mkd_x_variant":[
        "\u0422\u0440\u0430\u0432\u0443\u0459\u0430\u0446\u0438"
    ],
    "wof:name":"Travuljaci",
    "wof:placetype":"locality"
},
  "geometry": {"coordinates":[21.84237000000001,42.17437],"type":"Point"}
}