{
  "type": "Feature",
  "properties": {
    "gn:admin1_code":"F6",
    "gn:asciiname":"Kopanica",
    "gn:country_code":"MK",
    "gn:dem":424,
    "gn:feature_class":"P",
    "gn:feature_code":"PPL",
    "gn:name":"Kopanica",
    "gn:population":0,
    "gn:timezone":"Europe/Skopje",
    "iso:country":"MK",
    "name:bos_x_preferred":[
        "Kopanica"
    ],
    "name:bul_x_preferred":[
        "\u041a\u043e\u043f\u0430\u043d\u0438\u0446\u0430"
    ],
    "name:ceb_x_preferred":[
        "Kopanica"
    ],
    "name:fra_x_preferred":[
        "Kopanica"
    ],
    "name:lit_x_preferred":[
        "Kopanica"
    ],
    "name:mkd_x_preferred":[
        "\u041a\u043e\u043f\u0430\u043d\u0438\u0446\u0430"
    ],
    "name:pol_x_preferred":[
        "Kopanica"
    ],
    "name:srp_x_preferred":[
        "\u041a\u043e\u043f\u0430\u043d\u0438\u0446\u0430"
    ],
    "name:swe_x_preferred":[
        "Kopanica"
    ],
    "name:ukr_x_preferred":[
        "\u041a\u043e\u043f\u0430\u043d\u0438\u0446\u044f"
    ],
    "name:und_x_variant":[
        "Kopanic\u00eb"
    ],
    "wof:name":"Kopanica",
    "wof:placetype":"locality"
},
  "geometry": {"coordinates":[21.23496,42.00778],"type":"Point"}
}