{
  "type": "Feature",
  "properties": {
    "gn:admin1_code":"F6",
    "gn:asciiname":"Kopanica",
    "gn:country_code":"MK",
    "gn:dem":424,
    "gn:feature_class":"P",
    "gn:feature_code":"PPL",
    "gn:name":"Kopanica",
    "gn:population":0,
    "gn:timezone":"Europe/Skopje",
    "iso:country":"MK",
    "name:mkd_x_preferred":[
        "\u041a\u043e\u043f\u0430\u043d\u0438\u0446\u0430"
    ],
    "name:und_x_variant":[
        "Kopanic\u00eb",
        "Kopanica"
    ],
    "wof:name":"Kopanica",
    "wof:placetype":"locality"
},
  "geometry": {"coordinates":[21.23496,42.00778],"type":"Point"}
}