{
  "type": "Feature",
  "properties": {
    "gn:country":"MK",
    "gn:fcode":"PPL",
    "gn:pop":388,
    "iso:country":"MK",
    "name:mkd_x_preferred":[
        "\u041c\u0443\u0441\u0438\u043d\u0446\u0438"
    ],
    "name:unk_x_variant":[
        "Musa Oba"
    ],
    "qs:name":"Musinci",
    "qs:photos_9r":0,
    "qs:photos_sr":0,
    "qs:pop_sr":"2",
    "wd:wordcount":89,
    "wof:name":"Musinci",
    "wof:placetype":"locality",
    "wof:population":388
},
  "geometry": {"coordinates":[21.53806,41.16639],"type":"Point"}
}