{
  "type": "Feature",
  "properties": {
    "gn:country":"MK",
    "gn:fcode":"PPL",
    "gn:population":388,
    "iso:country":"MK",
    "name:bul_x_preferred":[
        "\u0410\u043b\u0438\u043d\u0446\u0438"
    ],
    "name:ceb_x_preferred":[
        "Alinci"
    ],
    "name:deu_x_preferred":[
        "Alinci"
    ],
    "name:eng_x_preferred":[
        "Alinci"
    ],
    "name:fra_x_preferred":[
        "Alintsi"
    ],
    "name:hun_x_preferred":[
        "Alinci"
    ],
    "name:mkd_x_preferred":[
        "\u041c\u0443\u0441\u0438\u043d\u0446\u0438"
    ],
    "name:mkd_x_variant":[
        "\u0410\u043b\u0438\u043d\u0446\u0438"
    ],
    "name:nan_x_preferred":[
        "Alintsi"
    ],
    "name:nld_x_preferred":[
        "Alinci"
    ],
    "name:sqi_x_preferred":[
        "Alinci"
    ],
    "name:srp_x_preferred":[
        "\u0410\u043b\u0438\u043d\u0446\u0438"
    ],
    "name:swe_x_preferred":[
        "Alinci"
    ],
    "name:und_x_variant":[
        "Musa Oba"
    ],
    "qs:name":"Musinci",
    "qs:photos_9r":0,
    "qs:photos_sr":0,
    "qs:pop_sr":"2",
    "wd:wordcount":89,
    "wof:name":"Musinci",
    "wof:placetype":"locality",
    "wof:population":388
},
  "geometry": {"coordinates":[21.53806,41.16639],"type":"Point"}
}