{
  "type": "Feature",
  "properties": {
    "gn:country":"MK",
    "gn:fcode":"PPLA",
    "gn:pop":20664,
    "iso:country":"MK",
    "name:ara_x_preferred":[
        "\u063a\u064a\u0641\u063a\u0644\u064a\u0627"
    ],
    "name:bul_x_preferred":[
        "\u0413\u0435\u0432\u0433\u0435\u043b\u0438"
    ],
    "name:chu_x_preferred":[
        "\u0413\u0454\u0475\u0433\u0454\u043b\u0430"
    ],
    "name:ell_x_preferred":[
        "\u0393\u03b5\u03c5\u03b3\u03b5\u03bb\u03ae"
    ],
    "name:eng_x_preferred":[
        "Gevgelija"
    ],
    "name:fas_x_preferred":[
        "\u06af\u0641\u0644\u06cc\u0627"
    ],
    "name:fra_x_preferred":[
        "Guevgueliya"
    ],
    "name:heb_x_preferred":[
        "\u05d2\u05d1\u05d2\u05dc\u05d9\u05d4"
    ],
    "name:hun_x_preferred":[
        "Gyevgyelija"
    ],
    "name:hye_x_preferred":[
        "\u0533\u0587\u0563\u0565\u056c\u056b\u0561"
    ],
    "name:jpn_x_preferred":[
        "\u30b2\u30f4\u30b2\u30ea\u30e4"
    ],
    "name:kat_x_preferred":[
        "\u10d2\u10d4\u10d5\u10d2\u10d4\u10da\u10d8\u10d0"
    ],
    "name:kor_x_preferred":[
        "\uac8c\ube0c\uac94\ub9ac\uc57c"
    ],
    "name:mkd_x_preferred":[
        "\u0413\u0435\u0432\u0433\u0435\u043b\u0438\u0458\u0430"
    ],
    "name:pol_x_preferred":[
        "Gewgelija"
    ],
    "name:rus_x_preferred":[
        "\u0413\u0435\u0432\u0433\u0435\u043b\u0438\u044f"
    ],
    "name:sqi_x_preferred":[
        "Gjevgjelia"
    ],
    "name:srp_x_preferred":[
        "\u0402\u0435\u0432\u0452\u0435\u043b\u0438\u0458\u0430"
    ],
    "name:ukr_x_preferred":[
        "\u0413\u0435\u0432\u0433\u0435\u043b\u0456\u044f"
    ],
    "name:unk_x_variant":[
        "Gevgeli"
    ],
    "name:vol_x_preferred":[
        "Gevgeliya"
    ],
    "name:zho_x_preferred":[
        "\u84cb\u592b\u84cb\u5229\u4e9e"
    ],
    "qs:name":"Gevgelija",
    "qs:name_adm0":"Macedonia",
    "qs:name_adm1":"Gevgelija",
    "qs:photos":42,
    "qs:photos_1k":9,
    "qs:photos_9k":1,
    "qs:photos_9r":2,
    "qs:photos_all":42,
    "qs:photos_sr":2,
    "qs:placetype":"Town",
    "qs:pop_sr":"7",
    "wd:wordcount":358,
    "wof:name":"Gevgelija",
    "wof:placetype":"locality",
    "wof:population":20664
},
  "geometry": {"coordinates":[22.50141,41.14166],"type":"Point"}
}