{
  "type": "Feature",
  "properties": {
    "gn:admin1_code":"97",
    "gn:asciiname":"Glecenska Maala",
    "gn:country_code":"MK",
    "gn:dem":807,
    "gn:feature_class":"P",
    "gn:feature_code":"PPL",
    "gn:name":"Gle\u010denska Maala",
    "gn:population":0,
    "gn:timezone":"Europe/Skopje",
    "iso:country":"MK",
    "name:mkd_x_preferred":[
        "Gle\u010denska Maala"
    ],
    "name:mkd_x_variant":[
        "\u0413\u043b\u0435\u0447\u0435\u043d\u0441\u043a\u0430 \u041c\u0430\u0430\u043b\u0430"
    ],
    "wof:name":"Glecenska Maala",
    "wof:placetype":"locality"
},
  "geometry": {"coordinates":[21.93026,42.28928],"type":"Point"}
}