{
  "type": "Feature",
  "properties": {
    "gn:country":"MK",
    "gn:fcode":"PPL",
    "gn:population":2878,
    "iso:country":"MK",
    "name:bul_x_preferred":[
        "\u0427\u0430\u0448\u043a\u0430"
    ],
    "name:ceb_x_preferred":[
        "\u010ca\u0161ka"
    ],
    "name:deu_x_preferred":[
        "\u010ca\u0161ka"
    ],
    "name:eng_x_preferred":[
        "\u010ca\u0161ka"
    ],
    "name:epo_x_preferred":[
        "\u010ca\u0161ka"
    ],
    "name:fra_x_preferred":[
        "Tchachka"
    ],
    "name:hun_x_preferred":[
        "Csaska"
    ],
    "name:kat_x_preferred":[
        "\u10e9\u10d0\u10e8\u10d9\u10d0"
    ],
    "name:mkd_x_preferred":[
        "\u0427\u0430\u0448\u043a\u0430"
    ],
    "name:nan_x_preferred":[
        "Tchachka"
    ],
    "name:nld_x_preferred":[
        "\u010ca\u0161ka"
    ],
    "name:nno_x_preferred":[
        "Tsjasjka"
    ],
    "name:pol_x_preferred":[
        "Czaszka"
    ],
    "name:rus_x_preferred":[
        "\u0427\u0430\u0448\u043a\u0430"
    ],
    "name:sqi_x_preferred":[
        "\u00c7ashka"
    ],
    "name:srp_x_preferred":[
        "\u0427\u0430\u0448\u043a\u0430"
    ],
    "name:swe_x_preferred":[
        "\u010casjka"
    ],
    "name:tur_x_preferred":[
        "\u00c7a\u015fka"
    ],
    "name:ukr_x_preferred":[
        "\u0427\u0430\u0448\u043a\u0430"
    ],
    "qs:name":"\u010ca\u0161ka",
    "qs:name_adm0":"Macedonia",
    "qs:name_adm1":"\u010ca\u0161ka",
    "qs:photos_9k":1,
    "qs:photos_9r":1,
    "qs:photos_all":1,
    "qs:photos_sr":0,
    "qs:placetype":"Town",
    "qs:pop_sr":"4",
    "wd:elevation":344.0,
    "wd:wordcount":60,
    "wof:name":"\u010ca\u0161ka",
    "wof:placetype":"locality",
    "wof:population":2878
},
  "geometry": {"coordinates":[21.66222,41.65056],"type":"Point"}
}