{
  "type": "Feature",
  "properties": {
    "gn:country":"MK",
    "gn:fcode":"PPL",
    "gn:pop":2878,
    "iso:country":"MK",
    "name:mkd_x_preferred":[
        "\u0427\u0430\u0448\u043a\u0430"
    ],
    "qs:name":"\u010ca\u0161ka",
    "qs:name_adm0":"Macedonia",
    "qs:name_adm1":"\u010ca\u0161ka",
    "qs:photos_9k":1,
    "qs:photos_9r":1,
    "qs:photos_all":1,
    "qs:photos_sr":0,
    "qs:placetype":"Town",
    "qs:pop_sr":"4",
    "wd:elevation":344.0,
    "wd:wordcount":60,
    "wof:name":"\u010ca\u0161ka",
    "wof:placetype":"locality",
    "wof:population":2878
},
  "geometry": {"coordinates":[21.66222,41.65056],"type":"Point"}
}