{
  "type": "Feature",
  "properties": {
    "gn:admin1_code":"52",
    "gn:asciiname":"Recka Maala",
    "gn:country_code":"MK",
    "gn:dem":853,
    "gn:feature_class":"P",
    "gn:feature_code":"PPLL",
    "gn:name":"Re\u010dka Maala",
    "gn:population":0,
    "gn:timezone":"Europe/Skopje",
    "iso:country":"MK",
    "name:mkd_x_preferred":[
        "Re\u010dka Maala"
    ],
    "name:mkd_x_variant":[
        "\u0420\u0435\u0447\u043a\u0430 \u041c\u0430\u0430\u043b\u0430"
    ],
    "wof:name":"Recka Maala",
    "wof:placetype":"locality"
},
  "geometry": {"coordinates":[22.31154,42.28659],"type":"Point"}
}