{
  "type": "Feature",
  "properties": {
    "gn:admin1_code":"52",
    "gn:asciiname":"Kiselica",
    "gn:country_code":"MK",
    "gn:dem":936,
    "gn:feature_class":"P",
    "gn:feature_code":"PPLL",
    "gn:name":"Kiselica",
    "gn:population":0,
    "gn:timezone":"Europe/Skopje",
    "iso:country":"MK",
    "name:mkd_x_preferred":[
        "Kiselica"
    ],
    "name:mkd_x_variant":[
        "\u041a\u0438\u0441\u0435\u043b\u0438\u0446\u0430"
    ],
    "wof:name":"Kiselica",
    "wof:placetype":"locality"
},
  "geometry": {"coordinates":[22.34443,42.25115],"type":"Point"}
}