{
  "type": "Feature",
  "properties": {
    "gn:admin1_code":"98",
    "gn:asciiname":"Suvo Grlo",
    "gn:country_code":"MK",
    "gn:dem":460,
    "gn:feature_class":"P",
    "gn:feature_code":"PPL",
    "gn:name":"Suvo Grlo",
    "gn:population":0,
    "gn:timezone":"Europe/Skopje",
    "iso:country":"MK",
    "name:mkd_x_preferred":[
        "\u0421\u0443\u0432\u043e \u0413\u0440\u043b\u043e"
    ],
    "name:und_x_variant":[
        "Sogrlo",
        "Suvo Grlo"
    ],
    "wof:name":"Suvo Grlo",
    "wof:placetype":"locality"
},
  "geometry": {"coordinates":[22.2319,41.60687],"type":"Point"}
}