{
  "type": "Feature",
  "properties": {
    "gn:admin1_code":"83",
    "gn:asciiname":"Strisovci",
    "gn:country_code":"MK",
    "gn:dem":482,
    "gn:feature_class":"P",
    "gn:feature_code":"PPL",
    "gn:name":"Strisovci",
    "gn:population":0,
    "gn:timezone":"Europe/Skopje",
    "iso:country":"MK",
    "name:mkd_x_preferred":[
        "\u0421\u0442\u0440\u0438\u0441\u043e\u0432\u0446\u0438"
    ],
    "name:mkd_x_variant":[
        "Strezovce",
        "\u0421\u0442\u0440\u0435\u0437\u043e\u0432\u0446\u0435"
    ],
    "name:und_x_variant":[
        "Strisovce",
        "Strojisavci",
        "Strisovci"
    ],
    "wof:name":"Strisovci",
    "wof:placetype":"locality"
},
  "geometry": {"coordinates":[22.09655,41.96592],"type":"Point"}
}