{
  "type": "Feature",
  "properties": {
    "gn:admin1_code":"E7",
    "gn:asciiname":"Dabilja",
    "gn:country_code":"MK",
    "gn:dem":222,
    "gn:feature_class":"P",
    "gn:feature_code":"PPL",
    "gn:name":"Dabilja",
    "gn:population":0,
    "gn:timezone":"Europe/Skopje",
    "iso:country":"MK",
    "name:mkd_x_preferred":[
        "\u0414\u0430\u0431\u0438\u043b\u0458\u0430"
    ],
    "name:und_x_variant":[
        "Dabila",
        "Dabilja",
        "Dabile"
    ],
    "wof:name":"Dabilja",
    "wof:placetype":"locality"
},
  "geometry": {"coordinates":[22.69056,41.44315],"type":"Point"}
}