{
  "type": "Feature",
  "properties": {
    "gn:admin1_code":"22",
    "gn:asciiname":"Bojcoska Maala",
    "gn:country_code":"MK",
    "gn:dem":661,
    "gn:feature_class":"P",
    "gn:feature_code":"PPL",
    "gn:name":"Boj\u010doska Maala",
    "gn:population":0,
    "gn:timezone":"Europe/Skopje",
    "iso:country":"MK",
    "name:mkd_x_preferred":[
        "\u0411\u043e\u0458\u0447\u043e\u0441\u043a\u0430 \u041c\u0430\u0430\u043b\u0430"
    ],
    "name:und_x_variant":[
        "Stefanska",
        "Boj\u010doska Maala"
    ],
    "wof:name":"Bojcoska Maala",
    "wof:placetype":"locality"
},
  "geometry": {"coordinates":[22.66713,41.97333],"type":"Point"}
}