{
  "type": "Feature",
  "properties": {
    "gn:admin1_code":"97",
    "gn:asciiname":"Dejlovce",
    "gn:country_code":"MK",
    "gn:dem":1022,
    "gn:feature_class":"P",
    "gn:feature_code":"PPLL",
    "gn:name":"Dejlovce",
    "gn:population":0,
    "gn:timezone":"Europe/Skopje",
    "iso:country":"MK",
    "name:mkd_x_preferred":[
        "\u0414\u0435\u0458\u043b\u043e\u0432\u0446\u0435"
    ],
    "name:und_x_variant":[
        "Dejlovci",
        "Dejlovce"
    ],
    "wof:name":"Dejlovce",
    "wof:placetype":"locality"
},
  "geometry": {"coordinates":[22.0187,42.25518],"type":"Point"}
}