{
  "type": "Feature",
  "properties": {
    "gn:admin1_code":"83",
    "gn:asciiname":"Ratkovica",
    "gn:country_code":"MK",
    "gn:dem":986,
    "gn:feature_class":"P",
    "gn:feature_code":"PPL",
    "gn:name":"Ratkovica",
    "gn:population":0,
    "gn:timezone":"Europe/Skopje",
    "iso:country":"MK",
    "name:bos_x_preferred":[
        "Ratkovica"
    ],
    "name:ceb_x_preferred":[
        "Ratkovica"
    ],
    "name:hrv_x_preferred":[
        "Ratkovica"
    ],
    "name:mkd_x_preferred":[
        "\u0420\u0430\u0442\u043a\u043e\u0432\u0438\u0446\u0430"
    ],
    "name:nld_x_preferred":[
        "Ratkovica"
    ],
    "name:slv_x_preferred":[
        "Ratkovica"
    ],
    "name:spa_x_preferred":[
        "Ratkovica"
    ],
    "name:srp_x_preferred":[
        "\u0420\u0430\u0442\u043a\u043e\u0432\u0438\u0446\u0430"
    ],
    "name:swe_x_preferred":[
        "Ratkovica"
    ],
    "name:ukr_x_preferred":[
        "\u0420\u0430\u0442\u043a\u043e\u0432\u0438\u0446\u044f"
    ],
    "name:und_x_variant":[
        "Ratavica",
        "Ratovica"
    ],
    "wof:name":"Ratkovica",
    "wof:placetype":"locality"
},
  "geometry": {"coordinates":[22.30444,42.00778],"type":"Point"}
}