{
  "type": "Feature",
  "properties": {
    "gn:country":"MK",
    "gn:fcode":"PPL",
    "gn:pop":1272,
    "iso:country":"MK",
    "name:alb_x_preferred":[
        "Llogovardi"
    ],
    "name:bul_x_preferred":[
        "\u041b\u043e\u0433\u043e\u0432\u0430\u0440\u0434\u0438"
    ],
    "name:dut_x_preferred":[
        "Logovardi"
    ],
    "name:eng_x_preferred":[
        "Logovardi"
    ],
    "name:fre_x_preferred":[
        "Logovardi"
    ],
    "name:hun_x_preferred":[
        "Logovardi"
    ],
    "name:mac_x_preferred":[
        "\u041b\u043e\u0433\u043e\u0432\u0430\u0440\u0434\u0438"
    ],
    "name:mkd_x_preferred":[
        "\u041b\u043e\u0433\u043e\u0432\u0430\u0440\u0434\u0438"
    ],
    "name:pol_x_preferred":[
        "\u0141ogowardi"
    ],
    "name:srp_x_preferred":[
        "\u041b\u043e\u0433\u043e\u0432\u0430\u0440\u0434\u0438"
    ],
    "name:swe_x_preferred":[
        "Logovardi"
    ],
    "name:unk_x_variant":[
        "\u010cekrkci"
    ],
    "qs:name":"Logovardi",
    "qs:photos_9r":0,
    "qs:photos_sr":0,
    "qs:pop_sr":"3",
    "wd:elevation":576.0,
    "wd:wordcount":134,
    "wof:name":"Logovardi",
    "wof:placetype":"locality",
    "wof:population":1272
},
  "geometry": {"coordinates":[21.41139,41.02972],"type":"Point"}
}