{
  "type": "Feature",
  "properties": {
    "gn:admin1_code":"18",
    "gn:asciiname":"Bajramovci",
    "gn:country_code":"MK",
    "gn:dem":854,
    "gn:feature_class":"P",
    "gn:feature_code":"PPL",
    "gn:name":"Bajramovci",
    "gn:population":0,
    "gn:timezone":"Europe/Skopje",
    "iso:country":"MK",
    "name:bul_x_preferred":[
        "\u0411\u0430\u0439\u0440\u0430\u043c\u043e\u0432\u0446\u0438"
    ],
    "name:fra_x_preferred":[
        "Bayramovtsi"
    ],
    "name:hun_x_preferred":[
        "Bajramovci"
    ],
    "name:mkd_x_preferred":[
        "\u0411\u0430\u0458\u0440\u0430\u043c\u043e\u0432\u0446\u0438"
    ],
    "name:sqi_x_preferred":[
        "Bajramoci"
    ],
    "name:srp_x_preferred":[
        "\u0411\u0430\u0458\u0440\u0430\u043c\u043e\u0432\u0446\u0438"
    ],
    "name:und_x_variant":[
        "Jankovci"
    ],
    "wof:name":"Bajramovci",
    "wof:placetype":"locality"
},
  "geometry": {"coordinates":[20.57071,41.4805],"type":"Point"}
}