{
  "type": "Feature",
  "properties": {
    "gn:admin1_code":"06",
    "gn:asciiname":"Zabeni",
    "gn:country_code":"MK",
    "gn:dem":584,
    "gn:feature_class":"P",
    "gn:feature_code":"PPL",
    "gn:name":"\u017dabeni",
    "gn:population":0,
    "gn:timezone":"Europe/Skopje",
    "iso:country":"MK",
    "name:mkd_x_preferred":[
        "\u017dabeni"
    ],
    "name:mkd_x_variant":[
        "\u0416\u0430\u0431\u0435\u043d\u0438"
    ],
    "name:und_x_variant":[
        "\u017dabjane",
        "\u0416\u0430\u0431\u0458\u0430\u043d\u0435"
    ],
    "wof:name":"Zabeni",
    "wof:placetype":"locality"
},
  "geometry": {"coordinates":[21.39155,40.95578],"type":"Point"}
}