{
  "type": "Feature",
  "properties": {
    "gn:country":"MK",
    "gn:fcode":"PPL",
    "gn:pop":513,
    "iso:country":"MK",
    "name:alb_x_preferred":[
        "Rotina"
    ],
    "name:bul_x_preferred":[
        "\u0420\u043e\u0442\u0438\u043d\u043e"
    ],
    "name:dut_x_preferred":[
        "Rotino"
    ],
    "name:eng_x_preferred":[
        "Rotino"
    ],
    "name:fre_x_preferred":[
        "Rotino"
    ],
    "name:hun_x_preferred":[
        "Rotino"
    ],
    "name:mac_x_preferred":[
        "\u0420\u043e\u0442\u0438\u043d\u043e"
    ],
    "name:mkd_x_preferred":[
        "Rotino"
    ],
    "name:mkd_x_variant":[
        "\u0420\u043e\u0442\u0438\u043d\u043e"
    ],
    "name:nan_x_preferred":[
        "Rotino"
    ],
    "name:pol_x_preferred":[
        "Rotino"
    ],
    "name:srp_x_preferred":[
        "\u0420\u043e\u0442\u0438\u043d\u043e"
    ],
    "name:swe_x_preferred":[
        "Rotino"
    ],
    "qs:name":"Rotino",
    "qs:photos_9r":0,
    "qs:photos_sr":0,
    "qs:pop_sr":"2",
    "wd:elevation":1020.0,
    "wd:wordcount":31,
    "wof:name":"Rotino",
    "wof:placetype":"locality",
    "wof:population":513
},
  "geometry": {"coordinates":[21.21167,41.05722],"type":"Point"}
}