{
  "type": "Feature",
  "properties": {
    "gn:admin1_code":"52",
    "gn:asciiname":"Divjanci",
    "gn:country_code":"MK",
    "gn:dem":997,
    "gn:feature_class":"P",
    "gn:feature_code":"PPL",
    "gn:name":"Divjanci",
    "gn:population":0,
    "gn:timezone":"Europe/Skopje",
    "iso:country":"MK",
    "name:mkd_x_preferred":[
        "Divjanci"
    ],
    "name:mkd_x_variant":[
        "\u0414\u0438\u0432\u0458\u0430\u043d\u0446\u0438"
    ],
    "wof:name":"Divjanci",
    "wof:placetype":"locality"
},
  "geometry": {"coordinates":[22.31566,42.22474],"type":"Point"}
}