{
  "type": "Feature",
  "properties": {
    "gn:admin1_code":"F6",
    "gn:asciiname":"Volkovo",
    "gn:country_code":"MK",
    "gn:dem":286,
    "gn:feature_class":"P",
    "gn:feature_code":"PPL",
    "gn:name":"Volkovo",
    "gn:population":0,
    "gn:timezone":"Europe/Skopje",
    "iso:country":"MK",
    "name:bel_x_preferred":[
        "\u0412\u043e\u043b\u043a\u0430\u0432\u0430"
    ],
    "name:est_x_preferred":[
        "Volkovo"
    ],
    "name:hye_x_preferred":[
        "\u054e\u0578\u056c\u056f\u0578\u057e\u0578"
    ],
    "name:mkd_x_preferred":[
        "Vu\u010di Dol"
    ],
    "name:mkd_x_variant":[
        "Volkovo",
        "\u0412\u043e\u043b\u043a\u043e\u0432\u043e"
    ],
    "name:rus_x_preferred":[
        "\u0412\u043e\u043b\u043a\u043e\u0432\u043e"
    ],
    "name:tat_x_preferred":[
        "\u0412\u043e\u043b\u043a\u043e\u0432\u043e"
    ],
    "name:ukr_x_preferred":[
        "\u0412\u043e\u043b\u043a\u043e\u0432\u043e"
    ],
    "wof:name":"Volkovo",
    "wof:placetype":"locality"
},
  "geometry": {"coordinates":[21.34633,42.04482],"type":"Point"}
}