{
  "type": "Feature",
  "properties": {
    "gn:admin1_code":"A4",
    "gn:asciiname":"Meckuevci",
    "gn:country_code":"MK",
    "gn:dem":461,
    "gn:feature_class":"P",
    "gn:feature_code":"PPL",
    "gn:name":"Me\u010dkuevci",
    "gn:population":0,
    "gn:timezone":"Europe/Skopje",
    "iso:country":"MK",
    "name:mkd_x_preferred":[
        "\u041c\u0435\u0447\u043a\u0443\u0435\u0432\u0446\u0438"
    ],
    "name:und_x_variant":[
        "Me\u010dkujevci",
        "Me\u010dkuevci"
    ],
    "wof:name":"Meckuevci",
    "wof:placetype":"locality"
},
  "geometry": {"coordinates":[22.06193,41.91767],"type":"Point"}
}