{
  "type": "Feature",
  "properties": {
    "gn:admin1_code":"51",
    "gn:asciiname":"Zabel Maala",
    "gn:country_code":"MK",
    "gn:dem":682,
    "gn:feature_class":"P",
    "gn:feature_code":"PPL",
    "gn:name":"Zabel Maala",
    "gn:population":0,
    "gn:timezone":"Europe/Skopje",
    "iso:country":"MK",
    "name:mkd_x_preferred":[
        "Zabel Maala"
    ],
    "name:mkd_x_variant":[
        "\u0417\u0430\u0431\u0435\u043b \u041c\u0430\u0430\u043b\u0430"
    ],
    "wof:name":"Zabel Maala",
    "wof:placetype":"locality"
},
  "geometry": {"coordinates":[22.02062,42.12361],"type":"Point"}
}