{
  "type": "Feature",
  "properties": {
    "gn:admin1_code":"43",
    "gn:asciiname":"Gresnica",
    "gn:country_code":"MK",
    "gn:dem":694,
    "gn:feature_class":"P",
    "gn:feature_code":"PPL",
    "gn:name":"Gre\u0161nica",
    "gn:population":0,
    "gn:timezone":"Europe/Skopje",
    "iso:country":"MK",
    "name:mkd_x_preferred":[
        "\u0413\u0440\u0435\u0448\u043d\u0438\u0446\u0430"
    ],
    "name:und_x_variant":[
        "Gare\u0161nica",
        "Gre\u0161nica"
    ],
    "wof:name":"Gresnica",
    "wof:placetype":"locality"
},
  "geometry": {"coordinates":[20.93506,41.57485],"type":"Point"}
}