{
  "type": "Feature",
  "properties": {
    "gn:admin1_code":"D4",
    "gn:asciiname":"Mitroj Krsti",
    "gn:country_code":"MK",
    "gn:dem":830,
    "gn:feature_class":"P",
    "gn:feature_code":"PPL",
    "gn:name":"Mitroj Krsti",
    "gn:population":0,
    "gn:timezone":"Europe/Skopje",
    "iso:country":"MK",
    "name:mkd_x_preferred":[
        "\u041c\u0438\u0442\u0440\u043e\u0458 \u041a\u0440\u0441\u0442\u0438"
    ],
    "name:und_x_variant":[
        "Mitrovi Krsti",
        "Mitroj Krsti"
    ],
    "wof:name":"Mitroj Krsti",
    "wof:placetype":"locality"
},
  "geometry": {"coordinates":[20.89278,41.73805],"type":"Point"}
}