{
  "type": "Feature",
  "properties": {
    "gn:admin1_code":"46",
    "gn:asciiname":"Kocanik",
    "gn:country_code":"MK",
    "gn:dem":938,
    "gn:feature_class":"P",
    "gn:feature_code":"PPL",
    "gn:name":"Ko\u010danik",
    "gn:population":0,
    "gn:timezone":"Europe/Skopje",
    "iso:country":"MK",
    "name:mkd_x_preferred":[
        "Ko\u010danik"
    ],
    "name:mkd_x_variant":[
        "\u041a\u043e\u0447\u0430\u043d\u0438\u043a"
    ],
    "wof:name":"Kocanik",
    "wof:placetype":"locality"
},
  "geometry": {"coordinates":[22.435,42.03111],"type":"Point"}
}