{
  "type": "Feature",
  "properties": {
    "gn:country":"MK",
    "gn:fcode":"PPL",
    "gn:pop":2292,
    "iso:country":"MK",
    "name:bul_x_preferred":[
        "\u0418\u0434\u0440\u0438\u0437\u043e\u0432\u043e"
    ],
    "name:deu_x_preferred":[
        "Idrizovo"
    ],
    "name:eng_x_preferred":[
        "Idrizovo"
    ],
    "name:fra_x_preferred":[
        "Idrizovo"
    ],
    "name:mkd_x_preferred":[
        "\u0418\u0434\u0440\u0438\u0437\u043e\u0432\u043e"
    ],
    "name:nld_x_preferred":[
        "Idrizovo"
    ],
    "name:rus_x_preferred":[
        "\u0418\u0434\u0440\u0438\u0437\u043e\u0432\u043e"
    ],
    "name:sqi_x_preferred":[
        "Idrizova"
    ],
    "name:srp_x_preferred":[
        "\u0418\u0434\u0440\u0438\u0437\u043e\u0432\u043e"
    ],
    "name:swe_x_preferred":[
        "Idrizovo"
    ],
    "name:unk_x_variant":[
        "Idrizovo"
    ],
    "qs:name":"\u0418\u0434\u0440\u0438\u0437\u043e\u0432\u043e",
    "qs:photos_9r":0,
    "qs:photos_sr":0,
    "qs:pop_sr":"4",
    "wof:name":"\u0418\u0434\u0440\u0438\u0437\u043e\u0432\u043e",
    "wof:placetype":"locality",
    "wof:population":2292
},
  "geometry": {"coordinates":[21.57556,41.96083],"type":"Point"}
}