{
  "type": "Feature",
  "properties": {
    "gn:admin1_code":"62",
    "gn:asciiname":"Ramni Dol",
    "gn:country_code":"MK",
    "gn:dem":1037,
    "gn:feature_class":"P",
    "gn:feature_code":"PPL",
    "gn:name":"Ramni Dol",
    "gn:population":0,
    "gn:timezone":"Europe/Skopje",
    "iso:country":"MK",
    "name:mkd_x_preferred":[
        "Ramni Dol"
    ],
    "name:mkd_x_variant":[
        "\u0420\u0430\u043c\u043d\u0438 \u0414\u043e\u043b"
    ],
    "wof:name":"Ramni Dol",
    "wof:placetype":"locality"
},
  "geometry": {"coordinates":[22.52476,42.07432],"type":"Point"}
}