{
  "type": "Feature",
  "properties": {
    "gn:admin1_code":"51",
    "gn:asciiname":"Sotirova Maala",
    "gn:country_code":"MK",
    "gn:dem":512,
    "gn:feature_class":"P",
    "gn:feature_code":"PPL",
    "gn:name":"Sotirova Maala",
    "gn:population":0,
    "gn:timezone":"Europe/Skopje",
    "iso:country":"MK",
    "name:mkd_x_preferred":[
        "Sotirova Maala"
    ],
    "name:mkd_x_variant":[
        "\u0421\u043e\u0442\u0438\u0440\u043e\u0432\u0430 \u041c\u0430\u0430\u043b\u0430"
    ],
    "wof:name":"Sotirova Maala",
    "wof:placetype":"locality"
},
  "geometry": {"coordinates":[22.00603,42.10385],"type":"Point"}
}