{
  "type": "Feature",
  "properties": {
    "gn:country":"MK",
    "gn:fcode":"PPL",
    "gn:pop":967,
    "iso:country":"MK",
    "name:bul_x_preferred":[
        "\u041f\u0440\u0435\u0433\u043b\u043e\u0432\u043e"
    ],
    "name:ceb_x_preferred":[
        "Preglovo"
    ],
    "name:fra_x_preferred":[
        "Preglovo"
    ],
    "name:hun_x_preferred":[
        "Preglovo"
    ],
    "name:mkd_x_preferred":[
        "\u041f\u0440\u0435\u0433\u043b\u043e\u0432\u043e"
    ],
    "name:sqi_x_preferred":[
        "Pregllova"
    ],
    "name:srp_x_preferred":[
        "\u041f\u0440\u0435\u0433\u043b\u043e\u0432\u043e"
    ],
    "name:swe_x_preferred":[
        "Preglovo"
    ],
    "name:unk_x_variant":[
        "Preglevo"
    ],
    "qs:name":"Preglovo",
    "qs:photos_9r":0,
    "qs:photos_sr":0,
    "qs:pop_sr":"2",
    "wof:name":"Preglovo",
    "wof:placetype":"locality",
    "wof:population":967
},
  "geometry": {"coordinates":[21.12083,41.46361],"type":"Point"}
}