{
  "type": "Feature",
  "properties": {
    "gn:admin1_code":"85",
    "gn:asciiname":"Kavaklija",
    "gn:country_code":"MK",
    "gn:dem":477,
    "gn:feature_class":"P",
    "gn:feature_code":"PPL",
    "gn:name":"Kavaklija",
    "gn:population":0,
    "gn:timezone":"Europe/Skopje",
    "iso:country":"MK",
    "name:mkd_x_preferred":[
        "Kavaklija"
    ],
    "name:mkd_x_variant":[
        "\u041a\u0430\u0432\u0430\u043a\u043b\u0438\u0458\u0430"
    ],
    "wof:name":"Kavaklija",
    "wof:placetype":"locality"
},
  "geometry": {"coordinates":[22.1419,42.15868],"type":"Point"}
}