{
  "type": "Feature",
  "properties": {
    "gn:admin1_code":"52",
    "gn:asciiname":"Recanje",
    "gn:country_code":"MK",
    "gn:dem":881,
    "gn:feature_class":"P",
    "gn:feature_code":"PPL",
    "gn:name":"Re\u010danje",
    "gn:population":0,
    "gn:timezone":"Europe/Skopje",
    "iso:country":"MK",
    "name:mkd_x_preferred":[
        "Re\u010danje"
    ],
    "name:mkd_x_variant":[
        "\u0420\u0435\u0447\u0430\u045a\u0435"
    ],
    "wof:name":"Recanje",
    "wof:placetype":"locality"
},
  "geometry": {"coordinates":[22.30028,42.29333],"type":"Point"}
}