{
  "type": "Feature",
  "properties": {
    "gn:country":"MK",
    "gn:fcode":"PPL",
    "gn:pop":2,
    "iso:country":"MK",
    "name:mkd_x_preferred":[
        "Dvori\u0161te"
    ],
    "name:mkd_x_variant":[
        "\u0414\u0432\u043e\u0440\u0438\u0448\u0442\u0435"
    ],
    "qs:name":"Dvori\u0161te",
    "qs:photos_9r":0,
    "qs:photos_sr":0,
    "qs:pop_sr":"1",
    "wd:wordcount":54,
    "wof:name":"Dvori\u0161te",
    "wof:placetype":"locality",
    "wof:population":2
},
  "geometry": {"coordinates":[21.83611,41.57833],"type":"Point"}
}