{
  "type": "Feature",
  "properties": {
    "gn:admin1_code":"20",
    "gn:asciiname":"Azirlar",
    "gn:country_code":"MK",
    "gn:dem":1297,
    "gn:feature_class":"P",
    "gn:feature_code":"PPL",
    "gn:name":"Azirlar",
    "gn:population":0,
    "gn:timezone":"Europe/Skopje",
    "iso:country":"MK",
    "name:mkd_x_preferred":[
        "Azirlar"
    ],
    "name:mkd_x_variant":[
        "\u0410\u0437\u0438\u0440\u043b\u0430\u0440"
    ],
    "wof:name":"Azirlar",
    "wof:placetype":"locality"
},
  "geometry": {"coordinates":[21.49189,42.20319],"type":"Point"}
}