{
  "type": "Feature",
  "properties": {
    "gn:country":"MK",
    "gn:fcode":"PPL",
    "gn:population":37,
    "iso:country":"MK",
    "name:mkd_x_preferred":[
        "Gorno \u01f4u\u01f5ance"
    ],
    "name:mkd_x_variant":[
        "\u0413\u043e\u0440\u043d\u043e \u0403\u0443\u0453\u0430\u043d\u0446\u0435"
    ],
    "name:und_x_variant":[
        "Gorno Dzugance"
    ],
    "qs:name":"Gorno \u00d0ugance",
    "qs:photos_9r":0,
    "qs:photos_sr":0,
    "qs:pop_sr":"1",
    "wof:name":"Gorno \u00d0ugance",
    "wof:placetype":"locality",
    "wof:population":37
},
  "geometry": {"coordinates":[21.98528,41.99361],"type":"Point"}
}