{
  "type": "Feature",
  "properties": {
    "gn:country":"MK",
    "gn:fcode":"PPL",
    "gn:pop":17,
    "iso:country":"MK",
    "name:bar_x_preferred":[
        "Dabnica"
    ],
    "name:bul_x_preferred":[
        "\u0414\u0430\u0431\u043d\u0438\u0446\u0430"
    ],
    "name:cat_x_preferred":[
        "Dabnica"
    ],
    "name:ces_x_preferred":[
        "Dabnica"
    ],
    "name:dan_x_preferred":[
        "Dabnica"
    ],
    "name:deu_x_preferred":[
        "Dabnica"
    ],
    "name:eng_x_preferred":[
        "Dabnica"
    ],
    "name:epo_x_preferred":[
        "Dabnica"
    ],
    "name:fin_x_preferred":[
        "Dabnica"
    ],
    "name:fra_x_preferred":[
        "Dabnitsa"
    ],
    "name:gla_x_preferred":[
        "Dabnica"
    ],
    "name:glg_x_preferred":[
        "Dabnica"
    ],
    "name:gsw_x_preferred":[
        "Dabnica"
    ],
    "name:hrv_x_preferred":[
        "Dabnica"
    ],
    "name:hun_x_preferred":[
        "Dabnica"
    ],
    "name:ind_x_preferred":[
        "Dabnica"
    ],
    "name:isl_x_preferred":[
        "Dabnica"
    ],
    "name:ita_x_preferred":[
        "Dabnica"
    ],
    "name:ltz_x_preferred":[
        "Dabnica"
    ],
    "name:min_x_preferred":[
        "Dabnica"
    ],
    "name:mkd_x_preferred":[
        "\u0414\u0430\u0431\u043d\u0438\u0446\u0430"
    ],
    "name:msa_x_preferred":[
        "Dabnica"
    ],
    "name:nan_x_preferred":[
        "Dabnitsa"
    ],
    "name:nds_x_preferred":[
        "Dabnica"
    ],
    "name:nld_x_preferred":[
        "Dabnica"
    ],
    "name:nno_x_preferred":[
        "Dabnica"
    ],
    "name:nob_x_preferred":[
        "Dabnica"
    ],
    "name:pol_x_preferred":[
        "Dabnica"
    ],
    "name:por_x_preferred":[
        "Dabnica"
    ],
    "name:ron_x_preferred":[
        "Dabnica"
    ],
    "name:slk_x_preferred":[
        "Dabnica"
    ],
    "name:slv_x_preferred":[
        "Dabnica"
    ],
    "name:spa_x_preferred":[
        "Dabnica"
    ],
    "name:sqi_x_preferred":[
        "Dabnica"
    ],
    "name:srp_x_preferred":[
        "\u0414\u0430\u0431\u043d\u0438\u0446\u0430"
    ],
    "name:swe_x_preferred":[
        "Dabnica"
    ],
    "qs:name":"Dabnica",
    "qs:photos_9r":0,
    "qs:photos_sr":0,
    "qs:pop_sr":"1",
    "wd:wordcount":41,
    "wof:name":"Dabnica",
    "wof:placetype":"locality",
    "wof:population":17
},
  "geometry": {"coordinates":[21.56583,41.39806],"type":"Point"}
}