{
  "type": "Feature",
  "properties": {
    "gn:admin1_code":"83",
    "gn:asciiname":"Neokazi",
    "gn:country_code":"MK",
    "gn:dem":454,
    "gn:feature_class":"P",
    "gn:feature_code":"PPL",
    "gn:name":"Neokazi",
    "gn:population":0,
    "gn:timezone":"Europe/Skopje",
    "iso:country":"MK",
    "name:mkd_x_preferred":[
        "Neokazi"
    ],
    "name:mkd_x_variant":[
        "\u041d\u0435\u043e\u043a\u0430\u0437\u0438"
    ],
    "wof:name":"Neokazi",
    "wof:placetype":"locality"
},
  "geometry": {"coordinates":[22.19167,41.96139],"type":"Point"}
}