{
  "type": "Feature",
  "properties": {
    "gn:admin1_code":"85",
    "gn:asciiname":"Curkovci",
    "gn:country_code":"MK",
    "gn:dem":702,
    "gn:feature_class":"P",
    "gn:feature_code":"PPL",
    "gn:name":"\u010curkovci",
    "gn:population":0,
    "gn:timezone":"Europe/Skopje",
    "iso:country":"MK",
    "name:mkd_x_preferred":[
        "\u010curkovci"
    ],
    "name:mkd_x_variant":[
        "\u0427\u0443\u0440\u043a\u043e\u0432\u0446\u0438"
    ],
    "wof:name":"Curkovci",
    "wof:placetype":"locality"
},
  "geometry": {"coordinates":[22.2012,42.20026],"type":"Point"}
}