{
  "type": "Feature",
  "properties": {
    "gn:admin1_code":"62",
    "gn:asciiname":"Cvetanska Maala",
    "gn:country_code":"MK",
    "gn:dem":1092,
    "gn:feature_class":"P",
    "gn:feature_code":"PPL",
    "gn:name":"Cvetanska Maala",
    "gn:population":0,
    "gn:timezone":"Europe/Skopje",
    "iso:country":"MK",
    "name:mkd_x_preferred":[
        "Cvetanska Maala"
    ],
    "name:mkd_x_variant":[
        "\u0426\u0432\u0435\u0442\u0430\u043d\u0441\u043a\u0430 \u041c\u0430\u0430\u043b\u0430"
    ],
    "wof:name":"Cvetanska Maala",
    "wof:placetype":"locality"
},
  "geometry": {"coordinates":[22.50468,42.06225],"type":"Point"}
}