{
  "type": "Feature",
  "properties": {
    "gn:admin1_code":"D7",
    "gn:asciiname":"Kacarovci",
    "gn:country_code":"MK",
    "gn:dem":404,
    "gn:feature_class":"P",
    "gn:feature_code":"PPL",
    "gn:name":"Ka\u010darovci",
    "gn:population":0,
    "gn:timezone":"Europe/Skopje",
    "iso:country":"MK",
    "name:mkd_x_preferred":[
        "Ka\u010darovci"
    ],
    "name:mkd_x_variant":[
        "\u041a\u0430\u0447\u0430\u0440\u043e\u0432\u0446\u0438"
    ],
    "wof:name":"Kacarovci",
    "wof:placetype":"locality"
},
  "geometry": {"coordinates":[21.93595,42.11971],"type":"Point"}
}