{
  "type": "Feature",
  "properties": {
    "gn:admin1_code":"43",
    "gn:asciiname":"Dolno Strogomiste",
    "gn:country_code":"MK",
    "gn:dem":756,
    "gn:feature_class":"P",
    "gn:feature_code":"PPL",
    "gn:name":"Dolno Strogomi\u0161te",
    "gn:population":0,
    "gn:timezone":"Europe/Skopje",
    "iso:country":"MK",
    "name:mkd_x_preferred":[
        "\u0414\u043e\u043b\u043d\u043e \u0421\u0442\u0440\u043e\u0433\u043e\u043c\u0438\u0448\u0442\u0435"
    ],
    "name:mkd_x_variant":[
        "Dolno Stragomi\u0161te",
        "Dolno Strogomi\u0161ta",
        "\u0414\u043e\u043b\u043d\u043e \u0421\u0442\u0440\u043e\u0433\u043e\u043c\u0438\u0448\u0442\u0430"
    ],
    "name:und_x_variant":[
        "Dolno Strogomi\u0161te",
        "Dolno Stragoli\u0161te",
        "Dolna Strogomi\u0161ta"
    ],
    "wof:name":"Dolno Strogomiste",
    "wof:placetype":"locality"
},
  "geometry": {"coordinates":[20.97306,41.59278],"type":"Point"}
}