{
  "type": "Feature",
  "properties": {
    "gn:country":"MK",
    "gn:fcode":"PPL",
    "gn:pop":34,
    "iso:country":"MK",
    "name:mkd_x_preferred":[
        "Armatu\u0161"
    ],
    "name:mkd_x_variant":[
        "\u0410\u0440\u043c\u0430\u0442\u0443\u0448"
    ],
    "qs:name":"Armatu\u0161",
    "qs:photos_9r":0,
    "qs:photos_sr":0,
    "qs:pop_sr":"1",
    "wd:wordcount":133,
    "wof:name":"Armatu\u0161",
    "wof:placetype":"locality",
    "wof:population":34
},
  "geometry": {"coordinates":[21.52667,41.09694],"type":"Point"}
}