{
  "type": "Feature",
  "properties": {
    "gn:country":"MK",
    "gn:fcode":"PPL",
    "gn:population":34,
    "iso:country":"MK",
    "name:bul_x_preferred":[
        "\u041d\u043e\u0432\u0430\u0446\u0438"
    ],
    "name:ceb_x_preferred":[
        "Novaci"
    ],
    "name:deu_x_preferred":[
        "Op\u0161tina Novaci"
    ],
    "name:ell_x_preferred":[
        "\u0394\u03ae\u03bc\u03bf\u03c2 \u039d\u03cc\u03b2\u03b1\u03c4\u03c3\u03b9"
    ],
    "name:eng_x_preferred":[
        "Novaci Municipality"
    ],
    "name:fra_x_preferred":[
        "Novatsi"
    ],
    "name:hrv_x_preferred":[
        "Op\u0107ina Novaci"
    ],
    "name:ind_x_preferred":[
        "Munisipalitas Novaci"
    ],
    "name:ita_x_preferred":[
        "Novaci"
    ],
    "name:jpn_x_preferred":[
        "\u30ce\u30f4\u30a1\u30c4\u30a3"
    ],
    "name:kat_x_preferred":[
        "\u10dc\u10dd\u10d5\u10d0\u10ea\u10d8\u10e1 \u10d7\u10d4\u10db\u10d8"
    ],
    "name:kor_x_preferred":[
        "\ub178\ubc14\uce58 \uc2dc"
    ],
    "name:mkd_x_preferred":[
        "Armatu\u0161"
    ],
    "name:mkd_x_variant":[
        "\u0410\u0440\u043c\u0430\u0442\u0443\u0448",
        "\u041e\u043f\u0448\u0442\u0438\u043d\u0430 \u041d\u043e\u0432\u0430\u0446\u0438"
    ],
    "name:nan_x_preferred":[
        "Novatsi"
    ],
    "name:nld_x_preferred":[
        "Novaci"
    ],
    "name:rus_x_preferred":[
        "\u041d\u043e\u0432\u0430\u0446\u0438"
    ],
    "name:srp_x_preferred":[
        "\u041e\u043f\u0448\u0442\u0438\u043d\u0430 \u041d\u043e\u0432\u0430\u0446\u0438"
    ],
    "name:swe_x_preferred":[
        "Novaci"
    ],
    "name:tgk_x_preferred":[
        "\u0412\u0438\u043b\u043e\u044f\u0442\u0438 \u041d\u043e\u0432\u0430\u0442\u0441\u0438"
    ],
    "name:ukr_x_preferred":[
        "\u041d\u043e\u0432\u0430\u0446\u0456"
    ],
    "name:urd_x_preferred":[
        "\u0646\u0648\u0627\u062a\u0633\u06cc \u0628\u0644\u062f\u06cc\u06c1"
    ],
    "name:zho_x_preferred":[
        "\u8afe\u74e6\u6fdf\u5340"
    ],
    "qs:name":"Armatu\u0161",
    "qs:photos_9r":0,
    "qs:photos_sr":0,
    "qs:pop_sr":"1",
    "wd:wordcount":133,
    "wof:name":"Armatu\u0161",
    "wof:placetype":"locality",
    "wof:population":34
},
  "geometry": {"coordinates":[21.52667,41.09694],"type":"Point"}
}