{
  "type": "Feature",
  "properties": {
    "gn:admin1_code":"22",
    "gn:asciiname":"Nov Istevnik",
    "gn:country_code":"MK",
    "gn:dem":848,
    "gn:feature_class":"P",
    "gn:feature_code":"PPLL",
    "gn:name":"Nov Istevnik",
    "gn:population":0,
    "gn:timezone":"Europe/Skopje",
    "iso:country":"MK",
    "name:mkd_x_preferred":[
        "Nov Istevnik"
    ],
    "name:mkd_x_variant":[
        "\u041d\u043e\u0432 \u0418\u0441\u0442\u0435\u0432\u043d\u0438\u043a"
    ],
    "wof:name":"Nov Istevnik",
    "wof:placetype":"locality"
},
  "geometry": {"coordinates":[22.82306,41.84959],"type":"Point"}
}