{
  "type": "Feature",
  "properties": {
    "gn:admin1_code":"22",
    "gn:asciiname":"Trabotiviste",
    "gn:country_code":"MK",
    "gn:dem":652,
    "gn:feature_class":"P",
    "gn:feature_code":"PPL",
    "gn:name":"Trabotivi\u0161te",
    "gn:population":0,
    "gn:timezone":"Europe/Skopje",
    "iso:country":"MK",
    "name:mkd_x_preferred":[
        "\u0422\u0440\u0430\u0431\u043e\u0442\u0438\u0432\u0438\u0448\u0442\u0435"
    ],
    "name:und_x_variant":[
        "Trabotovi\u0161te",
        "Trebotivi\u0161te",
        "Trabotivi\u0161te"
    ],
    "wof:name":"Trabotiviste",
    "wof:placetype":"locality"
},
  "geometry": {"coordinates":[22.81518,41.89072],"type":"Point"}
}