{
  "type": "Feature",
  "properties": {
    "gn:admin1_code":"06",
    "gn:asciiname":"Ramna",
    "gn:country_code":"MK",
    "gn:dem":802,
    "gn:feature_class":"P",
    "gn:feature_code":"PPL",
    "gn:name":"Ramna",
    "gn:population":0,
    "gn:timezone":"Europe/Skopje",
    "iso:country":"MK",
    "name:mkd_x_preferred":[
        "Ramna"
    ],
    "name:mkd_x_variant":[
        "\u0420\u0430\u043c\u043d\u0430"
    ],
    "wof:name":"Ramna",
    "wof:placetype":"locality"
},
  "geometry": {"coordinates":[21.18583,41.09],"type":"Point"}
}