{
  "type": "Feature",
  "properties": {
    "gn:admin1_code":"E6",
    "gn:asciiname":"Brcevo",
    "gn:country_code":"MK",
    "gn:dem":957,
    "gn:feature_class":"P",
    "gn:feature_code":"PPL",
    "gn:name":"Br\u010devo",
    "gn:population":0,
    "gn:timezone":"Europe/Skopje",
    "iso:country":"MK",
    "name:bul_x_preferred":[
        "\u0411\u044a\u0440\u0447\u0435\u0432\u043e"
    ],
    "name:fra_x_preferred":[
        "Brtchevo"
    ],
    "name:hun_x_preferred":[
        "Brcsevo"
    ],
    "name:mkd_x_preferred":[
        "\u0411\u0440\u0447\u0435\u0432\u043e"
    ],
    "name:por_x_preferred":[
        "Br\u010devo"
    ],
    "name:sqi_x_preferred":[
        "B\u00ebr\u00e7eva"
    ],
    "name:srp_x_preferred":[
        "\u0411\u0440\u0447\u0435\u0432\u043e"
    ],
    "wof:name":"Brcevo",
    "wof:placetype":"locality"
},
  "geometry": {"coordinates":[20.67284,41.29769],"type":"Point"}
}