{
  "type": "Feature",
  "properties": {
    "gn:admin1_code":"20",
    "gn:asciiname":"Muriz",
    "gn:country_code":"MK",
    "gn:dem":1136,
    "gn:feature_class":"P",
    "gn:feature_code":"PPL",
    "gn:name":"Muriz",
    "gn:population":0,
    "gn:timezone":"Europe/Skopje",
    "iso:country":"MK",
    "name:mkd_x_preferred":[
        "Muriz"
    ],
    "name:mkd_x_variant":[
        "\u041c\u0443\u0440\u0438\u0437"
    ],
    "wof:name":"Muriz",
    "wof:placetype":"locality"
},
  "geometry": {"coordinates":[21.47868,42.22261],"type":"Point"}
}