{
  "type": "Feature",
  "properties": {
    "gn:admin1_code":"22",
    "gn:asciiname":"Gaovska Maala",
    "gn:country_code":"MK",
    "gn:dem":955,
    "gn:feature_class":"P",
    "gn:feature_code":"PPL",
    "gn:name":"Gaovska Maala",
    "gn:population":0,
    "gn:timezone":"Europe/Skopje",
    "iso:country":"MK",
    "name:mkd_x_preferred":[
        "Gaovska Maala"
    ],
    "name:mkd_x_variant":[
        "\u0413\u0430\u043e\u0432\u0441\u043a\u0430 \u041c\u0430\u0430\u043b\u0430"
    ],
    "wof:name":"Gaovska Maala",
    "wof:placetype":"locality"
},
  "geometry": {"coordinates":[22.66563,42.05454],"type":"Point"}
}