{
  "type": "Feature",
  "properties": {
    "gn:admin1_code":"62",
    "gn:asciiname":"Ognjanci",
    "gn:country_code":"MK",
    "gn:dem":824,
    "gn:feature_class":"P",
    "gn:feature_code":"PPL",
    "gn:name":"Ognjanci",
    "gn:population":0,
    "gn:timezone":"Europe/Skopje",
    "iso:country":"MK",
    "name:bul_x_preferred":[
        "\u041e\u0433\u043d\u044f\u043d\u0446\u0438"
    ],
    "name:ceb_x_preferred":[
        "Ognjaci"
    ],
    "name:fra_x_preferred":[
        "Ognyantsi"
    ],
    "name:mkd_x_preferred":[
        "Ognjanci"
    ],
    "name:mkd_x_variant":[
        "\u041e\u0433\u045a\u0430\u043d\u0446\u0438"
    ],
    "name:sqi_x_preferred":[
        "Ogjanca"
    ],
    "name:srp_x_preferred":[
        "\u041e\u0433\u045a\u0430\u043d\u0446\u0438"
    ],
    "name:swe_x_preferred":[
        "Ognjanci"
    ],
    "wof:name":"Ognjanci",
    "wof:placetype":"locality"
},
  "geometry": {"coordinates":[22.56281,42.04318],"type":"Point"}
}