{
  "type": "Feature",
  "properties": {
    "gn:admin1_code":"62",
    "gn:asciiname":"Ognjanci",
    "gn:country_code":"MK",
    "gn:dem":824,
    "gn:feature_class":"P",
    "gn:feature_code":"PPL",
    "gn:name":"Ognjanci",
    "gn:population":0,
    "gn:timezone":"Europe/Skopje",
    "iso:country":"MK",
    "name:mkd_x_preferred":[
        "Ognjanci"
    ],
    "name:mkd_x_variant":[
        "\u041e\u0433\u045a\u0430\u043d\u0446\u0438"
    ],
    "wof:name":"Ognjanci",
    "wof:placetype":"locality"
},
  "geometry": {"coordinates":[22.56281,42.04318],"type":"Point"}
}