{
  "type": "Feature",
  "properties": {
    "gn:country":"MK",
    "gn:fcode":"PPLA",
    "gn:pop":50974,
    "iso:country":"MK",
    "name:ara_x_preferred":[
        "\u063a\u0648\u0633\u062a\u064a\u0641\u0627\u0631"
    ],
    "name:bul_x_preferred":[
        "\u0413\u043e\u0441\u0442\u0438\u0432\u0430\u0440"
    ],
    "name:chu_x_preferred":[
        "\u0413\u043e\u0441\u0442\u0438\u0432\u0430\u0440\u0484\u044c"
    ],
    "name:dan_x_preferred":[
        "Gostivar"
    ],
    "name:deu_x_preferred":[
        "Gostivar"
    ],
    "name:ell_x_preferred":[
        "\u0393\u03ba\u03cc\u03c3\u03c4\u03b9\u03b2\u03b1\u03c1"
    ],
    "name:eng_x_preferred":[
        "Gostivar"
    ],
    "name:fas_x_preferred":[
        "\u06af\u0634\u062a\u06cc\u0641\u0627\u0631"
    ],
    "name:hbs_x_preferred":[
        "Gostivar"
    ],
    "name:heb_x_preferred":[
        "\u05d2\u05d5\u05e1\u05d8\u05d9\u05d1\u05e8"
    ],
    "name:hsb_x_preferred":[
        "Gostivar"
    ],
    "name:hun_x_preferred":[
        "Gosztivar"
    ],
    "name:hye_x_preferred":[
        "\u0533\u0578\u057d\u057f\u056b\u057e\u0561\u0580"
    ],
    "name:jpn_x_preferred":[
        "\u30b4\u30b9\u30c6\u30a3\u30f4\u30a1\u30eb"
    ],
    "name:kat_x_preferred":[
        "\u10d2\u10dd\u10e1\u10e2\u10d8\u10d5\u10d0\u10e0\u10d8"
    ],
    "name:kor_x_preferred":[
        "\uace0\uc2a4\ud2f0\ubc14\ub974"
    ],
    "name:lav_x_preferred":[
        "Gostivara"
    ],
    "name:lit_x_preferred":[
        "Gostivaras"
    ],
    "name:mkd_x_preferred":[
        "\u0413\u043e\u0441\u0442\u0438\u0432\u0430\u0440"
    ],
    "name:nld_x_preferred":[
        "Gostivar"
    ],
    "name:pol_x_preferred":[
        "Gostiwar"
    ],
    "name:rus_x_preferred":[
        "\u0413\u043e\u0441\u0442\u0438\u0432\u0430\u0440"
    ],
    "name:sqi_x_preferred":[
        "Gostivari"
    ],
    "name:srp_x_preferred":[
        "\u0413\u043e\u0441\u0442\u0438\u0432\u0430\u0440"
    ],
    "name:swe_x_preferred":[
        "Gostivar"
    ],
    "name:ukr_x_preferred":[
        "\u0413\u043e\u0441\u0442\u0438\u0432\u0430\u0440"
    ],
    "name:unk_x_variant":[
        "Kostovon"
    ],
    "name:zho_x_preferred":[
        "\u6208\u65af\u8482\u74e6\u5c14"
    ],
    "qs:name":"Gostivar",
    "qs:name_adm0":"Macedonia",
    "qs:name_adm1":"Gostivar",
    "qs:photos":50,
    "qs:photos_1k":10,
    "qs:photos_9k":1,
    "qs:photos_9r":2,
    "qs:photos_all":50,
    "qs:photos_sr":2,
    "qs:placetype":"Town",
    "qs:pop_sr":"8",
    "wd:wordcount":1221,
    "wof:name":"Gostivar",
    "wof:placetype":"locality",
    "wof:population":50974
},
  "geometry": {"coordinates":[20.90833,41.79722],"type":"Point"}
}