{
  "type": "Feature",
  "properties": {
    "gn:admin1_code":"33",
    "gn:asciiname":"Petrovo",
    "gn:country_code":"MK",
    "gn:dem":342,
    "gn:feature_class":"P",
    "gn:feature_code":"PPL",
    "gn:name":"Petrovo",
    "gn:population":0,
    "gn:timezone":"Europe/Skopje",
    "iso:country":"MK",
    "name:mkd_x_preferred":[
        "Petrovo"
    ],
    "name:mkd_x_variant":[
        "\u041f\u0435\u0442\u0440\u043e\u0432\u043e"
    ],
    "wof:name":"Petrovo",
    "wof:placetype":"locality"
},
  "geometry": {"coordinates":[22.38321,41.29489],"type":"Point"}
}