{
  "type": "Feature",
  "properties": {
    "gn:admin1_code":"D4",
    "gn:asciiname":"Beloviste",
    "gn:country_code":"MK",
    "gn:dem":553,
    "gn:feature_class":"P",
    "gn:feature_code":"PPL",
    "gn:name":"Belovi\u0161te",
    "gn:population":0,
    "gn:timezone":"Europe/Skopje",
    "iso:country":"MK",
    "name:mkd_x_preferred":[
        "\u0411\u0435\u043b\u043e\u0432\u0438\u0448\u0442\u0435"
    ],
    "name:und_x_variant":[
        "Velike-Tur\u010dane",
        "Belovi\u0161te"
    ],
    "wof:name":"Beloviste",
    "wof:placetype":"locality"
},
  "geometry": {"coordinates":[20.93243,41.77435],"type":"Point"}
}