{
  "type": "Feature",
  "properties": {
    "gn:admin1_code":"51",
    "gn:asciiname":"Knezevo",
    "gn:country_code":"MK",
    "gn:dem":1012,
    "gn:feature_class":"P",
    "gn:feature_code":"PPLL",
    "gn:name":"Kne\u017eevo",
    "gn:population":0,
    "gn:timezone":"Europe/Skopje",
    "iso:country":"MK",
    "name:mkd_x_preferred":[
        "Kne\u017eevo"
    ],
    "name:mkd_x_variant":[
        "\u041a\u043d\u0435\u0436\u0435\u0432\u043e"
    ],
    "wof:name":"Knezevo",
    "wof:placetype":"locality"
},
  "geometry": {"coordinates":[22.31334,42.11042],"type":"Point"}
}