{
  "type": "Feature",
  "properties": {
    "gn:admin1_code":"83",
    "gn:asciiname":"Pestrsino",
    "gn:country_code":"MK",
    "gn:dem":596,
    "gn:feature_class":"P",
    "gn:feature_code":"PPL",
    "gn:name":"Pestr\u0161ino",
    "gn:population":0,
    "gn:timezone":"Europe/Skopje",
    "iso:country":"MK",
    "name:mkd_x_preferred":[
        "Pestr\u0161ino"
    ],
    "name:mkd_x_variant":[
        "\u041f\u0435\u0441\u0442\u0440\u0448\u0438\u043d\u043e"
    ],
    "wof:name":"Pestrsino",
    "wof:placetype":"locality"
},
  "geometry": {"coordinates":[22.13448,41.90911],"type":"Point"}
}