{
  "type": "Feature",
  "properties": {
    "gn:admin1_code":"04",
    "gn:asciiname":"Curilska Maala",
    "gn:country_code":"MK",
    "gn:dem":887,
    "gn:feature_class":"P",
    "gn:feature_code":"PPL",
    "gn:name":"\u010curilska Maala",
    "gn:population":0,
    "gn:timezone":"Europe/Skopje",
    "iso:country":"MK",
    "name:mkd_x_preferred":[
        "\u010curilska Maala"
    ],
    "name:mkd_x_variant":[
        "\u0427\u0443\u0440\u0438\u043b\u0441\u043a\u0430 \u041c\u0430\u0430\u043b\u0430"
    ],
    "wof:name":"Curilska Maala",
    "wof:placetype":"locality"
},
  "geometry": {"coordinates":[22.92639,41.58681],"type":"Point"}
}