{
  "type": "Feature",
  "properties": {
    "gn:country":"MK",
    "gn:fcode":"PPL",
    "gn:pop":2234,
    "iso:country":"MK",
    "name:bul_x_preferred":[
        "\u041b\u043e\u044f\u043d\u0435"
    ],
    "name:deu_x_preferred":[
        "Lojane"
    ],
    "name:eng_x_preferred":[
        "Lojane"
    ],
    "name:fra_x_preferred":[
        "Loyan\u00e9"
    ],
    "name:mkd_x_preferred":[
        "\u041b\u043e\u0458\u0430\u043d\u0435"
    ],
    "name:nld_x_preferred":[
        "Lojane"
    ],
    "name:sqi_x_preferred":[
        "Llojani"
    ],
    "name:srp_x_preferred":[
        "\u041b\u043e\u0458\u0430\u043d\u0435"
    ],
    "name:swe_x_preferred":[
        "Lojane"
    ],
    "name:ukr_x_preferred":[
        "\u041b\u043e\u044f\u043d\u0435"
    ],
    "name:unk_x_variant":[
        "Llojan"
    ],
    "qs:name":"Lojane",
    "qs:photos_9r":0,
    "qs:photos_sr":0,
    "qs:pop_sr":"4",
    "wd:elevation":437.0,
    "wd:wordcount":185,
    "wof:name":"Lojane",
    "wof:placetype":"locality",
    "wof:population":2234
},
  "geometry": {"coordinates":[21.665,42.23333],"type":"Point"}
}